Workbook
Name RICK_and_MORTY_BAD_TRIP: #REF!
Name RICK_and_MORTY_BAD_ACID: #REF!

Sheet Лист1
A1: Номер | B1: Дата | C1: Время | D1: Позиция | E1: Коменты | F1: Скидка | G1: Чистый заработок за день | H1: Выручка | I1: Розничная цена | J1: Закупочная цена | K1: Прибыль с единицы
A4: 1 | B4: 45951 | C4: 0.57466435 | D4: RICK and MORTY BAD ACID | G4: =SUM(K4:K63) -> 269.2 | H4: =SUM(J4:K63) -> 622 | I4: {=IF(D4="","",INDEX('Товары '!$D$2:$D$78, MATCH(D4, 'Товары '!$B$2:$B$78, 0)))} -> 15 | J4: =IF(D4="","",VLOOKUP(D4, 'Товары '!$B$2:$C$78, 2, FALSE)) -> 9 | K4: =IF(OR(I4="", J4=""), "", VALUE(I4) - VALUE(J4))-F4 -> 6
A5: 2 | B5: 45951 | C5: 0.57469907 | D5: Катриджи Vaporesso XROS | I5: {=IF(D5="","",INDEX('Товары '!$D$2:$D$78, MATCH(D5, 'Товары '!$B$2:$B$78, 0)))} -> 13 | J5: =IF(D5="","",VLOOKUP(D5, 'Товары '!$B$2:$C$78, 2, FALSE)) -> 6.4 | K5: =IF(OR(I5="", J5=""), "", VALUE(I5) - VALUE(J5))-F5 -> 6.6
A6: 3 | B6: 45951 | C6: 0.57991898 | D6: Катриджи Vaporesso XROS | I6: {=IF(D6="","",INDEX('Товары '!$D$2:$D$78, MATCH(D6, 'Товары '!$B$2:$B$78, 0)))} -> 13 | J6: =IF(D6="","",VLOOKUP(D6, 'Товары '!$B$2:$C$78, 2, FALSE)) -> 6.4 | K6: =IF(OR(I6="", J6=""), "", VALUE(I6) - VALUE(J6))-F6 -> 6.6
A7: 4 | B7: 45951 | C7: 0.5843287 | D7: Xros 5 мини | I7: {=IF(D7="","",INDEX('Товары '!$D$2:$D$78, MATCH(D7, 'Товары '!$B$2:$B$78, 0)))} -> 70 | J7: =IF(D7="","",VLOOKUP(D7, 'Товары '!$B$2:$C$78, 2, FALSE)) -> 40 | K7: =IF(OR(I7="", J7=""), "", VALUE(I7) - VALUE(J7))-F7 -> 30
A8: 5 | B8: 45951 | C8: 0.58443287 | D8: CATSWILL (кислые | I8: {=IF(D8="","",INDEX('Товары '!$D$2:$D$78, MATCH(D8, 'Товары '!$B$2:$B$78, 0)))} -> 15 | J8: =IF(D8="","",VLOOKUP(D8, 'Товары '!$B$2:$C$78, 2, FALSE)) -> 9 | K8: =IF(OR(I8="", J8=""), "", VALUE(I8) - VALUE(J8))-F8 -> 6
A9: 6 | B9: 45951 | C9: 0.59041667 | D9: Катриджи Vaporesso XROS | I9: {=IF(D9="","",INDEX('Товары '!$D$2:$D$78, MATCH(D9, 'Товары '!$B$2:$B$78, 0)))} -> 13 | J9: =IF(D9="","",VLOOKUP(D9, 'Товары '!$B$2:$C$78, 2, FALSE)) -> 6.4 | K9: =IF(OR(I9="", J9=""), "", VALUE(I9) - VALUE(J9))-F9 -> 6.6
A10: 7 | B10: 45951 | C10: 0.59288194 | D10: RICK and MORTY BAD TRIP | I10: {=IF(D10="","",INDEX('Товары '!$D$2:$D$78, MATCH(D10, 'Товары '!$B$2:$B$78, 0)))} -> 15 | J10: =IF(D10="","",VLOOKUP(D10, 'Товары '!$B$2:$C$78, 2, FALSE)) -> 9 | K10: =IF(OR(I10="", J10=""), "", VALUE(I10) - VALUE(J10))-F10 -> 6
A11: 8 | B11: 45951 | C11: 0.59491898 | D11: RICK and MORTY BAD TRIP | I11: {=IF(D11="","",INDEX('Товары '!$D$2:$D$78, MATCH(D11, 'Товары '!$B$2:$B$78, 0)))} -> 15 | J11: =IF(D11="","",VLOOKUP(D11, 'Товары '!$B$2:$C$78, 2, FALSE)) -> 9 | K11: =IF(OR(I11="", J11=""), "", VALUE(I11) - VALUE(J11))-F11 -> 6
A12: 9 | B12: 45951 | D12: Катриджи Vaporesso XROS | I12: {=IF(D12="","",INDEX('Товары '!$D$2:$D$78, MATCH(D12, 'Товары '!$B$2:$B$78, 0)))} -> 13 | J12: =IF(D12="","",VLOOKUP(D12, 'Товары '!$B$2:$C$78, 2, FALSE)) -> 6.4 | K12: =IF(OR(I12="", J12=""), "", VALUE(I12) - VALUE(J12))-F12 -> 6.6
A13: 10 | B13: 45951 | D13: Катриджи Vaporesso XROS | F13: 1 | I13: {=IF(D13="","",INDEX('Товары '!$D$2:$D$78, MATCH(D13, 'Товары '!$B$2:$B$78, 0)))} -> 13 | J13: =IF(D13="","",VLOOKUP(D13, 'Товары '!$B$2:$C$78, 2, FALSE)) -> 6.4 | K13: =IF(OR(I13="", J13=""), "", VALUE(I13) - VALUE(J13))-F13 -> 5.6
A14: 11 | B14: 45951 | C14: 0.61070602 | D14: PODONKI LAST HAP | I14: {=IF(D14="","",INDEX('Товары '!$D$2:$D$78, MATCH(D14, 'Товары '!$B$2:$B$78, 0)))} -> 15 | J14: =IF(D14="","",VLOOKUP(D14, 'Товары '!$B$2:$C$78, 2, FALSE)) -> 8.5 | K14: =IF(OR(I14="", J14=""), "", VALUE(I14) - VALUE(J14))-F14 -> 6.5
A15: 12 | B15: 45951 | C15: 0.61423611 | D15: Катриджи Vaporesso XROS | I15: {=IF(D15="","",INDEX('Товары '!$D$2:$D$78, MATCH(D15, 'Товары '!$B$2:$B$78, 0)))} -> 13 | J15: =IF(D15="","",VLOOKUP(D15, 'Товары '!$B$2:$C$78, 2, FALSE)) -> 6.4 | K15: =IF(OR(I15="", J15=""), "", VALUE(I15) - VALUE(J15))-F15 -> 6.6
A16: 13 | B16: 45951 | C16: 0.64548611 | D16: CATSWILL (кислые | I16: {=IF(D16="","",INDEX('Товары '!$D$2:$D$78, MATCH(D16, 'Товары '!$B$2:$B$78, 0)))} -> 15 | J16: =IF(D16="","",VLOOKUP(D16, 'Товары '!$B$2:$C$78, 2, FALSE)) -> 9 | K16: =IF(OR(I16="", J16=""), "", VALUE(I16) - VALUE(J16))-F16 -> 6
A17: 14 | B17: 45951 | C17: 0.67211806 | D17: Катриджи Vaporesso XROS | I17: {=IF(D17="","",INDEX('Товары '!$D$2:$D$78, MATCH(D17, 'Товары '!$B$2:$B$78, 0)))} -> 13 | J17: =IF(D17="","",VLOOKUP(D17, 'Товары '!$B$2:$C$78, 2, FALSE)) -> 6.4 | K17: =IF(OR(I17="", J17=""), "", VALUE(I17) - VALUE(J17))-F17 -> 6.6
A18: 15 | B18: 45951 | C18: 0.70815972 | D18: Катриджи Vaporesso XROS | I18: {=IF(D18="","",INDEX('Товары '!$D$2:$D$78, MATCH(D18, 'Товары '!$B$2:$B$78, 0)))} -> 13 | J18: =IF(D18="","",VLOOKUP(D18, 'Товары '!$B$2:$C$78, 2, FALSE)) -> 6.4 | K18: =IF(OR(I18="", J18=""), "", VALUE(I18) - VALUE(J18))-F18 -> 6.6
A19: 16 | B19: 45951 | C19: 0.7081713 | D19: RICK AND MORTY BAD ICE | I19: {=IF(D19="","",INDEX('Товары '!$D$2:$D$78, MATCH(D19, 'Товары '!$B$2:$B$78, 0)))} -> 15 | J19: =IF(D19="","",VLOOKUP(D19, 'Товары '!$B$2:$C$78, 2, FALSE)) -> 9 | K19: =IF(OR(I19="", J19=""), "", VALUE(I19) - VALUE(J19))-F19 -> 6
A20: 17 | B20: 45951 | C20: 0.7359375 | D20: RICK and MORTY BAD TRIP | I20: {=IF(D20="","",INDEX('Товары '!$D$2:$D$78, MATCH(D20, 'Товары '!$B$2:$B$78, 0)))} -> 15 | J20: =IF(D20="","",VLOOKUP(D20, 'Товары '!$B$2:$C$78, 2, FALSE)) -> 9 | K20: =IF(OR(I20="", J20=""), "", VALUE(I20) - VALUE(J20))-F20 -> 6
A21: 18 | B21: 45951 | C21: 0.73615741 | D21: Podonk Critical | I21: {=IF(D21="","",INDEX('Товары '!$D$2:$D$78, MATCH(D21, 'Товары '!$B$2:$B$78, 0)))} -> 15 | J21: =IF(D21="","",VLOOKUP(D21, 'Товары '!$B$2:$C$78, 2, FALSE)) -> 8 | K21: =IF(OR(I21="", J21=""), "", VALUE(I21) - VALUE(J21))-F21 -> 7
A22: 19 | B22: 45951 | C22: 0.74640046 | D22: RICK and MORTY BAD TRIP | I22: {=IF(D22="","",INDEX('Товары '!$D$2:$D$78, MATCH(D22, 'Товары '!$B$2:$B$78, 0)))} -> 15 | J22: =IF(D22="","",VLOOKUP(D22, 'Товары '!$B$2:$C$78, 2, FALSE)) -> 9 | K22: =IF(OR(I22="", J22=""), "", VALUE(I22) - VALUE(J22))-F22 -> 6
A23: 20 | B23: 45951 | C23: 0.73841435 | D23: Катриджи Vaporesso XROS | I23: {=IF(D23="","",INDEX('Товары '!$D$2:$D$78, MATCH(D23, 'Товары '!$B$2:$B$78, 0)))} -> 13 | J23: =IF(D23="","",VLOOKUP(D23, 'Товары '!$B$2:$C$78, 2, FALSE)) -> 6.4 | K23: =IF(OR(I23="", J23=""), "", VALUE(I23) - VALUE(J23))-F23 -> 6.6
A24: 21 | B24: 45951 | C24: 0.73872685 | D24: Geek vape | I24: {=IF(D24="","",INDEX('Товары '!$D$2:$D$78, MATCH(D24, 'Товары '!$B$2:$B$78, 0)))} -> 13 | J24: =IF(D24="","",VLOOKUP(D24, 'Товары '!$B$2:$C$78, 2, FALSE)) -> 6.4 | K24: =IF(OR(I24="", J24=""), "", VALUE(I24) - VALUE(J24))-F24 -> 6.6
A25: 22 | B25: 45951 | C25: 0.74519676 | D25: Самоубийца V2 | I25: {=IF(D25="","",INDEX('Товары '!$D$2:$D$78, MATCH(D25, 'Товары '!$B$2:$B$78, 0)))} -> 15 | J25: =IF(D25="","",VLOOKUP(D25, 'Товары '!$B$2:$C$78, 2, FALSE)) -> 9 | K25: =IF(OR(I25="", J25=""), "", VALUE(I25) - VALUE(J25))-F25 -> 6
... A33: 30 | B33: 45951 | C33: 0.79703704 | D33: RICK and MORTY BAD ACID | I33: {=IF(D33="","",INDEX('Товары '!$D$2:$D$78, MATCH(D33, 'Товары '!$B$2:$B$78, 0)))} -> 15 | J33: =IF(D33="","",VLOOKUP(D33, 'Товары '!$B$2:$C$78, 2, FALSE)) -> 9 | K33: =IF(OR(I33="", J33=""), "", VALUE(I33) - VALUE(J33))-F33 -> 6
A34: 31 | B34: 45951 | C34: 0.79894676 | D34: Xros 5 мини | F34: 5 | I34: {=IF(D34="","",INDEX('Товары '!$D$2:$D$78, MATCH(D34, 'Товары '!$B$2:$B$78, 0)))} -> 70 | J34: =IF(D34="","",VLOOKUP(D34, 'Товары '!$B$2:$C$78, 2, FALSE)) -> 40 | K34: =IF(OR(I34="", J34=""), "", VALUE(I34) - VALUE(J34))-F34 -> 25
A35: 32 | B35: 45951 | C35: 0.82726852 | D35: RICK AND MORTY BAD ICE | I35: {=IF(D35="","",INDEX('Товары '!$D$2:$D$78, MATCH(D35, 'Товары '!$B$2:$B$78, 0)))} -> 15 | J35: =IF(D35="","",VLOOKUP(D35, 'Товары '!$B$2:$C$78, 2, FALSE)) -> 9 | K35: =IF(OR(I35="", J35=""), "", VALUE(I35) - VALUE(J35))-F35 -> 6
A36: 33 | B36: 45951 | C36: 0.82726852 | D36: RICK AND MORTY BAD ICE | I36: {=IF(D36="","",INDEX('Товары '!$D$2:$D$78, MATCH(D36, 'Товары '!$B$2:$B$78, 0)))} -> 15 | J36: =IF(D36="","",VLOOKUP(D36, 'Товары '!$B$2:$C$78, 2, FALSE)) -> 9 | K36: =IF(OR(I36="", J36=""), "", VALUE(I36) - VALUE(J36))-F36 -> 6
A37: 34 | B37: 45951 | C37: 0.8621412 | D37: Катриджи Vaporesso XROS | I37: {=IF(D37="","",INDEX('Товары '!$D$2:$D$78, MATCH(D37, 'Товары '!$B$2:$B$78, 0)))} -> 13 | J37: =IF(D37="","",VLOOKUP(D37, 'Товары '!$B$2:$C$78, 2, FALSE)) -> 6.4 | K37: =IF(OR(I37="", J37=""), "", VALUE(I37) - VALUE(J37))-F37 -> 6.6
A38: 35 | B38: 45951 | C38: 0.88949074 | D38: CATSWILL (кислые | I38: {=IF(D38="","",INDEX('Товары '!$D$2:$D$78, MATCH(D38, 'Товары '!$B$2:$B$78, 0)))} -> 15 | J38: =IF(D38="","",VLOOKUP(D38, 'Товары '!$B$2:$C$78, 2, FALSE)) -> 9 | K38: =IF(OR(I38="", J38=""), "", VALUE(I38) - VALUE(J38))-F38 -> 6
A39: 36 | B39: 45951 | C39: 0.88952546 | D39: CATSWILL (кислые | I39: {=IF(D39="","",INDEX('Товары '!$D$2:$D$78, MATCH(D39, 'Товары '!$B$2:$B$78, 0)))} -> 15 | J39: =IF(D39="","",VLOOKUP(D39, 'Товары '!$B$2:$C$78, 2, FALSE)) -> 9 | K39: =IF(OR(I39="", J39=""), "", VALUE(I39) - VALUE(J39))-F39 -> 6
A40: 37 | I40: {=IF(D40="","",INDEX('Товары '!$D$2:$D$78, MATCH(D40, 'Товары '!$B$2:$B$78, 0)))} | J40: =IF(D40="","",VLOOKUP(D40, 'Товары '!$B$2:$C$78, 2, FALSE)) | K40: =IF(OR(I40="", J40=""), "", VALUE(I40) - VALUE(J40))-F40 -> 0
A41: 38 | I41: {=IF(D41="","",INDEX('Товары '!$D$2:$D$78, MATCH(D41, 'Товары '!$B$2:$B$78, 0)))} | J41: =IF(D41="","",VLOOKUP(D41, 'Товары '!$B$2:$C$78, 2, FALSE)) | K41: =IF(OR(I41="", J41=""), "", VALUE(I41) - VALUE(J41))-F41 -> 0
A42: 39 | I42: {=IF(D42="","",INDEX('Товары '!$D$2:$D$78, MATCH(D42, 'Товары '!$B$2:$B$78, 0)))} | J42: =IF(D42="","",VLOOKUP(D42, 'Товары '!$B$2:$C$78, 2, FALSE)) | K42: =IF(OR(I42="", J42=""), "", VALUE(I42) - VALUE(J42))-F42 -> 0
A43: 40 | I43: {=IF(D43="","",INDEX('Товары '!$D$2:$D$78, MATCH(D43, 'Товары '!$B$2:$B$78, 0)))} | J43: =IF(D43="","",VLOOKUP(D43, 'Товары '!$B$2:$C$78, 2, FALSE)) | K43: =IF(OR(I43="", J43=""), "", VALUE(I43) - VALUE(J43))-F43 -> 0
A44: 41 | I44: {=IF(D44="","",INDEX('Товары '!$D$2:$D$78, MATCH(D44, 'Товары '!$B$2:$B$78, 0)))} | J44: =IF(D44="","",VLOOKUP(D44, 'Товары '!$B$2:$C$78, 2, FALSE)) | K44: =IF(OR(I44="", J44=""), "", VALUE(I44) - VALUE(J44))-F44 -> 0
A45: 42 | I45: {=IF(D45="","",INDEX('Товары '!$D$2:$D$78, MATCH(D45, 'Товары '!$B$2:$B$78, 0)))} | J45: =IF(D45="","",VLOOKUP(D45, 'Товары '!$B$2:$C$78, 2, FALSE)) | K45: =IF(OR(I45="", J45=""), "", VALUE(I45) - VALUE(J45))-F45 -> 0
A46: 43 | I46: {=IF(D46="","",INDEX('Товары '!$D$2:$D$78, MATCH(D46, 'Товары '!$B$2:$B$78, 0)))} | J46: =IF(D46="","",VLOOKUP(D46, 'Товары '!$B$2:$C$78, 2, FALSE)) | K46: =IF(OR(I46="", J46=""), "", VALUE(I46) - VALUE(J46))-F46 -> 0
A47: 44 | I47: {=IF(D47="","",INDEX('Товары '!$D$2:$D$78, MATCH(D47, 'Товары '!$B$2:$B$78, 0)))} | J47: =IF(D47="","",VLOOKUP(D47, 'Товары '!$B$2:$C$78, 2, FALSE)) | K47: =IF(OR(I47="", J47=""), "", VALUE(I47) - VALUE(J47))-F47 -> 0
A48: 45 | I48: {=IF(D48="","",INDEX('Товары '!$D$2:$D$78, MATCH(D48, 'Товары '!$B$2:$B$78, 0)))} | J48: =IF(D48="","",VLOOKUP(D48, 'Товары '!$B$2:$C$78, 2, FALSE)) | K48: =IF(OR(I48="", J48=""), "", VALUE(I48) - VALUE(J48))-F48 -> 0
A49: 46 | I49: {=IF(D49="","",INDEX('Товары '!$D$2:$D$78, MATCH(D49, 'Товары '!$B$2:$B$78, 0)))} | J49: =IF(D49="","",VLOOKUP(D49, 'Товары '!$B$2:$C$78, 2, FALSE)) | K49: =IF(OR(I49="", J49=""), "", VALUE(I49) - VALUE(J49))-F49 -> 0
A50: 47 | I50: {=IF(D50="","",INDEX('Товары '!$D$2:$D$78, MATCH(D50, 'Товары '!$B$2:$B$78, 0)))} | J50: =IF(D50="","",VLOOKUP(D50, 'Товары '!$B$2:$C$78, 2, FALSE)) | K50: =IF(OR(I50="", J50=""), "", VALUE(I50) - VALUE(J50))-F50 -> 0
A51: 48 | I51: {=IF(D51="","",INDEX('Товары '!$D$2:$D$78, MATCH(D51, 'Товары '!$B$2:$B$78, 0)))} | J51: =IF(D51="","",VLOOKUP(D51, 'Товары '!$B$2:$C$78, 2, FALSE)) | K51: =IF(OR(I51="", J51=""), "", VALUE(I51) - VALUE(J51))-F51 -> 0
... A63: 60 | I63: {=IF(D63="","",INDEX('Товары '!$D$2:$D$78, MATCH(D63, 'Товары '!$B$2:$B$78, 0)))} | J63: =IF(D63="","",VLOOKUP(D63, 'Товары '!$B$2:$C$78, 2, FALSE)) | K63: =IF(OR(I63="", J63=""), "", VALUE(I63) - VALUE(J63))-F63 -> 0
A64: Номер | B64: Дата | C64: Время | D64: Позиция | E64: Коменты | F64: Скидка | G64: Чистый заработок за день | H64: Выручка | I64: Розничная цена | J64: Закупочная цена | K64: Прибыль с единицы
A67: 1 | B67: 45952 | C67: 0.5772338 | D67: Катриджи Vaporesso XROS | G67: =SUM(K67:K126) -> 167.7 | H67: =SUM(J67:K126) -> 362 | I67: {=IF(D67="","",INDEX('Товары '!$D$2:$D$78, MATCH(D67, 'Товары '!$B$2:$B$78, 0)))} -> 13 | J67: =IF(D67="","",VLOOKUP(D67, 'Товары '!$B$2:$C$78, 2, FALSE)) -> 6.4 | K67: =IF(OR(I67="", J67=""), "", VALUE(I67) - VALUE(J67))-F67 -> 6.6
A68: 2 | B68: 45952 | C68: 0.58103009 | D68: Рик и морти на замерзоне strong | I68: {=IF(D68="","",INDEX('Товары '!$D$2:$D$78, MATCH(D68, 'Товары '!$B$2:$B$78, 0)))} -> 15 | J68: =IF(D68="","",VLOOKUP(D68, 'Товары '!$B$2:$C$78, 2, FALSE)) -> 6.9 | K68: =IF(OR(I68="", J68=""), "", VALUE(I68) - VALUE(J68))-F68 -> 8.1
A69: 3 | B69: 45952 | C69: 0.59349537 | D69: PODONKI Podgon | I69: {=IF(D69="","",INDEX('Товары '!$D$2:$D$78, MATCH(D69, 'Товары '!$B$2:$B$78, 0)))} -> 15 | J69: =IF(D69="","",VLOOKUP(D69, 'Товары '!$B$2:$C$78, 2, FALSE)) -> 6 | K69: =IF(OR(I69="", J69=""), "", VALUE(I69) - VALUE(J69))-F69 -> 9
A70: 4 | B70: 45952 | C70: 0.59364583 | D70: Катриджи Vaporesso XROS | I70: {=IF(D70="","",INDEX('Товары '!$D$2:$D$78, MATCH(D70, 'Товары '!$B$2:$B$78, 0)))} -> 13 | J70: =IF(D70="","",VLOOKUP(D70, 'Товары '!$B$2:$C$78, 2, FALSE)) -> 6.4 | K70: =IF(OR(I70="", J70=""), "", VALUE(I70) - VALUE(J70))-F70 -> 6.6
A71: 5 | B71: 45952 | C71: 0.6221412 | D71: PODONKI Podgon | I71: {=IF(D71="","",INDEX('Товары '!$D$2:$D$78, MATCH(D71, 'Товары '!$B$2:$B$78, 0)))} -> 15 | J71: =IF(D71="","",VLOOKUP(D71, 'Товары '!$B$2:$C$78, 2, FALSE)) -> 6 | K71: =IF(OR(I71="", J71=""), "", VALUE(I71) - VALUE(J71))-F71 -> 9
A72: 6 | B72: 45952 | C72: 0.62518519 | D72: RICK AND MORTY BAD ICE | I72: {=IF(D72="","",INDEX('Товары '!$D$2:$D$78, MATCH(D72, 'Товары '!$B$2:$B$78, 0)))} -> 15 | J72: =IF(D72="","",VLOOKUP(D72, 'Товары '!$B$2:$C$78, 2, FALSE)) -> 9 | K72: =IF(OR(I72="", J72=""), "", VALUE(I72) - VALUE(J72))-F72 -> 6
A73: 7 | B73: 45952 | C73: 0.62555556 | D73: Рик и морти на замерзоне strong | I73: {=IF(D73="","",INDEX('Товары '!$D$2:$D$78, MATCH(D73, 'Товары '!$B$2:$B$78, 0)))} -> 15 | J73: =IF(D73="","",VLOOKUP(D73, 'Товары '!$B$2:$C$78, 2, FALSE)) -> 6.9 | K73: =IF(OR(I73="", J73=""), "", VALUE(I73) - VALUE(J73))-F73 -> 8.1
A74: 8 | B74: 45952 | C74: 0.64361111 | D74: Podonk Critical | I74: {=IF(D74="","",INDEX('Товары '!$D$2:$D$78, MATCH(D74, 'Товары '!$B$2:$B$78, 0)))} -> 15 | J74: =IF(D74="","",VLOOKUP(D74, 'Товары '!$B$2:$C$78, 2, FALSE)) -> 8 | K74: =IF(OR(I74="", J74=""), "", VALUE(I74) - VALUE(J74))-F74 -> 7
A75: 9 | B75: 45952 | C75: 0.67600694 | D75: RICK and MORTY BAD TRIP | I75: {=IF(D75="","",INDEX('Товары '!$D$2:$D$78, MATCH(D75, 'Товары '!$B$2:$B$78, 0)))} -> 15 | J75: =IF(D75="","",VLOOKUP(D75, 'Товары '!$B$2:$C$78, 2, FALSE)) -> 9 | K75: =IF(OR(I75="", J75=""), "", VALUE(I75) - VALUE(J75))-F75 -> 6
A76: 10 | D76: RICK AND MORTY BAD ICE | I76: {=IF(D76="","",INDEX('Товары '!$D$2:$D$78, MATCH(D76, 'Товары '!$B$2:$B$78, 0)))} -> 15 | J76: =IF(D76="","",VLOOKUP(D76, 'Товары '!$B$2:$C$78, 2, FALSE)) -> 9 | K76: =IF(OR(I76="", J76=""), "", VALUE(I76) - VALUE(J76))-F76 -> 6
A77: 11 | B77: 45952 | C77: 0.67708333 | D77: PODONKI Podgon | I77: {=IF(D77="","",INDEX('Товары '!$D$2:$D$78, MATCH(D77, 'Товары '!$B$2:$B$78, 0)))} -> 15 | J77: =IF(D77="","",VLOOKUP(D77, 'Товары '!$B$2:$C$78, 2, FALSE)) -> 6 | K77: =IF(OR(I77="", J77=""), "", VALUE(I77) - VALUE(J77))-F77 -> 9
A78: 12 | B78: 45952 | C78: 0.69994213 | D78: RICK AND MORTY BAD ICE | I78: {=IF(D78="","",INDEX('Товары '!$D$2:$D$78, MATCH(D78, 'Товары '!$B$2:$B$78, 0)))} -> 15 | J78: =IF(D78="","",VLOOKUP(D78, 'Товары '!$B$2:$C$78, 2, FALSE)) -> 9 | K78: =IF(OR(I78="", J78=""), "", VALUE(I78) - VALUE(J78))-F78 -> 6
A79: 13 | D79: CATSWILL (кислые | I79: {=IF(D79="","",INDEX('Товары '!$D$2:$D$78, MATCH(D79, 'Товары '!$B$2:$B$78, 0)))} -> 15 | J79: =IF(D79="","",VLOOKUP(D79, 'Товары '!$B$2:$C$78, 2, FALSE)) -> 9 | K79: =IF(OR(I79="", J79=""), "", VALUE(I79) - VALUE(J79))-F79 -> 6
A80: 14 | B80: 45952 | C80: 0.70383102 | D80: PODONKI Podgon | I80: {=IF(D80="","",INDEX('Товары '!$D$2:$D$78, MATCH(D80, 'Товары '!$B$2:$B$78, 0)))} -> 15 | J80: =IF(D80="","",VLOOKUP(D80, 'Товары '!$B$2:$C$78, 2, FALSE)) -> 6 | K80: =IF(OR(I80="", J80=""), "", VALUE(I80) - VALUE(J80))-F80 -> 9
A81: 15 | D81: Катриджи Vaporesso XROS | I81: {=IF(D81="","",INDEX('Товары '!$D$2:$D$78, MATCH(D81, 'Товары '!$B$2:$B$78, 0)))} -> 13 | J81: =IF(D81="","",VLOOKUP(D81, 'Товары '!$B$2:$C$78, 2, FALSE)) -> 6.4 | K81: =IF(OR(I81="", J81=""), "", VALUE(I81) - VALUE(J81))-F81 -> 6.6
A82: 16 | B82: 45952 | C82: 0.71907407 | D82: Geek vape | I82: {=IF(D82="","",INDEX('Товары '!$D$2:$D$78, MATCH(D82, 'Товары '!$B$2:$B$78, 0)))} -> 13 | J82: =IF(D82="","",VLOOKUP(D82, 'Товары '!$B$2:$C$78, 2, FALSE)) -> 6.4 | K82: =IF(OR(I82="", J82=""), "", VALUE(I82) - VALUE(J82))-F82 -> 6.6
A83: 17 | B83: 45952 | C83: 0.7403588 | D83: Самоубийца V2 | I83: {=IF(D83="","",INDEX('Товары '!$D$2:$D$78, MATCH(D83, 'Товары '!$B$2:$B$78, 0)))} -> 15 | J83: =IF(D83="","",VLOOKUP(D83, 'Товары '!$B$2:$C$78, 2, FALSE)) -> 9 | K83: =IF(OR(I83="", J83=""), "", VALUE(I83) - VALUE(J83))-F83 -> 6
A84: 18 | B84: 45952 | C84: 0.74640046 | D84: RICK AND MORTY BAD ICE | I84: {=IF(D84="","",INDEX('Товары '!$D$2:$D$78, MATCH(D84, 'Товары '!$B$2:$B$78, 0)))} -> 15 | J84: =IF(D84="","",VLOOKUP(D84, 'Товары '!$B$2:$C$78, 2, FALSE)) -> 9 | K84: =IF(OR(I84="", J84=""), "", VALUE(I84) - VALUE(J84))-F84 -> 6
A85: 19 | B85: 45952 | C85: 0.75553241 | D85: PODONKI x ISTERIKA | I85: {=IF(D85="","",INDEX('Товары '!$D$2:$D$78, MATCH(D85, 'Товары '!$B$2:$B$78, 0)))} -> 15 | J85: =IF(D85="","",VLOOKUP(D85, 'Товары '!$B$2:$C$78, 2, FALSE)) -> 8.5 | K85: =IF(OR(I85="", J85=""), "", VALUE(I85) - VALUE(J85))-F85 -> 6.5
A86: 20 | B86: 45952 | C86: 0.77954861 | D86: RICK and MORTY BAD TRIP | I86: {=IF(D86="","",INDEX('Товары '!$D$2:$D$78, MATCH(D86, 'Товары '!$B$2:$B$78, 0)))} -> 15 | J86: =IF(D86="","",VLOOKUP(D86, 'Товары '!$B$2:$C$78, 2, FALSE)) -> 9 | K86: =IF(OR(I86="", J86=""), "", VALUE(I86) - VALUE(J86))-F86 -> 6
A87: 21 | B87: 45952 | C87: 0.79864583 | D87: RICK and MORTY BAD TRIP | I87: {=IF(D87="","",INDEX('Товары '!$D$2:$D$78, MATCH(D87, 'Товары '!$B$2:$B$78, 0)))} -> 15 | J87: =IF(D87="","",VLOOKUP(D87, 'Товары '!$B$2:$C$78, 2, FALSE)) -> 9 | K87: =IF(OR(I87="", J87=""), "", VALUE(I87) - VALUE(J87))-F87 -> 6
A88: 22 | B88: 45952 | C88: 0.79947917 | D88: PODONKI LAST HAP | I88: {=IF(D88="","",INDEX('Товары '!$D$2:$D$78, MATCH(D88, 'Товары '!$B$2:$B$78, 0)))} -> 15 | J88: =IF(D88="","",VLOOKUP(D88, 'Товары '!$B$2:$C$78, 2, FALSE)) -> 8.5 | K88: =IF(OR(I88="", J88=""), "", VALUE(I88) - VALUE(J88))-F88 -> 6.5
A89: 23 | B89: 45952 | C89: 0.82244213 | D89: CATSWILL (кислые | I89: {=IF(D89="","",INDEX('Товары '!$D$2:$D$78, MATCH(D89, 'Товары '!$B$2:$B$78, 0)))} -> 15 | J89: =IF(D89="","",VLOOKUP(D89, 'Товары '!$B$2:$C$78, 2, FALSE)) -> 9 | K89: =IF(OR(I89="", J89=""), "", VALUE(I89) - VALUE(J89))-F89 -> 6
A90: 24 | B90: 45952 | C90: 0.85690972 | D90: RICK and MORTY BAD TRIP | F90: 5 | I90: {=IF(D90="","",INDEX('Товары '!$D$2:$D$78, MATCH(D90, 'Товары '!$B$2:$B$78, 0)))} -> 15 | J90: =IF(D90="","",VLOOKUP(D90, 'Товары '!$B$2:$C$78, 2, FALSE)) -> 9 | K90: =IF(OR(I90="", J90=""), "", VALUE(I90) - VALUE(J90))-F90 -> 1
A91: 25 | B91: 45952 | C91: 0.90927083 | D91: Рик и морти на замерзоне strong | I91: {=IF(D91="","",INDEX('Товары '!$D$2:$D$78, MATCH(D91, 'Товары '!$B$2:$B$78, 0)))} -> 15 | J91: =IF(D91="","",VLOOKUP(D91, 'Товары '!$B$2:$C$78, 2, FALSE)) -> 6.9 | K91: =IF(OR(I91="", J91=""), "", VALUE(I91) - VALUE(J91))-F91 -> 8.1
A92: 26 | I92: {=IF(D92="","",INDEX('Товары '!$D$2:$D$78, MATCH(D92, 'Товары '!$B$2:$B$78, 0)))} | J92: =IF(D92="","",VLOOKUP(D92, 'Товары '!$B$2:$C$78, 2, FALSE)) | K92: =IF(OR(I92="", J92=""), "", VALUE(I92) - VALUE(J92))-F92 -> 0
A93: 27 | I93: {=IF(D93="","",INDEX('Товары '!$D$2:$D$78, MATCH(D93, 'Товары '!$B$2:$B$78, 0)))} | J93: =IF(D93="","",VLOOKUP(D93, 'Товары '!$B$2:$C$78, 2, FALSE)) | K93: =IF(OR(I93="", J93=""), "", VALUE(I93) - VALUE(J93))-F93 -> 0
A94: 28 | I94: {=IF(D94="","",INDEX('Товары '!$D$2:$D$78, MATCH(D94, 'Товары '!$B$2:$B$78, 0)))} | J94: =IF(D94="","",VLOOKUP(D94, 'Товары '!$B$2:$C$78, 2, FALSE)) | K94: =IF(OR(I94="", J94=""), "", VALUE(I94) - VALUE(J94))-F94 -> 0
A95: 29 | I95: {=IF(D95="","",INDEX('Товары '!$D$2:$D$78, MATCH(D95, 'Товары '!$B$2:$B$78, 0)))} | J95: =IF(D95="","",VLOOKUP(D95, 'Товары '!$B$2:$C$78, 2, FALSE)) | K95: =IF(OR(I95="", J95=""), "", VALUE(I95) - VALUE(J95))-F95 -> 0
A96: 30 | I96: {=IF(D96="","",INDEX('Товары '!$D$2:$D$78, MATCH(D96, 'Товары '!$B$2:$B$78, 0)))} | J96: =IF(D96="","",VLOOKUP(D96, 'Товары '!$B$2:$C$78, 2, FALSE)) | K96: =IF(OR(I96="", J96=""), "", VALUE(I96) - VALUE(J96))-F96 -> 0
A97: 31 | I97: {=IF(D97="","",INDEX('Товары '!$D$2:$D$78, MATCH(D97, 'Товары '!$B$2:$B$78, 0)))} | J97: =IF(D97="","",VLOOKUP(D97, 'Товары '!$B$2:$C$78, 2, FALSE)) | K97: =IF(OR(I97="", J97=""), "", VALUE(I97) - VALUE(J97))-F97 -> 0
A98: 32 | I98: {=IF(D98="","",INDEX('Товары '!$D$2:$D$78, MATCH(D98, 'Товары '!$B$2:$B$78, 0)))} | J98: =IF(D98="","",VLOOKUP(D98, 'Товары '!$B$2:$C$78, 2, FALSE)) | K98: =IF(OR(I98="", J98=""), "", VALUE(I98) - VALUE(J98))-F98 -> 0
A99: 33 | I99: {=IF(D99="","",INDEX('Товары '!$D$2:$D$78, MATCH(D99, 'Товары '!$B$2:$B$78, 0)))} | J99: =IF(D99="","",VLOOKUP(D99, 'Товары '!$B$2:$C$78, 2, FALSE)) | K99: =IF(OR(I99="", J99=""), "", VALUE(I99) - VALUE(J99))-F99 -> 0
A100: 34 | I100: {=IF(D100="","",INDEX('Товары '!$D$2:$D$78, MATCH(D100, 'Товары '!$B$2:$B$78, 0)))} | J100: =IF(D100="","",VLOOKUP(D100, 'Товары '!$B$2:$C$78, 2, FALSE)) | K100: =IF(OR(I100="", J100=""), "", VALUE(I100) - VALUE(J100))-F100 -> 0
A101: 35 | I101: {=IF(D101="","",INDEX('Товары '!$D$2:$D$78, MATCH(D101, 'Товары '!$B$2:$B$78, 0)))} | J101: =IF(D101="","",VLOOKUP(D101, 'Товары '!$B$2:$C$78, 2, FALSE)) | K101: =IF(OR(I101="", J101=""), "", VALUE(I101) - VALUE(J101))-F101 -> 0
A102: 36 | I102: {=IF(D102="","",INDEX('Товары '!$D$2:$D$78, MATCH(D102, 'Товары '!$B$2:$B$78, 0)))} | J102: =IF(D102="","",VLOOKUP(D102, 'Товары '!$B$2:$C$78, 2, FALSE)) | K102: =IF(OR(I102="", J102=""), "", VALUE(I102) - VALUE(J102))-F102 -> 0
A103: 37 | I103: {=IF(D103="","",INDEX('Товары '!$D$2:$D$78, MATCH(D103, 'Товары '!$B$2:$B$78, 0)))} | J103: =IF(D103="","",VLOOKUP(D103, 'Товары '!$B$2:$C$78, 2, FALSE)) | K103: =IF(OR(I103="", J103=""), "", VALUE(I103) - VALUE(J103))-F103 -> 0
... A126: 60 | I126: {=IF(D126="","",INDEX('Товары '!$D$2:$D$78, MATCH(D126, 'Товары '!$B$2:$B$78, 0)))} | J126: =IF(D126="","",VLOOKUP(D126, 'Товары '!$B$2:$C$78, 2, FALSE)) | K126: =IF(OR(I126="", J126=""), "", VALUE(I126) - VALUE(J126))-F126 -> 0
A127: Номер | B127: Дата | C127: Время | D127: Позиция | E127: Коменты | F127: Скидка | G127: Чистый заработок за день | H127: Выручка | I127: Розничная цена | J127: Закупочная цена | K127: Прибыль с единицы
A130: 1 | B130: 45953 | C130: 0.65300926 | D130: RICK AND MORTY BAD ICE | G130: =SUM(K130:K189) -> 129.9 | H130: =SUM(J130:K189) -> 284 | I130: {=IF(D130="","",INDEX('Товары '!$D$2:$D$78, MATCH(D130, 'Товары '!$B$2:$B$78, 0)))} -> 15 | J130: =IF(D130="","",VLOOKUP(D130, 'Товары '!$B$2:$C$78, 2, FALSE)) -> 9 | K130: =IF(OR(I130="", J130=""), "", VALUE(I130) - VALUE(J130))-F130 -> 6
A131: 2 | B131: 45953 | C131: 0.66123843 | D131: RICK AND MORTY BAD ICE | I131: {=IF(D131="","",INDEX('Товары '!$D$2:$D$78, MATCH(D131, 'Товары '!$B$2:$B$78, 0)))} -> 15 | J131: =IF(D131="","",VLOOKUP(D131, 'Товары '!$B$2:$C$78, 2, FALSE)) -> 9 | K131: =IF(OR(I131="", J131=""), "", VALUE(I131) - VALUE(J131))-F131 -> 6
A132: 3 | B132: 45953 | C132: 0.66127315 | D132: Катриджи Vaporesso XROS | I132: {=IF(D132="","",INDEX('Товары '!$D$2:$D$78, MATCH(D132, 'Товары '!$B$2:$B$78, 0)))} -> 13 | J132: =IF(D132="","",VLOOKUP(D132, 'Товары '!$B$2:$C$78, 2, FALSE)) -> 6.4 | K132: =IF(OR(I132="", J132=""), "", VALUE(I132) - VALUE(J132))-F132 -> 6.6
A133: 4 | B133: 45953 | C133: 0.7284838 | D133: RICK and MORTY BAD TRIP | I133: {=IF(D133="","",INDEX('Товары '!$D$2:$D$78, MATCH(D133, 'Товары '!$B$2:$B$78, 0)))} -> 15 | J133: =IF(D133="","",VLOOKUP(D133, 'Товары '!$B$2:$C$78, 2, FALSE)) -> 9 | K133: =IF(OR(I133="", J133=""), "", VALUE(I133) - VALUE(J133))-F133 -> 6
A134: 5 | B134: 45953 | C134: 0.75072917 | D134: Рик и морти на замерзоне strong | I134: {=IF(D134="","",INDEX('Товары '!$D$2:$D$78, MATCH(D134, 'Товары '!$B$2:$B$78, 0)))} -> 15 | J134: =IF(D134="","",VLOOKUP(D134, 'Товары '!$B$2:$C$78, 2, FALSE)) -> 6.9 | K134: =IF(OR(I134="", J134=""), "", VALUE(I134) - VALUE(J134))-F134 -> 8.1
A135: 6 | B135: 45953 | C135: 0.75081019 | D135: Катриджи Vaporesso XROS | I135: {=IF(D135="","",INDEX('Товары '!$D$2:$D$78, MATCH(D135, 'Товары '!$B$2:$B$78, 0)))} -> 13 | J135: =IF(D135="","",VLOOKUP(D135, 'Товары '!$B$2:$C$78, 2, FALSE)) -> 6.4 | K135: =IF(OR(I135="", J135=""), "", VALUE(I135) - VALUE(J135))-F135 -> 6.6
A136: 7 | B136: 45953 | C136: 0.76657407 | D136: RICK and MORTY BAD TRIP | I136: {=IF(D136="","",INDEX('Товары '!$D$2:$D$78, MATCH(D136, 'Товары '!$B$2:$B$78, 0)))} -> 15 | J136: =IF(D136="","",VLOOKUP(D136, 'Товары '!$B$2:$C$78, 2, FALSE)) -> 9 | K136: =IF(OR(I136="", J136=""), "", VALUE(I136) - VALUE(J136))-F136 -> 6
A137: 8 | B137: 45953 | C137: 0.78258102 | D137: Катриджи Vaporesso XROS | F137: 1 | I137: {=IF(D137="","",INDEX('Товары '!$D$2:$D$78, MATCH(D137, 'Товары '!$B$2:$B$78, 0)))} -> 13 | J137: =IF(D137="","",VLOOKUP(D137, 'Товары '!$B$2:$C$78, 2, FALSE)) -> 6.4 | K137: =IF(OR(I137="", J137=""), "", VALUE(I137) - VALUE(J137))-F137 -> 5.6
A138: 9 | B138: 45953 | C138: 0.78265046 | D138: Катриджи Vaporesso XROS | I138: {=IF(D138="","",INDEX('Товары '!$D$2:$D$78, MATCH(D138, 'Товары '!$B$2:$B$78, 0)))} -> 13 | J138: =IF(D138="","",VLOOKUP(D138, 'Товары '!$B$2:$C$78, 2, FALSE)) -> 6.4 | K138: =IF(OR(I138="", J138=""), "", VALUE(I138) - VALUE(J138))-F138 -> 6.6
A139: 10 | B139: 45953 | C139: 0.78273148 | D139: RICK and MORTY BAD TRIP | I139: {=IF(D139="","",INDEX('Товары '!$D$2:$D$78, MATCH(D139, 'Товары '!$B$2:$B$78, 0)))} -> 15 | J139: =IF(D139="","",VLOOKUP(D139, 'Товары '!$B$2:$C$78, 2, FALSE)) -> 9 | K139: =IF(OR(I139="", J139=""), "", VALUE(I139) - VALUE(J139))-F139 -> 6
A140: 11 | B140: 45953 | C140: 0.7828588 | D140: RICK and MORTY BAD ACID | I140: {=IF(D140="","",INDEX('Товары '!$D$2:$D$78, MATCH(D140, 'Товары '!$B$2:$B$78, 0)))} -> 15 | J140: =IF(D140="","",VLOOKUP(D140, 'Товары '!$B$2:$C$78, 2, FALSE)) -> 9 | K140: =IF(OR(I140="", J140=""), "", VALUE(I140) - VALUE(J140))-F140 -> 6
A141: 12 | B141: 45953 | C141: 0.78289352 | D141: PODONKI Podgon | I141: {=IF(D141="","",INDEX('Товары '!$D$2:$D$78, MATCH(D141, 'Товары '!$B$2:$B$78, 0)))} -> 15 | J141: =IF(D141="","",VLOOKUP(D141, 'Товары '!$B$2:$C$78, 2, FALSE)) -> 6 | K141: =IF(OR(I141="", J141=""), "", VALUE(I141) - VALUE(J141))-F141 -> 9
A142: 13 | B142: 45953 | C142: 0.78300926 | D142: снюс | I142: {=IF(D142="","",INDEX('Товары '!$D$2:$D$78, MATCH(D142, 'Товары '!$B$2:$B$78, 0)))} -> 15 | J142: =IF(D142="","",VLOOKUP(D142, 'Товары '!$B$2:$C$78, 2, FALSE)) -> 8.5 | K142: =IF(OR(I142="", J142=""), "", VALUE(I142) - VALUE(J142))-F142 -> 6.5
A143: 14 | B143: 45953 | C143: 0.79601852 | D143: CATSWILL (кислые | I143: {=IF(D143="","",INDEX('Товары '!$D$2:$D$78, MATCH(D143, 'Товары '!$B$2:$B$78, 0)))} -> 15 | J143: =IF(D143="","",VLOOKUP(D143, 'Товары '!$B$2:$C$78, 2, FALSE)) -> 9 | K143: =IF(OR(I143="", J143=""), "", VALUE(I143) - VALUE(J143))-F143 -> 6
A144: 15 | B144: 45953 | C144: 0.79623843 | D144: Катриджи Vaporesso XROS | I144: {=IF(D144="","",INDEX('Товары '!$D$2:$D$78, MATCH(D144, 'Товары '!$B$2:$B$78, 0)))} -> 13 | J144: =IF(D144="","",VLOOKUP(D144, 'Товары '!$B$2:$C$78, 2, FALSE)) -> 6.4 | K144: =IF(OR(I144="", J144=""), "", VALUE(I144) - VALUE(J144))-F144 -> 6.6
A145: 16 | B145: 45953 | C145: 0.82064815 | D145: Рик и морти на замерзоне strong | I145: {=IF(D145="","",INDEX('Товары '!$D$2:$D$78, MATCH(D145, 'Товары '!$B$2:$B$78, 0)))} -> 15 | J145: =IF(D145="","",VLOOKUP(D145, 'Товары '!$B$2:$C$78, 2, FALSE)) -> 6.9 | K145: =IF(OR(I145="", J145=""), "", VALUE(I145) - VALUE(J145))-F145 -> 8.1
A146: 17 | B146: 45953 | C146: 0.87709491 | D146: RICK and MORTY BAD TRIP | I146: {=IF(D146="","",INDEX('Товары '!$D$2:$D$78, MATCH(D146, 'Товары '!$B$2:$B$78, 0)))} -> 15 | J146: =IF(D146="","",VLOOKUP(D146, 'Товары '!$B$2:$C$78, 2, FALSE)) -> 9 | K146: =IF(OR(I146="", J146=""), "", VALUE(I146) - VALUE(J146))-F146 -> 6
...

Sheet Лист8

Sheet Лист6
A1: =IFERROR(__xludf.DUMMYFUNCTION("LET( _d, 'Днные'!A1:D5136, _b, 'Лист1'!D:D, _u, 2, _rows,IF(COUNTA(CHOOSECOLS(_b,_u-1))=0,0,LAMBDA(_e,COUNTIF(_e,""<""&MAX(_e))+1)(SCAN(0,CHOOSECOLS(_b,_u-1),LAMBDA(_a1,_b1, IF(_b1<>"""", _a1+1,_a1))))), _a,UNIQUE(MAKEARRAY(1,COLUMNS(_d),LAMBDA"&"(_x,_y,SCAN(,CHOOSECOLS(_d,_y),LAMBDA(_k,_m,IF(_m="""",_k,_m)))))), _r, MAKEARRAY(_rows,1,LAMBDA(_x,_y, TRANSPOSE(UNIQUE(IFERROR(FILTER(CHOOSECOLS(_a,_u),CHOOSECOLS(_a,_u-1)=INDEX(_b,_x,_u-1))))))), _r )"),"")
A4: =IFERROR(__xludf.DUMMYFUNCTION("""COMPUTED_VALUE"""),"Лесные ягоды") -> Лесные ягоды | B4: =IFERROR(__xludf.DUMMYFUNCTION("""COMPUTED_VALUE"""),"Алоэ виноград ") -> Алоэ виноград | C4: =IFERROR(__xludf.DUMMYFUNCTION("""COMPUTED_VALUE"""),"Апельсиновый адреналин") -> Апельсиновый адреналин | D4: =IFERROR(__xludf.DUMMYFUNCTION("""COMPUTED_VALUE"""),"Клюква лайм") -> Клюква лайм | E4: =IFERROR(__xludf.DUMMYFUNCTION("""COMPUTED_VALUE"""),"Виноградная фанта ") -> Виноградная фанта | F4: =IFERROR(__xludf.DUMMYFUNCTION("""COMPUTED_VALUE"""),"Зеленый чай лемонграсс") -> Зеленый чай лемонграсс | G4: =IFERROR(__xludf.DUMMYFUNCTION("""COMPUTED_VALUE"""),"Малина арбуз") -> Малина арбуз | H4: =IFERROR(__xludf.DUMMYFUNCTION("""COMPUTED_VALUE"""),"Ананас персик") -> Ананас персик | I4: =IFERROR(__xludf.DUMMYFUNCTION("""COMPUTED_VALUE"""),"Клубничный мохито ") -> Клубничный мохито | J4: =IFERROR(__xludf.DUMMYFUNCTION("""COMPUTED_VALUE"""),"Яблоко лайм") -> Яблоко лайм | K4: =IFERROR(__xludf.DUMMYFUNCTION("""COMPUTED_VALUE"""),"Спрайт арбуз лайм ") -> Спрайт арбуз лайм | L4: =IFERROR(__xludf.DUMMYFUNCTION("""COMPUTED_VALUE"""),"Черничная фанта") -> Черничная фанта | M4: =IFERROR(__xludf.DUMMYFUNCTION("""COMPUTED_VALUE"""),"Чёрная смородина") -> Чёрная смородина | N4: =IFERROR(__xludf.DUMMYFUNCTION("""COMPUTED_VALUE"""),"Червячки голубика малина") -> Червячки голубика малина | O4: =IFERROR(__xludf.DUMMYFUNCTION("""COMPUTED_VALUE"""),"Малина смородина ") -> Малина смородина | P4: =IFERROR(__xludf.DUMMYFUNCTION("""COMPUTED_VALUE"""),"Черника лайм ") -> Черника лайм | Q4: =IFERROR(__xludf.DUMMYFUNCTION("""COMPUTED_VALUE"""),"Виноградный чупа чупс") -> Виноградный чупа чупс | R4: =IFERROR(__xludf.DUMMYFUNCTION("""COMPUTED_VALUE"""),"Киви лайм") -> Киви лайм | S4: =IFERROR(__xludf.DUMMYFUNCTION("""COMPUTED_VALUE"""),"Ягодный морс") -> Ягодный морс | T4: =IFERROR(__xludf.DUMMYFUNCTION("""COMPUTED_VALUE"""),"Фруктовый скитлс") -> Фруктовый скитлс | U4: =IFERROR(__xludf.DUMMYFUNCTION("""COMPUTED_VALUE"""),"черника лимон ") -> черника лимон | V4: =IFERROR(__xludf.DUMMYFUNCTION("""COMPUTED_VALUE"""),"Вишнёвая бомба") -> Вишнёвая бомба | W4: =IFERROR(__xludf.DUMMYFUNCTION("""COMPUTED_VALUE"""),"Тропический манго") -> Тропический манго
A5: =IFERROR(__xludf.DUMMYFUNCTION("""COMPUTED_VALUE"""),"0.4") -> 0.4 | B5: =IFERROR(__xludf.DUMMYFUNCTION("""COMPUTED_VALUE"""),"0.6") -> 0.6 | C5: =IFERROR(__xludf.DUMMYFUNCTION("""COMPUTED_VALUE"""),"0.7") -> 0.7 | D5: =IFERROR(__xludf.DUMMYFUNCTION("""COMPUTED_VALUE"""),"0.8") -> 0.8
A6: =IFERROR(__xludf.DUMMYFUNCTION("""COMPUTED_VALUE"""),"0.4") -> 0.4 | B6: =IFERROR(__xludf.DUMMYFUNCTION("""COMPUTED_VALUE"""),"0.6") -> 0.6 | C6: =IFERROR(__xludf.DUMMYFUNCTION("""COMPUTED_VALUE"""),"0.7") -> 0.7 | D6: =IFERROR(__xludf.DUMMYFUNCTION("""COMPUTED_VALUE"""),"0.8") -> 0.8
A7: =IFERROR(__xludf.DUMMYFUNCTION("""COMPUTED_VALUE"""),"Малина вишня лёд") -> Малина вишня лёд
A8: =IFERROR(__xludf.DUMMYFUNCTION("""COMPUTED_VALUE"""),"кислая земляника") -> кислая земляника | B8: =IFERROR(__xludf.DUMMYFUNCTION("""COMPUTED_VALUE"""),"кислая фанта с черникой") -> кислая фанта с черникой | C8: =IFERROR(__xludf.DUMMYFUNCTION("""COMPUTED_VALUE"""),"кислое харибо с колой и черешней") -> кислое харибо с колой и черешней | D8: =IFERROR(__xludf.DUMMYFUNCTION("""COMPUTED_VALUE"""),"кислое яблочно клубничная шипучка") -> кислое яблочно клубничная шипучка | E8: =IFERROR(__xludf.DUMMYFUNCTION("""COMPUTED_VALUE"""),"кислые желатинки маракуйя ананас") -> кислые желатинки маракуйя ананас | F8: =IFERROR(__xludf.DUMMYFUNCTION("""COMPUTED_VALUE"""),"кислые ленточки маракуя манго") -> кислые ленточки маракуя манго | G8: =IFERROR(__xludf.DUMMYFUNCTION("""COMPUTED_VALUE"""),"кислые мармеладные ягоды") -> кислые мармеладные ягоды | H8: =IFERROR(__xludf.DUMMYFUNCTION("""COMPUTED_VALUE"""),"кислый виноград лайм") -> кислый виноград лайм | I8: =IFERROR(__xludf.DUMMYFUNCTION("""COMPUTED_VALUE"""),"кислый грейпфрут с вишней") -> кислый грейпфрут с вишней | J8: =IFERROR(__xludf.DUMMYFUNCTION("""COMPUTED_VALUE"""),"кислый леденец виноград киви яблоко") -> кислый леденец виноград киви яблоко | K8: =IFERROR(__xludf.DUMMYFUNCTION("""COMPUTED_VALUE"""),"кислый лимонад арбуз лайм малина") -> кислый лимонад арбуз лайм малина | L8: =IFERROR(__xludf.DUMMYFUNCTION("""COMPUTED_VALUE"""),"кислый персик клубника") -> кислый персик клубника | M8: =IFERROR(__xludf.DUMMYFUNCTION("""COMPUTED_VALUE"""),"кислый яблочно лимонные колечки") -> кислый яблочно лимонные колечки | N8: =IFERROR(__xludf.DUMMYFUNCTION("""COMPUTED_VALUE"""),"фанта апельсин с кислой малиной") -> фанта апельсин с кислой малиной
A9: =IFERROR(__xludf.DUMMYFUNCTION("""COMPUTED_VALUE"""),"0.4") -> 0.4 | B9: =IFERROR(__xludf.DUMMYFUNCTION("""COMPUTED_VALUE"""),"0.6") -> 0.6 | C9: =IFERROR(__xludf.DUMMYFUNCTION("""COMPUTED_VALUE"""),"0.7") -> 0.7 | D9: =IFERROR(__xludf.DUMMYFUNCTION("""COMPUTED_VALUE"""),"0.8") -> 0.8
A10: =IFERROR(__xludf.DUMMYFUNCTION("""COMPUTED_VALUE"""),"Арбуз Малина ") -> Арбуз Малина | B10: =IFERROR(__xludf.DUMMYFUNCTION("""COMPUTED_VALUE"""),"Банан Кокос ") -> Банан Кокос | C10: =IFERROR(__xludf.DUMMYFUNCTION("""COMPUTED_VALUE"""),"Барбарисовый Энергетик ") -> Барбарисовый Энергетик | D10: =IFERROR(__xludf.DUMMYFUNCTION("""COMPUTED_VALUE"""),"Виноградный Энергетик") -> Виноградный Энергетик | E10: =IFERROR(__xludf.DUMMYFUNCTION("""COMPUTED_VALUE"""),"Гранат Клубника ") -> Гранат Клубника | F10: =IFERROR(__xludf.DUMMYFUNCTION("""COMPUTED_VALUE"""),"Гранат Смородина ") -> Гранат Смородина | G10: =IFERROR(__xludf.DUMMYFUNCTION("""COMPUTED_VALUE"""),"Грейпфрутовый Швепс ") -> Грейпфрутовый Швепс | H10: =IFERROR(__xludf.DUMMYFUNCTION("""COMPUTED_VALUE"""),"Земляника Драгонфрут ") -> Земляника Драгонфрут | I10: =IFERROR(__xludf.DUMMYFUNCTION("""COMPUTED_VALUE"""),"Киви Личи ") -> Киви Личи | J10: =IFERROR(__xludf.DUMMYFUNCTION("""COMPUTED_VALUE"""),"Киви Маракуйя Гуава ") -> Киви Маракуйя Гуава | K10: =IFERROR(__xludf.DUMMYFUNCTION("""COMPUTED_VALUE"""),"Клубника Банан ") -> Клубника Банан | L10: =IFERROR(__xludf.DUMMYFUNCTION("""COMPUTED_VALUE"""),"Клубника Вишня ") -> Клубника Вишня | M10: =IFERROR(__xludf.DUMMYFUNCTION("""COMPUTED_VALUE"""),"Клубника Земляника ") -> Клубника Земляника | N10: =IFERROR(__xludf.DUMMYFUNCTION("""COMPUTED_VALUE"""),"Клубничный Мохито ") -> Клубничный Мохито | O10: =IFERROR(__xludf.DUMMYFUNCTION("""COMPUTED_VALUE"""),"Манго Грейпфрут ") -> Манго Грейпфрут | P10: =IFERROR(__xludf.DUMMYFUNCTION("""COMPUTED_VALUE"""),"Манго Персик Личи ") -> Манго Персик Личи | Q10: =IFERROR(__xludf.DUMMYFUNCTION("""COMPUTED_VALUE"""),"Персик Бабл Гам ") -> Персик Бабл Гам | R10: =IFERROR(__xludf.DUMMYFUNCTION("""COMPUTED_VALUE"""),"Садовые Ягоды ") -> Садовые Ягоды | S10: =IFERROR(__xludf.DUMMYFUNCTION("""COMPUTED_VALUE"""),"Скитлс Лимон Лайм 2") -> Скитлс Лимон Лайм 2 | T10: =IFERROR(__xludf.DUMMYFUNCTION("""COMPUTED_VALUE"""),"Смородина Мармелад 1") -> Смородина Мармелад 1 | U10: =IFERROR(__xludf.DUMMYFUNCTION("""COMPUTED_VALUE"""),"Темная Вишня 1") -> Темная Вишня 1 | V10: =IFERROR(__xludf.DUMMYFUNCTION("""COMPUTED_VALUE"""),"Фруктовые Пластинки 1") -> Фруктовые Пластинки 1 | W10: =IFERROR(__xludf.DUMMYFUNCTION("""COMPUTED_VALUE"""),"Черника Ежевика 1") -> Черника Ежевика 1 | X10: =IFERROR(__xludf.DUMMYFUNCTION("""COMPUTED_VALUE"""),"Черника Малина 1") -> Черника Малина 1 | Y10: =IFERROR(__xludf.DUMMYFUNCTION("""COMPUTED_VALUE"""),"Черника Мята 2") -> Черника Мята 2 | Z10: =IFERROR(__xludf.DUMMYFUNCTION("""COMPUTED_VALUE"""),"Яблоко Виноград 2") -> Яблоко Виноград 2 | AA10: =IFERROR(__xludf.DUMMYFUNCTION("""COMPUTED_VALUE"""),"Яблоко Малина 4") -> Яблоко Малина 4
A11: =IFERROR(__xludf.DUMMYFUNCTION("""COMPUTED_VALUE"""),"Арбуз Малина ") -> Арбуз Малина | B11: =IFERROR(__xludf.DUMMYFUNCTION("""COMPUTED_VALUE"""),"Банан Кокос ") -> Банан Кокос | C11: =IFERROR(__xludf.DUMMYFUNCTION("""COMPUTED_VALUE"""),"Барбарисовый Энергетик ") -> Барбарисовый Энергетик | D11: =IFERROR(__xludf.DUMMYFUNCTION("""COMPUTED_VALUE"""),"Виноградный Энергетик") -> Виноградный Энергетик | E11: =IFERROR(__xludf.DUMMYFUNCTION("""COMPUTED_VALUE"""),"Гранат Клубника ") -> Гранат Клубника | F11: =IFERROR(__xludf.DUMMYFUNCTION("""COMPUTED_VALUE"""),"Гранат Смородина ") -> Гранат Смородина | G11: =IFERROR(__xludf.DUMMYFUNCTION("""COMPUTED_VALUE"""),"Грейпфрутовый Швепс ") -> Грейпфрутовый Швепс | H11: =IFERROR(__xludf.DUMMYFUNCTION("""COMPUTED_VALUE"""),"Земляника Драгонфрут ") -> Земляника Драгонфрут | I11: =IFERROR(__xludf.DUMMYFUNCTION("""COMPUTED_VALUE"""),"Киви Личи ") -> Киви Личи | J11: =IFERROR(__xludf.DUMMYFUNCTION("""COMPUTED_VALUE"""),"Киви Маракуйя Гуава ") -> Киви Маракуйя Гуава | K11: =IFERROR(__xludf.DUMMYFUNCTION("""COMPUTED_VALUE"""),"Клубника Банан ") -> Клубника Банан | L11: =IFERROR(__xludf.DUMMYFUNCTION("""COMPUTED_VALUE"""),"Клубника Вишня ") -> Клубника Вишня | M11: =IFERROR(__xludf.DUMMYFUNCTION("""COMPUTED_VALUE"""),"Клубника Земляника ") -> Клубника Земляника | N11: =IFERROR(__xludf.DUMMYFUNCTION("""COMPUTED_VALUE"""),"Клубничный Мохито ") -> Клубничный Мохито | O11: =IFERROR(__xludf.DUMMYFUNCTION("""COMPUTED_VALUE"""),"Манго Грейпфрут ") -> Манго Грейпфрут | P11: =IFERROR(__xludf.DUMMYFUNCTION("""COMPUTED_VALUE"""),"Манго Персик Личи ") -> Манго Персик Личи | Q11: =IFERROR(__xludf.DUMMYFUNCTION("""COMPUTED_VALUE"""),"Персик Бабл Гам ") -> Персик Бабл Гам | R11: =IFERROR(__xludf.DUMMYFUNCTION("""COMPUTED_VALUE"""),"Садовые Ягоды ") -> Садовые Ягоды | S11: =IFERROR(__xludf.DUMMYFUNCTION("""COMPUTED_VALUE"""),"Скитлс Лимон Лайм 2") -> Скитлс Лимон Лайм 2 | T11: =IFERROR(__xludf.DUMMYFUNCTION("""COMPUTED_VALUE"""),"Смородина Мармелад 1") -> Смородина Мармелад 1 | U11: =IFERROR(__xludf.DUMMYFUNCTION("""COMPUTED_VALUE"""),"Темная Вишня 1") -> Темная Вишня 1 | V11: =IFERROR(__xludf.DUMMYFUNCTION("""COMPUTED_VALUE"""),"Фруктовые Пластинки 1") -> Фруктовые Пластинки 1 | W11: =IFERROR(__xludf.DUMMYFUNCTION("""COMPUTED_VALUE"""),"Черника Ежевика 1") -> Черника Ежевика 1 | X11: =IFERROR(__xludf.DUMMYFUNCTION("""COMPUTED_VALUE"""),"Черника Малина 1") -> Черника Малина 1 | Y11: =IFERROR(__xludf.DUMMYFUNCTION("""COMPUTED_VALUE"""),"Черника Мята 2") -> Черника Мята 2 | Z11: =IFERROR(__xludf.DUMMYFUNCTION("""COMPUTED_VALUE"""),"Яблоко Виноград 2") -> Яблоко Виноград 2 | AA11: =IFERROR(__xludf.DUMMYFUNCTION("""COMPUTED_VALUE"""),"Яблоко Малина 4") -> Яблоко Малина 4
A12: =IFERROR(__xludf.DUMMYFUNCTION("""COMPUTED_VALUE"""),"0.4") -> 0.4 | B12: =IFERROR(__xludf.DUMMYFUNCTION("""COMPUTED_VALUE"""),"0.6") -> 0.6 | C12: =IFERROR(__xludf.DUMMYFUNCTION("""COMPUTED_VALUE"""),"0.7") -> 0.7 | D12: =IFERROR(__xludf.DUMMYFUNCTION("""COMPUTED_VALUE"""),"0.8") -> 0.8
A13: =IFERROR(__xludf.DUMMYFUNCTION("""COMPUTED_VALUE"""),"0.4") -> 0.4 | B13: =IFERROR(__xludf.DUMMYFUNCTION("""COMPUTED_VALUE"""),"0.6") -> 0.6 | C13: =IFERROR(__xludf.DUMMYFUNCTION("""COMPUTED_VALUE"""),"0.7") -> 0.7 | D13: =IFERROR(__xludf.DUMMYFUNCTION("""COMPUTED_VALUE"""),"0.8") -> 0.8
A14: =IFERROR(__xludf.DUMMYFUNCTION("""COMPUTED_VALUE"""),"Маракуйя с тропическими нотками") -> Маракуйя с тропическими нотками | B14: =IFERROR(__xludf.DUMMYFUNCTION("""COMPUTED_VALUE"""),"Арбузный милкшейк") -> Арбузный милкшейк | C14: =IFERROR(__xludf.DUMMYFUNCTION("""COMPUTED_VALUE"""),"Конфеты со вкусом винограда") -> Конфеты со вкусом винограда | D14: =IFERROR(__xludf.DUMMYFUNCTION("""COMPUTED_VALUE"""),"Манго с апельсином и послевкусием гуавы") -> Манго с апельсином и послевкусием гуавы | E14: =IFERROR(__xludf.DUMMYFUNCTION("""COMPUTED_VALUE"""),"Холодное сочетание мяты и конфет холс") -> Холодное сочетание мяты и конфет холс | F14: =IFERROR(__xludf.DUMMYFUNCTION("""COMPUTED_VALUE"""),"Яблочные мармеладные червячки") -> Яблочные мармеладные червячки | G14: =IFERROR(__xludf.DUMMYFUNCTION("""COMPUTED_VALUE"""),"Микс сладкогоперсика и вишни с кислинкой") -> Микс сладкогоперсика и вишни с кислинкой | H14: =IFERROR(__xludf.DUMMYFUNCTION("""COMPUTED_VALUE"""),"Лимон лайм") -> Лимон лайм | I14: =IFERROR(__xludf.DUMMYFUNCTION("""COMPUTED_VALUE"""),"Классика энергетика с кислой малиной") -> Классика энергетика с кислой малиной | J14: =IFERROR(__xludf.DUMMYFUNCTION("""COMPUTED_VALUE"""),"Зеленое манго и смородина") -> Зеленое манго и смородина | K14: =IFERROR(__xludf.DUMMYFUNCTION("""COMPUTED_VALUE"""),"Дуэт лемонграсса и сладкой малины") -> Дуэт лемонграсса и сладкой малины | L14: =IFERROR(__xludf.DUMMYFUNCTION("""COMPUTED_VALUE"""),"Сладкий мармелад из черной смородины") -> Сладкий мармелад из черной смородины | M14: =IFERROR(__xludf.DUMMYFUNCTION("""COMPUTED_VALUE"""),"Вишня кола") -> Вишня кола | N14: =IFERROR(__xludf.DUMMYFUNCTION("""COMPUTED_VALUE"""),"Малина с кокосом") -> Малина с кокосом | O14: =IFERROR(__xludf.DUMMYFUNCTION("""COMPUTED_VALUE"""),"Сладкие конфеты СКИТЛЗ и смородина") -> Сладкие конфеты СКИТЛЗ и смородина | P14: =IFERROR(__xludf.DUMMYFUNCTION("""COMPUTED_VALUE"""),"Ежевичный лимонад") -> Ежевичный лимонад | Q14: =IFERROR(__xludf.DUMMYFUNCTION("""COMPUTED_VALUE"""),"Дыня кокос") -> Дыня кокос | R14: =IFERROR(__xludf.DUMMYFUNCTION("""COMPUTED_VALUE"""),"Земляничный бабл гам") -> Земляничный бабл гам | S14: =IFERROR(__xludf.DUMMYFUNCTION("""COMPUTED_VALUE"""),"Лимонные леденцы") -> Лимонные леденцы | T14: =IFERROR(__xludf.DUMMYFUNCTION("""COMPUTED_VALUE"""),"Экзотический фрукты") -> Экзотический фрукты | U14: =IFERROR(__xludf.DUMMYFUNCTION("""COMPUTED_VALUE"""),"Личи виноград мята") -> Личи виноград мята | V14: =IFERROR(__xludf.DUMMYFUNCTION("""COMPUTED_VALUE"""),"Черника малина мята") -> Черника малина мята | W14: =IFERROR(__xludf.DUMMYFUNCTION("""COMPUTED_VALUE"""),"Абрикосовый йогурт") -> Абрикосовый йогурт | X14: =IFERROR(__xludf.DUMMYFUNCTION("""COMPUTED_VALUE"""),"Арбуз лед") -> Арбуз лед | Y14: =IFERROR(__xludf.DUMMYFUNCTION("""COMPUTED_VALUE"""),"Банан клубника лед") -> Банан клубника лед | Z14: =IFERROR(__xludf.DUMMYFUNCTION("""COMPUTED_VALUE"""),"Арбузное мороженное") -> Арбузное мороженное | AA14: =IFERROR(__xludf.DUMMYFUNCTION("""COMPUTED_VALUE"""),"Клубника малина жвачка") -> Клубника малина жвачка | AB14: =IFERROR(__xludf.DUMMYFUNCTION("""COMPUTED_VALUE"""),"Клубничное мороженное") -> Клубничное мороженное | AC14: =IFERROR(__xludf.DUMMYFUNCTION("""COMPUTED_VALUE"""),"Кола сода лед") -> Кола сода лед | AD14: =IFERROR(__xludf.DUMMYFUNCTION("""COMPUTED_VALUE"""),"Банановый милкшейк") -> Банановый милкшейк | AE14: =IFERROR(__xludf.DUMMYFUNCTION("""COMPUTED_VALUE"""),"Микс ягод лед") -> Микс ягод лед | AF14: =IFERROR(__xludf.DUMMYFUNCTION("""COMPUTED_VALUE"""),"Брусничный морс") -> Брусничный морс | AG14: =IFERROR(__xludf.DUMMYFUNCTION("""COMPUTED_VALUE"""),"Яблочный лимонад") -> Яблочный лимонад | AH14: =IFERROR(__xludf.DUMMYFUNCTION("""COMPUTED_VALUE"""),"Лесные ягоды") -> Лесные ягоды | AI14: =IFERROR(__xludf.DUMMYFUNCTION("""COMPUTED_VALUE"""),"Смородиновый лимонад") -> Смородиновый лимонад | AJ14: =IFERROR(__xludf.DUMMYFUNCTION("""COMPUTED_VALUE"""),"Вишня лайм лед") -> Вишня лайм лед | AK14: =IFERROR(__xludf.DUMMYFUNCTION("""COMPUTED_VALUE"""),"Лист виноград мята энергетик") -> Лист виноград мята энергетик | AL14: =IFERROR(__xludf.DUMMYFUNCTION("""COMPUTED_VALUE"""),"Двойное яблоко лед") -> Двойное яблоко лед | AM14: =IFERROR(__xludf.DUMMYFUNCTION("""COMPUTED_VALUE"""),"Смородиновый холс") -> Смородиновый холс | AN14: =IFERROR(__xludf.DUMMYFUNCTION("""COMPUTED_VALUE"""),"Клубничное шампанское") -> Клубничное шампанское
A15: =IFERROR(__xludf.DUMMYFUNCTION("""COMPUTED_VALUE"""),"0.4") -> 0.4 | B15: =IFERROR(__xludf.DUMMYFUNCTION("""COMPUTED_VALUE"""),"0.6") -> 0.6 | C15: =IFERROR(__xludf.DUMMYFUNCTION("""COMPUTED_VALUE"""),"0.7") -> 0.7 | D15: =IFERROR(__xludf.DUMMYFUNCTION("""COMPUTED_VALUE"""),"0.8") -> 0.8
A16: =IFERROR(__xludf.DUMMYFUNCTION("""COMPUTED_VALUE"""),"кислая земляника") -> кислая земляника | B16: =IFERROR(__xludf.DUMMYFUNCTION("""COMPUTED_VALUE"""),"кислая фанта с черникой") -> кислая фанта с черникой | C16: =IFERROR(__xludf.DUMMYFUNCTION("""COMPUTED_VALUE"""),"кислое харибо с колой и черешней") -> кислое харибо с колой и черешней | D16: =IFERROR(__xludf.DUMMYFUNCTION("""COMPUTED_VALUE"""),"кислое яблочно клубничная шипучка") -> кислое яблочно клубничная шипучка | E16: =IFERROR(__xludf.DUMMYFUNCTION("""COMPUTED_VALUE"""),"кислые желатинки маракуйя ананас") -> кислые желатинки маракуйя ананас | F16: =IFERROR(__xludf.DUMMYFUNCTION("""COMPUTED_VALUE"""),"кислые ленточки маракуя манго") -> кислые ленточки маракуя манго | G16: =IFERROR(__xludf.DUMMYFUNCTION("""COMPUTED_VALUE"""),"кислые мармеладные ягоды") -> кислые мармеладные ягоды | H16: =IFERROR(__xludf.DUMMYFUNCTION("""COMPUTED_VALUE"""),"кислый виноград лайм") -> кислый виноград лайм | I16: =IFERROR(__xludf.DUMMYFUNCTION("""COMPUTED_VALUE"""),"кислый грейпфрут с вишней") -> кислый грейпфрут с вишней | J16: =IFERROR(__xludf.DUMMYFUNCTION("""COMPUTED_VALUE"""),"кислый леденец виноград киви яблоко") -> кислый леденец виноград киви яблоко | K16: =IFERROR(__xludf.DUMMYFUNCTION("""COMPUTED_VALUE"""),"кислый лимонад арбуз лайм малина") -> кислый лимонад арбуз лайм малина | L16: =IFERROR(__xludf.DUMMYFUNCTION("""COMPUTED_VALUE"""),"кислый персик клубника") -> кислый персик клубника | M16: =IFERROR(__xludf.DUMMYFUNCTION("""COMPUTED_VALUE"""),"кислый яблочно лимонные колечки") -> кислый яблочно лимонные колечки | N16: =IFERROR(__xludf.DUMMYFUNCTION("""COMPUTED_VALUE"""),"фанта апельсин с кислой малиной") -> фанта апельсин с кислой малиной
A17: =IFERROR(__xludf.DUMMYFUNCTION("""COMPUTED_VALUE"""),"0.4") -> 0.4 | B17: =IFERROR(__xludf.DUMMYFUNCTION("""COMPUTED_VALUE"""),"0.6") -> 0.6 | C17: =IFERROR(__xludf.DUMMYFUNCTION("""COMPUTED_VALUE"""),"0.7") -> 0.7 | D17: =IFERROR(__xludf.DUMMYFUNCTION("""COMPUTED_VALUE"""),"0.8") -> 0.8
A18: =IFERROR(__xludf.DUMMYFUNCTION("""COMPUTED_VALUE"""),"0.4") -> 0.4 | B18: =IFERROR(__xludf.DUMMYFUNCTION("""COMPUTED_VALUE"""),"0.6") -> 0.6 | C18: =IFERROR(__xludf.DUMMYFUNCTION("""COMPUTED_VALUE"""),"0.7") -> 0.7 | D18: =IFERROR(__xludf.DUMMYFUNCTION("""COMPUTED_VALUE"""),"0.8") -> 0.8
A19: =IFERROR(__xludf.DUMMYFUNCTION("""COMPUTED_VALUE"""),"Ананас киви") -> Ананас киви | B19: =IFERROR(__xludf.DUMMYFUNCTION("""COMPUTED_VALUE"""),"Арбузный смузи") -> Арбузный смузи | C19: =IFERROR(__xludf.DUMMYFUNCTION("""COMPUTED_VALUE"""),"Виноградная фанта") -> Виноградная фанта | D19: =IFERROR(__xludf.DUMMYFUNCTION("""COMPUTED_VALUE"""),"Вишневый морс") -> Вишневый морс | E19: =IFERROR(__xludf.DUMMYFUNCTION("""COMPUTED_VALUE"""),"Гранатовый мармелад") -> Гранатовый мармелад | F19: =IFERROR(__xludf.DUMMYFUNCTION("""COMPUTED_VALUE"""),"Грейпфрут киви") -> Грейпфрут киви | G19: =IFERROR(__xludf.DUMMYFUNCTION("""COMPUTED_VALUE"""),"Ежевика мята") -> Ежевика мята | H19: =IFERROR(__xludf.DUMMYFUNCTION("""COMPUTED_VALUE"""),"Киви манго") -> Киви манго | I19: =IFERROR(__xludf.DUMMYFUNCTION("""COMPUTED_VALUE"""),"Клубника манго") -> Клубника манго | J19: =IFERROR(__xludf.DUMMYFUNCTION("""COMPUTED_VALUE"""),"черника грейфрут ") -> черника грейфрут | K19: =IFERROR(__xludf.DUMMYFUNCTION("""COMPUTED_VALUE"""),"Малина лайм") -> Малина лайм | L19: =IFERROR(__xludf.DUMMYFUNCTION("""COMPUTED_VALUE"""),"Манго арбуз ") -> Манго арбуз | M19: =IFERROR(__xludf.DUMMYFUNCTION("""COMPUTED_VALUE"""),"Малиновый чай с жасмином") -> Малиновый чай с жасмином | N19: =IFERROR(__xludf.DUMMYFUNCTION("""COMPUTED_VALUE"""),"малина апельсин ") -> малина апельсин | O19: =IFERROR(__xludf.DUMMYFUNCTION("""COMPUTED_VALUE"""),"Манго апельсин") -> Манго апельсин | P19: =IFERROR(__xludf.DUMMYFUNCTION("""COMPUTED_VALUE"""),"Ред булл") -> Ред булл | Q19: =IFERROR(__xludf.DUMMYFUNCTION("""COMPUTED_VALUE"""),"Спрайт") -> Спрайт | R19: =IFERROR(__xludf.DUMMYFUNCTION("""COMPUTED_VALUE"""),"ананас клюква ") -> ананас клюква | S19: =IFERROR(__xludf.DUMMYFUNCTION("""COMPUTED_VALUE"""),"Тархун") -> Тархун | T19: =IFERROR(__xludf.DUMMYFUNCTION("""COMPUTED_VALUE"""),"алоэ Виноград ") -> алоэ Виноград | U19: =IFERROR(__xludf.DUMMYFUNCTION("""COMPUTED_VALUE"""),"Фруктовая жвачка") -> Фруктовая жвачка | V19: =IFERROR(__xludf.DUMMYFUNCTION("""COMPUTED_VALUE"""),"Холодная кола") -> Холодная кола | W19: =IFERROR(__xludf.DUMMYFUNCTION("""COMPUTED_VALUE"""),"Черная смородина клюква") -> Черная смородина клюква | X19: =IFERROR(__xludf.DUMMYFUNCTION("""COMPUTED_VALUE"""),"Черника арбуз") -> Черника арбуз | Y19: =IFERROR(__xludf.DUMMYFUNCTION("""COMPUTED_VALUE"""),"Яблоко черника") -> Яблоко черника
A20: =IFERROR(__xludf.DUMMYFUNCTION("""COMPUTED_VALUE"""),"Арбуз Малина ") -> Арбуз Малина | B20: =IFERROR(__xludf.DUMMYFUNCTION("""COMPUTED_VALUE"""),"Банан Кокос ") -> Банан Кокос | C20: =IFERROR(__xludf.DUMMYFUNCTION("""COMPUTED_VALUE"""),"Барбарисовый Энергетик ") -> Барбарисовый Энергетик | D20: =IFERROR(__xludf.DUMMYFUNCTION("""COMPUTED_VALUE"""),"Виноградный Энергетик") -> Виноградный Энергетик | E20: =IFERROR(__xludf.DUMMYFUNCTION("""COMPUTED_VALUE"""),"Гранат Клубника ") -> Гранат Клубника | F20: =IFERROR(__xludf.DUMMYFUNCTION("""COMPUTED_VALUE"""),"Гранат Смородина ") -> Гранат Смородина | G20: =IFERROR(__xludf.DUMMYFUNCTION("""COMPUTED_VALUE"""),"Грейпфрутовый Швепс ") -> Грейпфрутовый Швепс | H20: =IFERROR(__xludf.DUMMYFUNCTION("""COMPUTED_VALUE"""),"Земляника Драгонфрут ") -> Земляника Драгонфрут | I20: =IFERROR(__xludf.DUMMYFUNCTION("""COMPUTED_VALUE"""),"Киви Личи ") -> Киви Личи | J20: =IFERROR(__xludf.DUMMYFUNCTION("""COMPUTED_VALUE"""),"Киви Маракуйя Гуава ") -> Киви Маракуйя Гуава | K20: =IFERROR(__xludf.DUMMYFUNCTION("""COMPUTED_VALUE"""),"Клубника Банан ") -> Клубника Банан | L20: =IFERROR(__xludf.DUMMYFUNCTION("""COMPUTED_VALUE"""),"Клубника Вишня ") -> Клубника Вишня | M20: =IFERROR(__xludf.DUMMYFUNCTION("""COMPUTED_VALUE"""),"Клубника Земляника ") -> Клубника Земляника | N20: =IFERROR(__xludf.DUMMYFUNCTION("""COMPUTED_VALUE"""),"Клубничный Мохито ") -> Клубничный Мохито | O20: =IFERROR(__xludf.DUMMYFUNCTION("""COMPUTED_VALUE"""),"Манго Грейпфрут ") -> Манго Грейпфрут | P20: =IFERROR(__xludf.DUMMYFUNCTION("""COMPUTED_VALUE"""),"Манго Персик Личи ") -> Манго Персик Личи | Q20: =IFERROR(__xludf.DUMMYFUNCTION("""COMPUTED_VALUE"""),"Персик Бабл Гам ") -> Персик Бабл Гам | R20: =IFERROR(__xludf.DUMMYFUNCTION("""COMPUTED_VALUE"""),"Садовые Ягоды ") -> Садовые Ягоды | S20: =IFERROR(__xludf.DUMMYFUNCTION("""COMPUTED_VALUE"""),"Скитлс Лимон Лайм 2") -> Скитлс Лимон Лайм 2 | T20: =IFERROR(__xludf.DUMMYFUNCTION("""COMPUTED_VALUE"""),"Смородина Мармелад 1") -> Смородина Мармелад 1 | U20: =IFERROR(__xludf.DUMMYFUNCTION("""COMPUTED_VALUE"""),"Темная Вишня 1") -> Темная Вишня 1 | V20: =IFERROR(__xludf.DUMMYFUNCTION("""COMPUTED_VALUE"""),"Фруктовые Пластинки 1") -> Фруктовые Пластинки 1 | W20: =IFERROR(__xludf.DUMMYFUNCTION("""COMPUTED_VALUE"""),"Черника Ежевика 1") -> Черника Ежевика 1 | X20: =IFERROR(__xludf.DUMMYFUNCTION("""COMPUTED_VALUE"""),"Черника Малина 1") -> Черника Малина 1 | Y20: =IFERROR(__xludf.DUMMYFUNCTION("""COMPUTED_VALUE"""),"Черника Мята 2") -> Черника Мята 2 | Z20: =IFERROR(__xludf.DUMMYFUNCTION("""COMPUTED_VALUE"""),"Яблоко Виноград 2") -> Яблоко Виноград 2 | AA20: =IFERROR(__xludf.DUMMYFUNCTION("""COMPUTED_VALUE"""),"Яблоко Малина 4") -> Яблоко Малина 4
A21: =IFERROR(__xludf.DUMMYFUNCTION("""COMPUTED_VALUE"""),"Апельсиновое драже") -> Апельсиновое драже | B21: =IFERROR(__xludf.DUMMYFUNCTION("""COMPUTED_VALUE"""),"Бабл гам") -> Бабл гам | C21: =IFERROR(__xludf.DUMMYFUNCTION("""COMPUTED_VALUE"""),"Виноградная конфета") -> Виноградная конфета | D21: =IFERROR(__xludf.DUMMYFUNCTION("""COMPUTED_VALUE"""),"Даня кокос") -> Даня кокос | E21: =IFERROR(__xludf.DUMMYFUNCTION("""COMPUTED_VALUE"""),"Земляника груша") -> Земляника груша | F21: =IFERROR(__xludf.DUMMYFUNCTION("""COMPUTED_VALUE"""),"Кислый киви") -> Кислый киви | G21: =IFERROR(__xludf.DUMMYFUNCTION("""COMPUTED_VALUE"""),"Кислый малиновый лимонад ") -> Кислый малиновый лимонад | H21: =IFERROR(__xludf.DUMMYFUNCTION("""COMPUTED_VALUE"""),"Кола сода айс") -> Кола сода айс | I21: =IFERROR(__xludf.DUMMYFUNCTION("""COMPUTED_VALUE"""),"Ледяной ананас") -> Ледяной ананас | J21: =IFERROR(__xludf.DUMMYFUNCTION("""COMPUTED_VALUE"""),"Лимонные червячки ") -> Лимонные червячки | K21: =IFERROR(__xludf.DUMMYFUNCTION("""COMPUTED_VALUE"""),"Манго апельсин") -> Манго апельсин | L21: =IFERROR(__xludf.DUMMYFUNCTION("""COMPUTED_VALUE"""),"Смородина виноград") -> Смородина виноград | M21: =IFERROR(__xludf.DUMMYFUNCTION("""COMPUTED_VALUE"""),"Яблочный холс") -> Яблочный холс | N21: =IFERROR(__xludf.DUMMYFUNCTION("""COMPUTED_VALUE"""),"Ягодный смузи") -> Ягодный смузи | O21: =IFERROR(__xludf.DUMMYFUNCTION("""COMPUTED_VALUE"""),"Ягодный энергетик") -> Ягодный энергетик
A22: =IFERROR(__xludf.DUMMYFUNCTION("""COMPUTED_VALUE"""),"Арбуз Малина ") -> Арбуз Малина | B22: =IFERROR(__xludf.DUMMYFUNCTION("""COMPUTED_VALUE"""),"Банан Кокос ") -> Банан Кокос | C22: =IFERROR(__xludf.DUMMYFUNCTION("""COMPUTED_VALUE"""),"Барбарисовый Энергетик ") -> Барбарисовый Энергетик | D22: =IFERROR(__xludf.DUMMYFUNCTION("""COMPUTED_VALUE"""),"Виноградный Энергетик") -> Виноградный Энергетик | E22: =IFERROR(__xludf.DUMMYFUNCTION("""COMPUTED_VALUE"""),"Гранат Клубника ") -> Гранат Клубника | F22: =IFERROR(__xludf.DUMMYFUNCTION("""COMPUTED_VALUE"""),"Гранат Смородина ") -> Гранат Смородина | G22: =IFERROR(__xludf.DUMMYFUNCTION("""COMPUTED_VALUE"""),"Грейпфрутовый Швепс ") -> Грейпфрутовый Швепс | H22: =IFERROR(__xludf.DUMMYFUNCTION("""COMPUTED_VALUE"""),"Земляника Драгонфрут ") -> Земляника Драгонфрут | I22: =IFERROR(__xludf.DUMMYFUNCTION("""COMPUTED_VALUE"""),"Киви Личи ") -> Киви Личи | J22: =IFERROR(__xludf.DUMMYFUNCTION("""COMPUTED_VALUE"""),"Киви Маракуйя Гуава ") -> Киви Маракуйя Гуава | K22: =IFERROR(__xludf.DUMMYFUNCTION("""COMPUTED_VALUE"""),"Клубника Банан ") -> Клубника Банан | L22: =IFERROR(__xludf.DUMMYFUNCTION("""COMPUTED_VALUE"""),"Клубника Вишня ") -> Клубника Вишня | M22: =IFERROR(__xludf.DUMMYFUNCTION("""COMPUTED_VALUE"""),"Клубника Земляника ") -> Клубника Земляника | N22: =IFERROR(__xludf.DUMMYFUNCTION("""COMPUTED_VALUE"""),"Клубничный Мохито ") -> Клубничный Мохито | O22: =IFERROR(__xludf.DUMMYFUNCTION("""COMPUTED_VALUE"""),"Манго Грейпфрут ") -> Манго Грейпфрут | P22: =IFERROR(__xludf.DUMMYFUNCTION("""COMPUTED_VALUE"""),"Манго Персик Личи ") -> Манго Персик Личи | Q22: =IFERROR(__xludf.DUMMYFUNCTION("""COMPUTED_VALUE"""),"Персик Бабл Гам ") -> Персик Бабл Гам | R22: =IFERROR(__xludf.DUMMYFUNCTION("""COMPUTED_VALUE"""),"Садовые Ягоды ") -> Садовые Ягоды | S22: =IFERROR(__xludf.DUMMYFUNCTION("""COMPUTED_VALUE"""),"Скитлс Лимон Лайм 2") -> Скитлс Лимон Лайм 2 | T22: =IFERROR(__xludf.DUMMYFUNCTION("""COMPUTED_VALUE"""),"Смородина Мармелад 1") -> Смородина Мармелад 1 | U22: =IFERROR(__xludf.DUMMYFUNCTION("""COMPUTED_VALUE"""),"Темная Вишня 1") -> Темная Вишня 1 | V22: =IFERROR(__xludf.DUMMYFUNCTION("""COMPUTED_VALUE"""),"Фруктовые Пластинки 1") -> Фруктовые Пластинки 1 | W22: =IFERROR(__xludf.DUMMYFUNCTION("""COMPUTED_VALUE"""),"Черника Ежевика 1") -> Черника Ежевика 1 | X22: =IFERROR(__xludf.DUMMYFUNCTION("""COMPUTED_VALUE"""),"Черника Малина 1") -> Черника Малина 1 | Y22: =IFERROR(__xludf.DUMMYFUNCTION("""COMPUTED_VALUE"""),"Черника Мята 2") -> Черника Мята 2 | Z22: =IFERROR(__xludf.DUMMYFUNCTION("""COMPUTED_VALUE"""),"Яблоко Виноград 2") -> Яблоко Виноград 2 | AA22: =IFERROR(__xludf.DUMMYFUNCTION("""COMPUTED_VALUE"""),"Яблоко Малина 4") -> Яблоко Малина 4
A23: =IFERROR(__xludf.DUMMYFUNCTION("""COMPUTED_VALUE"""),"0.4") -> 0.4 | B23: =IFERROR(__xludf.DUMMYFUNCTION("""COMPUTED_VALUE"""),"0.6") -> 0.6 | C23: =IFERROR(__xludf.DUMMYFUNCTION("""COMPUTED_VALUE"""),"0.7") -> 0.7 | D23: =IFERROR(__xludf.DUMMYFUNCTION("""COMPUTED_VALUE"""),"0.8") -> 0.8
A24: =IFERROR(__xludf.DUMMYFUNCTION("""COMPUTED_VALUE"""),"0.2") -> 0.2 | B24: =IFERROR(__xludf.DUMMYFUNCTION("""COMPUTED_VALUE"""),"0.3") -> 0.3
A25: =IFERROR(__xludf.DUMMYFUNCTION("""COMPUTED_VALUE"""),"Ягодный микс") -> Ягодный микс | B25: =IFERROR(__xludf.DUMMYFUNCTION("""COMPUTED_VALUE"""),"Энергетик малина") -> Энергетик малина | C25: =IFERROR(__xludf.DUMMYFUNCTION("""COMPUTED_VALUE"""),"Клубника арбуз") -> Клубника арбуз | D25: =IFERROR(__xludf.DUMMYFUNCTION("""COMPUTED_VALUE"""),"Ежевика малина") -> Ежевика малина | E25: =IFERROR(__xludf.DUMMYFUNCTION("""COMPUTED_VALUE"""),"Голубая малина виноград") -> Голубая малина виноград | F25: =IFERROR(__xludf.DUMMYFUNCTION("""COMPUTED_VALUE"""),"Вишня яблоко") -> Вишня яблоко | G25: =IFERROR(__xludf.DUMMYFUNCTION("""COMPUTED_VALUE"""),"Виноград лёд") -> Виноград лёд | H25: =IFERROR(__xludf.DUMMYFUNCTION("""COMPUTED_VALUE"""),"Бабл гам") -> Бабл гам | I25: =IFERROR(__xludf.DUMMYFUNCTION("""COMPUTED_VALUE"""),"Энергетик лайм") -> Энергетик лайм | J25: =IFERROR(__xludf.DUMMYFUNCTION("""COMPUTED_VALUE"""),"Черника смородина айс") -> Черника смородина айс | K25: =IFERROR(__xludf.DUMMYFUNCTION("""COMPUTED_VALUE"""),"Мохито клубничный лёд") -> Мохито клубничный лёд | L25: =IFERROR(__xludf.DUMMYFUNCTION("""COMPUTED_VALUE"""),"Черная вишня лёд") -> Черная вишня лёд | M25: =IFERROR(__xludf.DUMMYFUNCTION("""COMPUTED_VALUE"""),"Ананас кокос лёд") -> Ананас кокос лёд | N25: =IFERROR(__xludf.DUMMYFUNCTION("""COMPUTED_VALUE"""),"Киви лёд") -> Киви лёд | O25: =IFERROR(__xludf.DUMMYFUNCTION("""COMPUTED_VALUE"""),"Кислая клюква лёд") -> Кислая клюква лёд | P25: =IFERROR(__xludf.DUMMYFUNCTION("""COMPUTED_VALUE"""),"Кислый скитлс лёд") -> Кислый скитлс лёд | Q25: =IFERROR(__xludf.DUMMYFUNCTION("""COMPUTED_VALUE"""),"Клубника черника лёд") -> Клубника черника лёд | R25: =IFERROR(__xludf.DUMMYFUNCTION("""COMPUTED_VALUE"""),"Малина смородина лёд") -> Малина смородина лёд | S25: =IFERROR(__xludf.DUMMYFUNCTION("""COMPUTED_VALUE"""),"Манго лёд") -> Манго лёд | T25: =IFERROR(__xludf.DUMMYFUNCTION("""COMPUTED_VALUE"""),"Малина вишня лёд") -> Малина вишня лёд
A26: =IFERROR(__xludf.DUMMYFUNCTION("""COMPUTED_VALUE"""),"Арбуз Малина ") -> Арбуз Малина | B26: =IFERROR(__xludf.DUMMYFUNCTION("""COMPUTED_VALUE"""),"Банан Кокос ") -> Банан Кокос | C26: =IFERROR(__xludf.DUMMYFUNCTION("""COMPUTED_VALUE"""),"Барбарисовый Энергетик ") -> Барбарисовый Энергетик | D26: =IFERROR(__xludf.DUMMYFUNCTION("""COMPUTED_VALUE"""),"Виноградный Энергетик") -> Виноградный Энергетик | E26: =IFERROR(__xludf.DUMMYFUNCTION("""COMPUTED_VALUE"""),"Гранат Клубника ") -> Гранат Клубника | F26: =IFERROR(__xludf.DUMMYFUNCTION("""COMPUTED_VALUE"""),"Гранат Смородина ") -> Гранат Смородина | G26: =IFERROR(__xludf.DUMMYFUNCTION("""COMPUTED_VALUE"""),"Грейпфрутовый Швепс ") -> Грейпфрутовый Швепс | H26: =IFERROR(__xludf.DUMMYFUNCTION("""COMPUTED_VALUE"""),"Земляника Драгонфрут ") -> Земляника Драгонфрут | I26: =IFERROR(__xludf.DUMMYFUNCTION("""COMPUTED_VALUE"""),"Киви Личи ") -> Киви Личи | J26: =IFERROR(__xludf.DUMMYFUNCTION("""COMPUTED_VALUE"""),"Киви Маракуйя Гуава ") -> Киви Маракуйя Гуава | K26: =IFERROR(__xludf.DUMMYFUNCTION("""COMPUTED_VALUE"""),"Клубника Банан ") -> Клубника Банан | L26: =IFERROR(__xludf.DUMMYFUNCTION("""COMPUTED_VALUE"""),"Клубника Вишня ") -> Клубника Вишня | M26: =IFERROR(__xludf.DUMMYFUNCTION("""COMPUTED_VALUE"""),"Клубника Земляника ") -> Клубника Земляника | N26: =IFERROR(__xludf.DUMMYFUNCTION("""COMPUTED_VALUE"""),"Клубничный Мохито ") -> Клубничный Мохито | O26: =IFERROR(__xludf.DUMMYFUNCTION("""COMPUTED_VALUE"""),"Манго Грейпфрут ") -> Манго Грейпфрут | P26: =IFERROR(__xludf.DUMMYFUNCTION("""COMPUTED_VALUE"""),"Манго Персик Личи ") -> Манго Персик Личи | Q26: =IFERROR(__xludf.DUMMYFUNCTION("""COMPUTED_VALUE"""),"Персик Бабл Гам ") -> Персик Бабл Гам | R26: =IFERROR(__xludf.DUMMYFUNCTION("""COMPUTED_VALUE"""),"Садовые Ягоды ") -> Садовые Ягоды | S26: =IFERROR(__xludf.DUMMYFUNCTION("""COMPUTED_VALUE"""),"Скитлс Лимон Лайм 2") -> Скитлс Лимон Лайм 2 | T26: =IFERROR(__xludf.DUMMYFUNCTION("""COMPUTED_VALUE"""),"Смородина Мармелад 1") -> Смородина Мармелад 1 | U26: =IFERROR(__xludf.DUMMYFUNCTION("""COMPUTED_VALUE"""),"Темная Вишня 1") -> Темная Вишня 1 | V26: =IFERROR(__xludf.DUMMYFUNCTION("""COMPUTED_VALUE"""),"Фруктовые Пластинки 1") -> Фруктовые Пластинки 1 | W26: =IFERROR(__xludf.DUMMYFUNCTION("""COMPUTED_VALUE"""),"Черника Ежевика 1") -> Черника Ежевика 1 | X26: =IFERROR(__xludf.DUMMYFUNCTION("""COMPUTED_VALUE"""),"Черника Малина 1") -> Черника Малина 1 | Y26: =IFERROR(__xludf.DUMMYFUNCTION("""COMPUTED_VALUE"""),"Черника Мята 2") -> Черника Мята 2 | Z26: =IFERROR(__xludf.DUMMYFUNCTION("""COMPUTED_VALUE"""),"Яблоко Виноград 2") -> Яблоко Виноград 2 | AA26: =IFERROR(__xludf.DUMMYFUNCTION("""COMPUTED_VALUE"""),"Яблоко Малина 4") -> Яблоко Малина 4
A27: =IFERROR(__xludf.DUMMYFUNCTION("""COMPUTED_VALUE"""),"Арбуз Малина ") -> Арбуз Малина | B27: =IFERROR(__xludf.DUMMYFUNCTION("""COMPUTED_VALUE"""),"Банан Кокос ") -> Банан Кокос | C27: =IFERROR(__xludf.DUMMYFUNCTION("""COMPUTED_VALUE"""),"Барбарисовый Энергетик ") -> Барбарисовый Энергетик | D27: =IFERROR(__xludf.DUMMYFUNCTION("""COMPUTED_VALUE"""),"Виноградный Энергетик") -> Виноградный Энергетик | E27: =IFERROR(__xludf.DUMMYFUNCTION("""COMPUTED_VALUE"""),"Гранат Клубника ") -> Гранат Клубника | F27: =IFERROR(__xludf.DUMMYFUNCTION("""COMPUTED_VALUE"""),"Гранат Смородина ") -> Гранат Смородина | G27: =IFERROR(__xludf.DUMMYFUNCTION("""COMPUTED_VALUE"""),"Грейпфрутовый Швепс ") -> Грейпфрутовый Швепс | H27: =IFERROR(__xludf.DUMMYFUNCTION("""COMPUTED_VALUE"""),"Земляника Драгонфрут ") -> Земляника Драгонфрут | I27: =IFERROR(__xludf.DUMMYFUNCTION("""COMPUTED_VALUE"""),"Киви Личи ") -> Киви Личи | J27: =IFERROR(__xludf.DUMMYFUNCTION("""COMPUTED_VALUE"""),"Киви Маракуйя Гуава ") -> Киви Маракуйя Гуава | K27: =IFERROR(__xludf.DUMMYFUNCTION("""COMPUTED_VALUE"""),"Клубника Банан ") -> Клубника Банан | L27: =IFERROR(__xludf.DUMMYFUNCTION("""COMPUTED_VALUE"""),"Клубника Вишня ") -> Клубника Вишня | M27: =IFERROR(__xludf.DUMMYFUNCTION("""COMPUTED_VALUE"""),"Клубника Земляника ") -> Клубника Земляника | N27: =IFERROR(__xludf.DUMMYFUNCTION("""COMPUTED_VALUE"""),"Клубничный Мохито ") -> Клубничный Мохито | O27: =IFERROR(__xludf.DUMMYFUNCTION("""COMPUTED_VALUE"""),"Манго Грейпфрут ") -> Манго Грейпфрут | P27: =IFERROR(__xludf.DUMMYFUNCTION("""COMPUTED_VALUE"""),"Манго Персик Личи ") -> Манго Персик Личи | Q27: =IFERROR(__xludf.DUMMYFUNCTION("""COMPUTED_VALUE"""),"Персик Бабл Гам ") -> Персик Бабл Гам | R27: =IFERROR(__xludf.DUMMYFUNCTION("""COMPUTED_VALUE"""),"Садовые Ягоды ") -> Садовые Ягоды | S27: =IFERROR(__xludf.DUMMYFUNCTION("""COMPUTED_VALUE"""),"Скитлс Лимон Лайм 2") -> Скитлс Лимон Лайм 2 | T27: =IFERROR(__xludf.DUMMYFUNCTION("""COMPUTED_VALUE"""),"Смородина Мармелад 1") -> Смородина Мармелад 1 | U27: =IFERROR(__xludf.DUMMYFUNCTION("""COMPUTED_VALUE"""),"Темная Вишня 1") -> Темная Вишня 1 | V27: =IFERROR(__xludf.DUMMYFUNCTION("""COMPUTED_VALUE"""),"Фруктовые Пластинки 1") -> Фруктовые Пластинки 1 | W27: =IFERROR(__xludf.DUMMYFUNCTION("""COMPUTED_VALUE"""),"Черника Ежевика 1") -> Черника Ежевика 1 | X27: =IFERROR(__xludf.DUMMYFUNCTION("""COMPUTED_VALUE"""),"Черника Малина 1") -> Черника Малина 1 | Y27: =IFERROR(__xludf.DUMMYFUNCTION("""COMPUTED_VALUE"""),"Черника Мята 2") -> Черника Мята 2 | Z27: =IFERROR(__xludf.DUMMYFUNCTION("""COMPUTED_VALUE"""),"Яблоко Виноград 2") -> Яблоко Виноград 2 | AA27: =IFERROR(__xludf.DUMMYFUNCTION("""COMPUTED_VALUE"""),"Яблоко Малина 4") -> Яблоко Малина 4
A28: =IFERROR(__xludf.DUMMYFUNCTION("""COMPUTED_VALUE"""),"Ягодный микс") -> Ягодный микс | B28: =IFERROR(__xludf.DUMMYFUNCTION("""COMPUTED_VALUE"""),"Энергетик малина") -> Энергетик малина | C28: =IFERROR(__xludf.DUMMYFUNCTION("""COMPUTED_VALUE"""),"Клубника арбуз") -> Клубника арбуз | D28: =IFERROR(__xludf.DUMMYFUNCTION("""COMPUTED_VALUE"""),"Ежевика малина") -> Ежевика малина | E28: =IFERROR(__xludf.DUMMYFUNCTION("""COMPUTED_VALUE"""),"Голубая малина виноград") -> Голубая малина виноград | F28: =IFERROR(__xludf.DUMMYFUNCTION("""COMPUTED_VALUE"""),"Вишня яблоко") -> Вишня яблоко | G28: =IFERROR(__xludf.DUMMYFUNCTION("""COMPUTED_VALUE"""),"Виноград лёд") -> Виноград лёд | H28: =IFERROR(__xludf.DUMMYFUNCTION("""COMPUTED_VALUE"""),"Бабл гам") -> Бабл гам | I28: =IFERROR(__xludf.DUMMYFUNCTION("""COMPUTED_VALUE"""),"Энергетик лайм") -> Энергетик лайм | J28: =IFERROR(__xludf.DUMMYFUNCTION("""COMPUTED_VALUE"""),"Черника смородина айс") -> Черника смородина айс | K28: =IFERROR(__xludf.DUMMYFUNCTION("""COMPUTED_VALUE"""),"Мохито клубничный лёд") -> Мохито клубничный лёд | L28: =IFERROR(__xludf.DUMMYFUNCTION("""COMPUTED_VALUE"""),"Черная вишня лёд") -> Черная вишня лёд | M28: =IFERROR(__xludf.DUMMYFUNCTION("""COMPUTED_VALUE"""),"Ананас кокос лёд") -> Ананас кокос лёд | N28: =IFERROR(__xludf.DUMMYFUNCTION("""COMPUTED_VALUE"""),"Киви лёд") -> Киви лёд | O28: =IFERROR(__xludf.DUMMYFUNCTION("""COMPUTED_VALUE"""),"Кислая клюква лёд") -> Кислая клюква лёд | P28: =IFERROR(__xludf.DUMMYFUNCTION("""COMPUTED_VALUE"""),"Кислый скитлс лёд") -> Кислый скитлс лёд | Q28: =IFERROR(__xludf.DUMMYFUNCTION("""COMPUTED_VALUE"""),"Клубника черника лёд") -> Клубника черника лёд | R28: =IFERROR(__xludf.DUMMYFUNCTION("""COMPUTED_VALUE"""),"Малина смородина лёд") -> Малина смородина лёд | S28: =IFERROR(__xludf.DUMMYFUNCTION("""COMPUTED_VALUE"""),"Манго лёд") -> Манго лёд | T28: =IFERROR(__xludf.DUMMYFUNCTION("""COMPUTED_VALUE"""),"Малина вишня лёд") -> Малина вишня лёд
A29: =IFERROR(__xludf.DUMMYFUNCTION("""COMPUTED_VALUE"""),"Апельсиновое драже") -> Апельсиновое драже | B29: =IFERROR(__xludf.DUMMYFUNCTION("""COMPUTED_VALUE"""),"Бабл гам") -> Бабл гам | C29: =IFERROR(__xludf.DUMMYFUNCTION("""COMPUTED_VALUE"""),"Виноградная конфета") -> Виноградная конфета | D29: =IFERROR(__xludf.DUMMYFUNCTION("""COMPUTED_VALUE"""),"Даня кокос") -> Даня кокос | E29: =IFERROR(__xludf.DUMMYFUNCTION("""COMPUTED_VALUE"""),"Земляника груша") -> Земляника груша | F29: =IFERROR(__xludf.DUMMYFUNCTION("""COMPUTED_VALUE"""),"Кислый киви") -> Кислый киви | G29: =IFERROR(__xludf.DUMMYFUNCTION("""COMPUTED_VALUE"""),"Кислый малиновый лимонад ") -> Кислый малиновый лимонад | H29: =IFERROR(__xludf.DUMMYFUNCTION("""COMPUTED_VALUE"""),"Кола сода айс") -> Кола сода айс | I29: =IFERROR(__xludf.DUMMYFUNCTION("""COMPUTED_VALUE"""),"Ледяной ананас") -> Ледяной ананас | J29: =IFERROR(__xludf.DUMMYFUNCTION("""COMPUTED_VALUE"""),"Лимонные червячки ") -> Лимонные червячки | K29: =IFERROR(__xludf.DUMMYFUNCTION("""COMPUTED_VALUE"""),"Манго апельсин") -> Манго апельсин | L29: =IFERROR(__xludf.DUMMYFUNCTION("""COMPUTED_VALUE"""),"Смородина виноград") -> Смородина виноград | M29: =IFERROR(__xludf.DUMMYFUNCTION("""COMPUTED_VALUE"""),"Яблочный холс") -> Яблочный холс | N29: =IFERROR(__xludf.DUMMYFUNCTION("""COMPUTED_VALUE"""),"Ягодный смузи") -> Ягодный смузи | O29: =IFERROR(__xludf.DUMMYFUNCTION("""COMPUTED_VALUE"""),"Ягодный энергетик") -> Ягодный энергетик
A30: =IFERROR(__xludf.DUMMYFUNCTION("""COMPUTED_VALUE"""),"Лесные ягоды") -> Лесные ягоды | B30: =IFERROR(__xludf.DUMMYFUNCTION("""COMPUTED_VALUE"""),"Алоэ виноград ") -> Алоэ виноград | C30: =IFERROR(__xludf.DUMMYFUNCTION("""COMPUTED_VALUE"""),"Апельсиновый адреналин") -> Апельсиновый адреналин | D30: =IFERROR(__xludf.DUMMYFUNCTION("""COMPUTED_VALUE"""),"Клюква лайм") -> Клюква лайм | E30: =IFERROR(__xludf.DUMMYFUNCTION("""COMPUTED_VALUE"""),"Виноградная фанта ") -> Виноградная фанта | F30: =IFERROR(__xludf.DUMMYFUNCTION("""COMPUTED_VALUE"""),"Зеленый чай лемонграсс") -> Зеленый чай лемонграсс | G30: =IFERROR(__xludf.DUMMYFUNCTION("""COMPUTED_VALUE"""),"Малина арбуз") -> Малина арбуз | H30: =IFERROR(__xludf.DUMMYFUNCTION("""COMPUTED_VALUE"""),"Ананас персик") -> Ананас персик | I30: =IFERROR(__xludf.DUMMYFUNCTION("""COMPUTED_VALUE"""),"Клубничный мохито ") -> Клубничный мохито | J30: =IFERROR(__xludf.DUMMYFUNCTION("""COMPUTED_VALUE"""),"Яблоко лайм") -> Яблоко лайм | K30: =IFERROR(__xludf.DUMMYFUNCTION("""COMPUTED_VALUE"""),"Спрайт арбуз лайм ") -> Спрайт арбуз лайм | L30: =IFERROR(__xludf.DUMMYFUNCTION("""COMPUTED_VALUE"""),"Черничная фанта") -> Черничная фанта | M30: =IFERROR(__xludf.DUMMYFUNCTION("""COMPUTED_VALUE"""),"Чёрная смородина") -> Чёрная смородина | N30: =IFERROR(__xludf.DUMMYFUNCTION("""COMPUTED_VALUE"""),"Червячки голубика малина") -> Червячки голубика малина | O30: =IFERROR(__xludf.DUMMYFUNCTION("""COMPUTED_VALUE"""),"Малина смородина ") -> Малина смородина | P30: =IFERROR(__xludf.DUMMYFUNCTION("""COMPUTED_VALUE"""),"Черника лайм ") -> Черника лайм | Q30: =IFERROR(__xludf.DUMMYFUNCTION("""COMPUTED_VALUE"""),"Виноградный чупа чупс") -> Виноградный чупа чупс | R30: =IFERROR(__xludf.DUMMYFUNCTION("""COMPUTED_VALUE"""),"Киви лайм") -> Киви лайм | S30: =IFERROR(__xludf.DUMMYFUNCTION("""COMPUTED_VALUE"""),"Ягодный морс") -> Ягодный морс | T30: =IFERROR(__xludf.DUMMYFUNCTION("""COMPUTED_VALUE"""),"Фруктовый скитлс") -> Фруктовый скитлс | U30: =IFERROR(__xludf.DUMMYFUNCTION("""COMPUTED_VALUE"""),"черника лимон ") -> черника лимон | V30: =IFERROR(__xludf.DUMMYFUNCTION("""COMPUTED_VALUE"""),"Вишнёвая бомба") -> Вишнёвая бомба | W30: =IFERROR(__xludf.DUMMYFUNCTION("""COMPUTED_VALUE"""),"Тропический манго") -> Тропический манго
A31: =IFERROR(__xludf.DUMMYFUNCTION("""COMPUTED_VALUE"""),"Кислый малиново-грейпфрутовый швепс") -> Кислый малиново-грейпфрутовый швепс | B31: =IFERROR(__xludf.DUMMYFUNCTION("""COMPUTED_VALUE"""),"Ананас апельсин") -> Ананас апельсин | C31: =IFERROR(__xludf.DUMMYFUNCTION("""COMPUTED_VALUE"""),"Пинаколада") -> Пинаколада | D31: =IFERROR(__xludf.DUMMYFUNCTION("""COMPUTED_VALUE"""),"Мятный бабл гам") -> Мятный бабл гам | E31: =IFERROR(__xludf.DUMMYFUNCTION("""COMPUTED_VALUE"""),"Мянго драгонфрут") -> Мянго драгонфрут | F31: =IFERROR(__xludf.DUMMYFUNCTION("""COMPUTED_VALUE"""),"Клубничная фанта") -> Клубничная фанта | G31: =IFERROR(__xludf.DUMMYFUNCTION("""COMPUTED_VALUE"""),"Клубничная арбуз") -> Клубничная арбуз | H31: =IFERROR(__xludf.DUMMYFUNCTION("""COMPUTED_VALUE"""),"Кислый скитлс") -> Кислый скитлс | I31: =IFERROR(__xludf.DUMMYFUNCTION("""COMPUTED_VALUE"""),"Кислый лайм арбуз") -> Кислый лайм арбуз | J31: =IFERROR(__xludf.DUMMYFUNCTION("""COMPUTED_VALUE"""),"Тропический банан") -> Тропический банан | K31: =IFERROR(__xludf.DUMMYFUNCTION("""COMPUTED_VALUE"""),"Яблочный энергетик") -> Яблочный энергетик | L31: =IFERROR(__xludf.DUMMYFUNCTION("""COMPUTED_VALUE"""),"Барбарисовый лимонад") -> Барбарисовый лимонад | M31: =IFERROR(__xludf.DUMMYFUNCTION("""COMPUTED_VALUE"""),"Лимонад виноград вишня") -> Лимонад виноград вишня | N31: =IFERROR(__xludf.DUMMYFUNCTION("""COMPUTED_VALUE"""),"Розовый лимонад") -> Розовый лимонад | O31: =IFERROR(__xludf.DUMMYFUNCTION("""COMPUTED_VALUE"""),"Двойной манго") -> Двойной манго | P31: =IFERROR(__xludf.DUMMYFUNCTION("""COMPUTED_VALUE"""),"Лесные ягоды ") -> Лесные ягоды | Q31: =IFERROR(__xludf.DUMMYFUNCTION("""COMPUTED_VALUE"""),"Ежевика малина ") -> Ежевика малина | R31: =IFERROR(__xludf.DUMMYFUNCTION("""COMPUTED_VALUE"""),"Смородиновый лимонад") -> Смородиновый лимонад | S31: =IFERROR(__xludf.DUMMYFUNCTION("""COMPUTED_VALUE"""),"Кола вишня") -> Кола вишня | T31: =IFERROR(__xludf.DUMMYFUNCTION("""COMPUTED_VALUE"""),"Манго арбуз") -> Манго арбуз | U31: =IFERROR(__xludf.DUMMYFUNCTION("""COMPUTED_VALUE"""),"Алоэ виноград") -> Алоэ виноград | V31: =IFERROR(__xludf.DUMMYFUNCTION("""COMPUTED_VALUE"""),"Банан клубника") -> Банан клубника | W31: =IFERROR(__xludf.DUMMYFUNCTION("""COMPUTED_VALUE"""),"Малиновый мармелад") -> Малиновый мармелад | X31: =IFERROR(__xludf.DUMMYFUNCTION("""COMPUTED_VALUE"""),"Клубника киви") -> Клубника киви | Y31: =IFERROR(__xludf.DUMMYFUNCTION("""COMPUTED_VALUE"""),"Клюква лайм") -> Клюква лайм | Z31: =IFERROR(__xludf.DUMMYFUNCTION("""COMPUTED_VALUE"""),"Гуава ананас") -> Гуава ананас | AA31: =IFERROR(__xludf.DUMMYFUNCTION("""COMPUTED_VALUE"""),"Морс") -> Морс | AB31: =IFERROR(__xludf.DUMMYFUNCTION("""COMPUTED_VALUE"""),"Красный апельсин") -> Красный апельсин | AC31: =IFERROR(__xludf.DUMMYFUNCTION("""COMPUTED_VALUE"""),"Арбузная жвачка") -> Арбузная жвачка | AD31: =IFERROR(__xludf.DUMMYFUNCTION("""COMPUTED_VALUE"""),"Смородина Виноград") -> Смородина Виноград | AE31: =IFERROR(__xludf.DUMMYFUNCTION("""COMPUTED_VALUE"""),"Гранатовая Мармелад") -> Гранатовая Мармелад | AF31: =IFERROR(__xludf.DUMMYFUNCTION("""COMPUTED_VALUE"""),"Яблоко Киви") -> Яблоко Киви | AG31: =IFERROR(__xludf.DUMMYFUNCTION("""COMPUTED_VALUE"""),"Клубника Ежевика") -> Клубника Ежевика | AH31: =IFERROR(__xludf.DUMMYFUNCTION("""COMPUTED_VALUE"""),"Клубничный Коктейль") -> Клубничный Коктейль | AI31: =IFERROR(__xludf.DUMMYFUNCTION("""COMPUTED_VALUE"""),"Клюква Земляника ") -> Клюква Земляника | AJ31: =IFERROR(__xludf.DUMMYFUNCTION("""COMPUTED_VALUE"""),"Какос Дыня") -> Какос Дыня | AK31: =IFERROR(__xludf.DUMMYFUNCTION("""COMPUTED_VALUE"""),"Маракуйя мандарин") -> Маракуйя мандарин | AL31: =IFERROR(__xludf.DUMMYFUNCTION("""COMPUTED_VALUE"""),"Персик кактус") -> Персик кактус | AM31: =IFERROR(__xludf.DUMMYFUNCTION("""COMPUTED_VALUE"""),"Спрайт") -> Спрайт | AN31: =IFERROR(__xludf.DUMMYFUNCTION("""COMPUTED_VALUE"""),"Черничная фанта") -> Черничная фанта | AO31: =IFERROR(__xludf.DUMMYFUNCTION("""COMPUTED_VALUE"""),"Ягодная жвачка") -> Ягодная жвачка | AP31: =IFERROR(__xludf.DUMMYFUNCTION("""COMPUTED_VALUE"""),"Ягодный энергетик") -> Ягодный энергетик | AQ31: =IFERROR(__xludf.DUMMYFUNCTION("""COMPUTED_VALUE"""),"Ягодный пунш ") -> Ягодный пунш | AR31: =IFERROR(__xludf.DUMMYFUNCTION("""COMPUTED_VALUE"""),"Виноградный холс") -> Виноградный холс | AS31: =IFERROR(__xludf.DUMMYFUNCTION("""COMPUTED_VALUE"""),"Грейпфрут смородина") -> Грейпфрут смородина | AT31: =IFERROR(__xludf.DUMMYFUNCTION("""COMPUTED_VALUE"""),"Дыня персик") -> Дыня персик | AU31: =IFERROR(__xludf.DUMMYFUNCTION("""COMPUTED_VALUE"""),"Земляника виноград") -> Земляника виноград | AV31: =IFERROR(__xludf.DUMMYFUNCTION("""COMPUTED_VALUE"""),"Киви маракуйя гуава") -> Киви маракуйя гуава | AW31: =IFERROR(__xludf.DUMMYFUNCTION("""COMPUTED_VALUE"""),"Кислые вишнёвые червячки") -> Кислые вишнёвые червячки | AX31: =IFERROR(__xludf.DUMMYFUNCTION("""COMPUTED_VALUE"""),"Кислые чернично-малиновое червячки") -> Кислые чернично-малиновое червячки
A32: =IFERROR(__xludf.DUMMYFUNCTION("""COMPUTED_VALUE"""),"Ягодный микс") -> Ягодный микс | B32: =IFERROR(__xludf.DUMMYFUNCTION("""COMPUTED_VALUE"""),"Энергетик малина") -> Энергетик малина | C32: =IFERROR(__xludf.DUMMYFUNCTION("""COMPUTED_VALUE"""),"Клубника арбуз") -> Клубника арбуз | D32: =IFERROR(__xludf.DUMMYFUNCTION("""COMPUTED_VALUE"""),"Ежевика малина") -> Ежевика малина | E32: =IFERROR(__xludf.DUMMYFUNCTION("""COMPUTED_VALUE"""),"Голубая малина виноград") -> Голубая малина виноград | F32: =IFERROR(__xludf.DUMMYFUNCTION("""COMPUTED_VALUE"""),"Вишня яблоко") -> Вишня яблоко | G32: =IFERROR(__xludf.DUMMYFUNCTION("""COMPUTED_VALUE"""),"Виноград лёд") -> Виноград лёд | H32: =IFERROR(__xludf.DUMMYFUNCTION("""COMPUTED_VALUE"""),"Бабл гам") -> Бабл гам | I32: =IFERROR(__xludf.DUMMYFUNCTION("""COMPUTED_VALUE"""),"Энергетик лайм") -> Энергетик лайм | J32: =IFERROR(__xludf.DUMMYFUNCTION("""COMPUTED_VALUE"""),"Черника смородина айс") -> Черника смородина айс | K32: =IFERROR(__xludf.DUMMYFUNCTION("""COMPUTED_VALUE"""),"Мохито клубничный лёд") -> Мохито клубничный лёд | L32: =IFERROR(__xludf.DUMMYFUNCTION("""COMPUTED_VALUE"""),"Черная вишня лёд") -> Черная вишня лёд | M32: =IFERROR(__xludf.DUMMYFUNCTION("""COMPUTED_VALUE"""),"Ананас кокос лёд") -> Ананас кокос лёд | N32: =IFERROR(__xludf.DUMMYFUNCTION("""COMPUTED_VALUE"""),"Киви лёд") -> Киви лёд | O32: =IFERROR(__xludf.DUMMYFUNCTION("""COMPUTED_VALUE"""),"Кислая клюква лёд") -> Кислая клюква лёд | P32: =IFERROR(__xludf.DUMMYFUNCTION("""COMPUTED_VALUE"""),"Кислый скитлс лёд") -> Кислый скитлс лёд | Q32: =IFERROR(__xludf.DUMMYFUNCTION("""COMPUTED_VALUE"""),"Клубника черника лёд") -> Клубника черника лёд | R32: =IFERROR(__xludf.DUMMYFUNCTION("""COMPUTED_VALUE"""),"Малина смородина лёд") -> Малина смородина лёд | S32: =IFERROR(__xludf.DUMMYFUNCTION("""COMPUTED_VALUE"""),"Манго лёд") -> Манго лёд | T32: =IFERROR(__xludf.DUMMYFUNCTION("""COMPUTED_VALUE"""),"Малина вишня лёд") -> Малина вишня лёд
A33: =IFERROR(__xludf.DUMMYFUNCTION("""COMPUTED_VALUE"""),"Лесные ягоды") -> Лесные ягоды | B33: =IFERROR(__xludf.DUMMYFUNCTION("""COMPUTED_VALUE"""),"Алоэ виноград ") -> Алоэ виноград | C33: =IFERROR(__xludf.DUMMYFUNCTION("""COMPUTED_VALUE"""),"Апельсиновый адреналин") -> Апельсиновый адреналин | D33: =IFERROR(__xludf.DUMMYFUNCTION("""COMPUTED_VALUE"""),"Клюква лайм") -> Клюква лайм | E33: =IFERROR(__xludf.DUMMYFUNCTION("""COMPUTED_VALUE"""),"Виноградная фанта ") -> Виноградная фанта | F33: =IFERROR(__xludf.DUMMYFUNCTION("""COMPUTED_VALUE"""),"Зеленый чай лемонграсс") -> Зеленый чай лемонграсс | G33: =IFERROR(__xludf.DUMMYFUNCTION("""COMPUTED_VALUE"""),"Малина арбуз") -> Малина арбуз | H33: =IFERROR(__xludf.DUMMYFUNCTION("""COMPUTED_VALUE"""),"Ананас персик") -> Ананас персик | I33: =IFERROR(__xludf.DUMMYFUNCTION("""COMPUTED_VALUE"""),"Клубничный мохито ") -> Клубничный мохито | J33: =IFERROR(__xludf.DUMMYFUNCTION("""COMPUTED_VALUE"""),"Яблоко лайм") -> Яблоко лайм | K33: =IFERROR(__xludf.DUMMYFUNCTION("""COMPUTED_VALUE"""),"Спрайт арбуз лайм ") -> Спрайт арбуз лайм | L33: =IFERROR(__xludf.DUMMYFUNCTION("""COMPUTED_VALUE"""),"Черничная фанта") -> Черничная фанта | M33: =IFERROR(__xludf.DUMMYFUNCTION("""COMPUTED_VALUE"""),"Чёрная смородина") -> Чёрная смородина | N33: =IFERROR(__xludf.DUMMYFUNCTION("""COMPUTED_VALUE"""),"Червячки голубика малина") -> Червячки голубика малина | O33: =IFERROR(__xludf.DUMMYFUNCTION("""COMPUTED_VALUE"""),"Малина смородина ") -> Малина смородина | P33: =IFERROR(__xludf.DUMMYFUNCTION("""COMPUTED_VALUE"""),"Черника лайм ") -> Черника лайм | Q33: =IFERROR(__xludf.DUMMYFUNCTION("""COMPUTED_VALUE"""),"Виноградный чупа чупс") -> Виноградный чупа чупс | R33: =IFERROR(__xludf.DUMMYFUNCTION("""COMPUTED_VALUE"""),"Киви лайм") -> Киви лайм | S33: =IFERROR(__xludf.DUMMYFUNCTION("""COMPUTED_VALUE"""),"Ягодный морс") -> Ягодный морс | T33: =IFERROR(__xludf.DUMMYFUNCTION("""COMPUTED_VALUE"""),"Фруктовый скитлс") -> Фруктовый скитлс | U33: =IFERROR(__xludf.DUMMYFUNCTION("""COMPUTED_VALUE"""),"черника лимон ") -> черника лимон | V33: =IFERROR(__xludf.DUMMYFUNCTION("""COMPUTED_VALUE"""),"Вишнёвая бомба") -> Вишнёвая бомба | W33: =IFERROR(__xludf.DUMMYFUNCTION("""COMPUTED_VALUE"""),"Тропический манго") -> Тропический манго
A34: =IFERROR(__xludf.DUMMYFUNCTION("""COMPUTED_VALUE"""),"Малина вишня лёд") -> Малина вишня лёд
A35: =IFERROR(__xludf.DUMMYFUNCTION("""COMPUTED_VALUE"""),"Ананас киви") -> Ананас киви | B35: =IFERROR(__xludf.DUMMYFUNCTION("""COMPUTED_VALUE"""),"Арбузный смузи") -> Арбузный смузи | C35: =IFERROR(__xludf.DUMMYFUNCTION("""COMPUTED_VALUE"""),"Виноградная фанта") -> Виноградная фанта | D35: =IFERROR(__xludf.DUMMYFUNCTION("""COMPUTED_VALUE"""),"Вишневый морс") -> Вишневый морс | E35: =IFERROR(__xludf.DUMMYFUNCTION("""COMPUTED_VALUE"""),"Гранатовый мармелад") -> Гранатовый мармелад | F35: =IFERROR(__xludf.DUMMYFUNCTION("""COMPUTED_VALUE"""),"Грейпфрут киви") -> Грейпфрут киви | G35: =IFERROR(__xludf.DUMMYFUNCTION("""COMPUTED_VALUE"""),"Ежевика мята") -> Ежевика мята | H35: =IFERROR(__xludf.DUMMYFUNCTION("""COMPUTED_VALUE"""),"Киви манго") -> Киви манго | I35: =IFERROR(__xludf.DUMMYFUNCTION("""COMPUTED_VALUE"""),"Клубника манго") -> Клубника манго | J35: =IFERROR(__xludf.DUMMYFUNCTION("""COMPUTED_VALUE"""),"черника грейфрут ") -> черника грейфрут | K35: =IFERROR(__xludf.DUMMYFUNCTION("""COMPUTED_VALUE"""),"Малина лайм") -> Малина лайм | L35: =IFERROR(__xludf.DUMMYFUNCTION("""COMPUTED_VALUE"""),"Манго арбуз ") -> Манго арбуз | M35: =IFERROR(__xludf.DUMMYFUNCTION("""COMPUTED_VALUE"""),"Малиновый чай с жасмином") -> Малиновый чай с жасмином | N35: =IFERROR(__xludf.DUMMYFUNCTION("""COMPUTED_VALUE"""),"малина апельсин ") -> малина апельсин | O35: =IFERROR(__xludf.DUMMYFUNCTION("""COMPUTED_VALUE"""),"Манго апельсин") -> Манго апельсин | P35: =IFERROR(__xludf.DUMMYFUNCTION("""COMPUTED_VALUE"""),"Ред булл") -> Ред булл | Q35: =IFERROR(__xludf.DUMMYFUNCTION("""COMPUTED_VALUE"""),"Спрайт") -> Спрайт | R35: =IFERROR(__xludf.DUMMYFUNCTION("""COMPUTED_VALUE"""),"ананас клюква ") -> ананас клюква | S35: =IFERROR(__xludf.DUMMYFUNCTION("""COMPUTED_VALUE"""),"Тархун") -> Тархун | T35: =IFERROR(__xludf.DUMMYFUNCTION("""COMPUTED_VALUE"""),"алоэ Виноград ") -> алоэ Виноград | U35: =IFERROR(__xludf.DUMMYFUNCTION("""COMPUTED_VALUE"""),"Фруктовая жвачка") -> Фруктовая жвачка | V35: =IFERROR(__xludf.DUMMYFUNCTION("""COMPUTED_VALUE"""),"Холодная кола") -> Холодная кола | W35: =IFERROR(__xludf.DUMMYFUNCTION("""COMPUTED_VALUE"""),"Черная смородина клюква") -> Черная смородина клюква | X35: =IFERROR(__xludf.DUMMYFUNCTION("""COMPUTED_VALUE"""),"Черника арбуз") -> Черника арбуз | Y35: =IFERROR(__xludf.DUMMYFUNCTION("""COMPUTED_VALUE"""),"Яблоко черника") -> Яблоко черника
A36: =IFERROR(__xludf.DUMMYFUNCTION("""COMPUTED_VALUE"""),"Ананас киви") -> Ананас киви | B36: =IFERROR(__xludf.DUMMYFUNCTION("""COMPUTED_VALUE"""),"Арбузный смузи") -> Арбузный смузи | C36: =IFERROR(__xludf.DUMMYFUNCTION("""COMPUTED_VALUE"""),"Виноградная фанта") -> Виноградная фанта | D36: =IFERROR(__xludf.DUMMYFUNCTION("""COMPUTED_VALUE"""),"Вишневый морс") -> Вишневый морс | E36: =IFERROR(__xludf.DUMMYFUNCTION("""COMPUTED_VALUE"""),"Гранатовый мармелад") -> Гранатовый мармелад | F36: =IFERROR(__xludf.DUMMYFUNCTION("""COMPUTED_VALUE"""),"Грейпфрут киви") -> Грейпфрут киви | G36: =IFERROR(__xludf.DUMMYFUNCTION("""COMPUTED_VALUE"""),"Ежевика мята") -> Ежевика мята | H36: =IFERROR(__xludf.DUMMYFUNCTION("""COMPUTED_VALUE"""),"Киви манго") -> Киви манго | I36: =IFERROR(__xludf.DUMMYFUNCTION("""COMPUTED_VALUE"""),"Клубника манго") -> Клубника манго | J36: =IFERROR(__xludf.DUMMYFUNCTION("""COMPUTED_VALUE"""),"черника грейфрут ") -> черника грейфрут | K36: =IFERROR(__xludf.DUMMYFUNCTION("""COMPUTED_VALUE"""),"Малина лайм") -> Малина лайм | L36: =IFERROR(__xludf.DUMMYFUNCTION("""COMPUTED_VALUE"""),"Манго арбуз ") -> Манго арбуз | M36: =IFERROR(__xludf.DUMMYFUNCTION("""COMPUTED_VALUE"""),"Малиновый чай с жасмином") -> Малиновый чай с жасмином | N36: =IFERROR(__xludf.DUMMYFUNCTION("""COMPUTED_VALUE"""),"малина апельсин ") -> малина апельсин | O36: =IFERROR(__xludf.DUMMYFUNCTION("""COMPUTED_VALUE"""),"Манго апельсин") -> Манго апельсин | P36: =IFERROR(__xludf.DUMMYFUNCTION("""COMPUTED_VALUE"""),"Ред булл") -> Ред булл | Q36: =IFERROR(__xludf.DUMMYFUNCTION("""COMPUTED_VALUE"""),"Спрайт") -> Спрайт | R36: =IFERROR(__xludf.DUMMYFUNCTION("""COMPUTED_VALUE"""),"ананас клюква ") -> ананас клюква | S36: =IFERROR(__xludf.DUMMYFUNCTION("""COMPUTED_VALUE"""),"Тархун") -> Тархун | T36: =IFERROR(__xludf.DUMMYFUNCTION("""COMPUTED_VALUE"""),"алоэ Виноград ") -> алоэ Виноград | U36: =IFERROR(__xludf.DUMMYFUNCTION("""COMPUTED_VALUE"""),"Фруктовая жвачка") -> Фруктовая жвачка | V36: =IFERROR(__xludf.DUMMYFUNCTION("""COMPUTED_VALUE"""),"Холодная кола") -> Холодная кола | W36: =IFERROR(__xludf.DUMMYFUNCTION("""COMPUTED_VALUE"""),"Черная смородина клюква") -> Черная смородина клюква | X36: =IFERROR(__xludf.DUMMYFUNCTION("""COMPUTED_VALUE"""),"Черника арбуз") -> Черника арбуз | Y36: =IFERROR(__xludf.DUMMYFUNCTION("""COMPUTED_VALUE"""),"Яблоко черника") -> Яблоко черника
A37: =IFERROR(__xludf.DUMMYFUNCTION("""COMPUTED_VALUE"""),"0.4") -> 0.4 | B37: =IFERROR(__xludf.DUMMYFUNCTION("""COMPUTED_VALUE"""),"0.6") -> 0.6 | C37: =IFERROR(__xludf.DUMMYFUNCTION("""COMPUTED_VALUE"""),"0.7") -> 0.7 | D37: =IFERROR(__xludf.DUMMYFUNCTION("""COMPUTED_VALUE"""),"0.8") -> 0.8
A38: =IFERROR(__xludf.DUMMYFUNCTION("""COMPUTED_VALUE"""),"кислая земляника") -> кислая земляника | B38: =IFERROR(__xludf.DUMMYFUNCTION("""COMPUTED_VALUE"""),"кислая фанта с черникой") -> кислая фанта с черникой | C38: =IFERROR(__xludf.DUMMYFUNCTION("""COMPUTED_VALUE"""),"кислое харибо с колой и черешней") -> кислое харибо с колой и черешней | D38: =IFERROR(__xludf.DUMMYFUNCTION("""COMPUTED_VALUE"""),"кислое яблочно клубничная шипучка") -> кислое яблочно клубничная шипучка | E38: =IFERROR(__xludf.DUMMYFUNCTION("""COMPUTED_VALUE"""),"кислые желатинки маракуйя ананас") -> кислые желатинки маракуйя ананас | F38: =IFERROR(__xludf.DUMMYFUNCTION("""COMPUTED_VALUE"""),"кислые ленточки маракуя манго") -> кислые ленточки маракуя манго | G38: =IFERROR(__xludf.DUMMYFUNCTION("""COMPUTED_VALUE"""),"кислые мармеладные ягоды") -> кислые мармеладные ягоды | H38: =IFERROR(__xludf.DUMMYFUNCTION("""COMPUTED_VALUE"""),"кислый виноград лайм") -> кислый виноград лайм | I38: =IFERROR(__xludf.DUMMYFUNCTION("""COMPUTED_VALUE"""),"кислый грейпфрут с вишней") -> кислый грейпфрут с вишней | J38: =IFERROR(__xludf.DUMMYFUNCTION("""COMPUTED_VALUE"""),"кислый леденец виноград киви яблоко") -> кислый леденец виноград киви яблоко | K38: =IFERROR(__xludf.DUMMYFUNCTION("""COMPUTED_VALUE"""),"кислый лимонад арбуз лайм малина") -> кислый лимонад арбуз лайм малина | L38: =IFERROR(__xludf.DUMMYFUNCTION("""COMPUTED_VALUE"""),"кислый персик клубника") -> кислый персик клубника | M38: =IFERROR(__xludf.DUMMYFUNCTION("""COMPUTED_VALUE"""),"кислый яблочно лимонные колечки") -> кислый яблочно лимонные колечки | N38: =IFERROR(__xludf.DUMMYFUNCTION("""COMPUTED_VALUE"""),"фанта апельсин с кислой малиной") -> фанта апельсин с кислой малиной
A39: =IFERROR(__xludf.DUMMYFUNCTION("""COMPUTED_VALUE"""),"кислая земляника") -> кислая земляника | B39: =IFERROR(__xludf.DUMMYFUNCTION("""COMPUTED_VALUE"""),"кислая фанта с черникой") -> кислая фанта с черникой | C39: =IFERROR(__xludf.DUMMYFUNCTION("""COMPUTED_VALUE"""),"кислое харибо с колой и черешней") -> кислое харибо с колой и черешней | D39: =IFERROR(__xludf.DUMMYFUNCTION("""COMPUTED_VALUE"""),"кислое яблочно клубничная шипучка") -> кислое яблочно клубничная шипучка | E39: =IFERROR(__xludf.DUMMYFUNCTION("""COMPUTED_VALUE"""),"кислые желатинки маракуйя ананас") -> кислые желатинки маракуйя ананас | F39: =IFERROR(__xludf.DUMMYFUNCTION("""COMPUTED_VALUE"""),"кислые ленточки маракуя манго") -> кислые ленточки маракуя манго | G39: =IFERROR(__xludf.DUMMYFUNCTION("""COMPUTED_VALUE"""),"кислые мармеладные ягоды") -> кислые мармеладные ягоды | H39: =IFERROR(__xludf.DUMMYFUNCTION("""COMPUTED_VALUE"""),"кислый виноград лайм") -> кислый виноград лайм | I39: =IFERROR(__xludf.DUMMYFUNCTION("""COMPUTED_VALUE"""),"кислый грейпфрут с вишней") -> кислый грейпфрут с вишней | J39: =IFERROR(__xludf.DUMMYFUNCTION("""COMPUTED_VALUE"""),"кислый леденец виноград киви яблоко") -> кислый леденец виноград киви яблоко | K39: =IFERROR(__xludf.DUMMYFUNCTION("""COMPUTED_VALUE"""),"кислый лимонад арбуз лайм малина") -> кислый лимонад арбуз лайм малина | L39: =IFERROR(__xludf.DUMMYFUNCTION("""COMPUTED_VALUE"""),"кислый персик клубника") -> кислый персик клубника | M39: =IFERROR(__xludf.DUMMYFUNCTION("""COMPUTED_VALUE"""),"кислый яблочно лимонные колечки") -> кислый яблочно лимонные колечки | N39: =IFERROR(__xludf.DUMMYFUNCTION("""COMPUTED_VALUE"""),"фанта апельсин с кислой малиной") -> фанта апельсин с кислой малиной
A67: =IFERROR(__xludf.DUMMYFUNCTION("""COMPUTED_VALUE"""),"0.4") -> 0.4 | B67: =IFERROR(__xludf.DUMMYFUNCTION("""COMPUTED_VALUE"""),"0.6") -> 0.6 | C67: =IFERROR(__xludf.DUMMYFUNCTION("""COMPUTED_VALUE"""),"0.7") -> 0.7 | D67: =IFERROR(__xludf.DUMMYFUNCTION("""COMPUTED_VALUE"""),"0.8") -> 0.8
A68: =IFERROR(__xludf.DUMMYFUNCTION("""COMPUTED_VALUE"""),"Кислый малиново-грейпфрутовый швепс") -> Кислый малиново-грейпфрутовый швепс | B68: =IFERROR(__xludf.DUMMYFUNCTION("""COMPUTED_VALUE"""),"Ананас апельсин") -> Ананас апельсин | C68: =IFERROR(__xludf.DUMMYFUNCTION("""COMPUTED_VALUE"""),"Пинаколада") -> Пинаколада | D68: =IFERROR(__xludf.DUMMYFUNCTION("""COMPUTED_VALUE"""),"Мятный бабл гам") -> Мятный бабл гам | E68: =IFERROR(__xludf.DUMMYFUNCTION("""COMPUTED_VALUE"""),"Мянго драгонфрут") -> Мянго драгонфрут | F68: =IFERROR(__xludf.DUMMYFUNCTION("""COMPUTED_VALUE"""),"Клубничная фанта") -> Клубничная фанта | G68: =IFERROR(__xludf.DUMMYFUNCTION("""COMPUTED_VALUE"""),"Клубничная арбуз") -> Клубничная арбуз | H68: =IFERROR(__xludf.DUMMYFUNCTION("""COMPUTED_VALUE"""),"Кислый скитлс") -> Кислый скитлс | I68: =IFERROR(__xludf.DUMMYFUNCTION("""COMPUTED_VALUE"""),"Кислый лайм арбуз") -> Кислый лайм арбуз | J68: =IFERROR(__xludf.DUMMYFUNCTION("""COMPUTED_VALUE"""),"Тропический банан") -> Тропический банан | K68: =IFERROR(__xludf.DUMMYFUNCTION("""COMPUTED_VALUE"""),"Яблочный энергетик") -> Яблочный энергетик | L68: =IFERROR(__xludf.DUMMYFUNCTION("""COMPUTED_VALUE"""),"Барбарисовый лимонад") -> Барбарисовый лимонад | M68: =IFERROR(__xludf.DUMMYFUNCTION("""COMPUTED_VALUE"""),"Лимонад виноград вишня") -> Лимонад виноград вишня | N68: =IFERROR(__xludf.DUMMYFUNCTION("""COMPUTED_VALUE"""),"Розовый лимонад") -> Розовый лимонад | O68: =IFERROR(__xludf.DUMMYFUNCTION("""COMPUTED_VALUE"""),"Двойной манго") -> Двойной манго | P68: =IFERROR(__xludf.DUMMYFUNCTION("""COMPUTED_VALUE"""),"Лесные ягоды ") -> Лесные ягоды | Q68: =IFERROR(__xludf.DUMMYFUNCTION("""COMPUTED_VALUE"""),"Ежевика малина ") -> Ежевика малина | R68: =IFERROR(__xludf.DUMMYFUNCTION("""COMPUTED_VALUE"""),"Смородиновый лимонад") -> Смородиновый лимонад | S68: =IFERROR(__xludf.DUMMYFUNCTION("""COMPUTED_VALUE"""),"Кола вишня") -> Кола вишня | T68: =IFERROR(__xludf.DUMMYFUNCTION("""COMPUTED_VALUE"""),"Манго арбуз") -> Манго арбуз | U68: =IFERROR(__xludf.DUMMYFUNCTION("""COMPUTED_VALUE"""),"Алоэ виноград") -> Алоэ виноград | V68: =IFERROR(__xludf.DUMMYFUNCTION("""COMPUTED_VALUE"""),"Банан клубника") -> Банан клубника | W68: =IFERROR(__xludf.DUMMYFUNCTION("""COMPUTED_VALUE"""),"Малиновый мармелад") -> Малиновый мармелад | X68: =IFERROR(__xludf.DUMMYFUNCTION("""COMPUTED_VALUE"""),"Клубника киви") -> Клубника киви | Y68: =IFERROR(__xludf.DUMMYFUNCTION("""COMPUTED_VALUE"""),"Клюква лайм") -> Клюква лайм | Z68: =IFERROR(__xludf.DUMMYFUNCTION("""COMPUTED_VALUE"""),"Гуава ананас") -> Гуава ананас | AA68: =IFERROR(__xludf.DUMMYFUNCTION("""COMPUTED_VALUE"""),"Морс") -> Морс | AB68: =IFERROR(__xludf.DUMMYFUNCTION("""COMPUTED_VALUE"""),"Красный апельсин") -> Красный апельсин | AC68: =IFERROR(__xludf.DUMMYFUNCTION("""COMPUTED_VALUE"""),"Арбузная жвачка") -> Арбузная жвачка | AD68: =IFERROR(__xludf.DUMMYFUNCTION("""COMPUTED_VALUE"""),"Смородина Виноград") -> Смородина Виноград | AE68: =IFERROR(__xludf.DUMMYFUNCTION("""COMPUTED_VALUE"""),"Гранатовая Мармелад") -> Гранатовая Мармелад | AF68: =IFERROR(__xludf.DUMMYFUNCTION("""COMPUTED_VALUE"""),"Яблоко Киви") -> Яблоко Киви | AG68: =IFERROR(__xludf.DUMMYFUNCTION("""COMPUTED_VALUE"""),"Клубника Ежевика") -> Клубника Ежевика | AH68: =IFERROR(__xludf.DUMMYFUNCTION("""COMPUTED_VALUE"""),"Клубничный Коктейль") -> Клубничный Коктейль | AI68: =IFERROR(__xludf.DUMMYFUNCTION("""COMPUTED_VALUE"""),"Клюква Земляника ") -> Клюква Земляника | AJ68: =IFERROR(__xludf.DUMMYFUNCTION("""COMPUTED_VALUE"""),"Какос Дыня") -> Какос Дыня | AK68: =IFERROR(__xludf.DUMMYFUNCTION("""COMPUTED_VALUE"""),"Маракуйя мандарин") -> Маракуйя мандарин | AL68: =IFERROR(__xludf.DUMMYFUNCTION("""COMPUTED_VALUE"""),"Персик кактус") -> Персик кактус | AM68: =IFERROR(__xludf.DUMMYFUNCTION("""COMPUTED_VALUE"""),"Спрайт") -> Спрайт | AN68: =IFERROR(__xludf.DUMMYFUNCTION("""COMPUTED_VALUE"""),"Черничная фанта") -> Черничная фанта | AO68: =IFERROR(__xludf.DUMMYFUNCTION("""COMPUTED_VALUE"""),"Ягодная жвачка") -> Ягодная жвачка | AP68: =IFERROR(__xludf.DUMMYFUNCTION("""COMPUTED_VALUE"""),"Ягодный энергетик") -> Ягодный энергетик | AQ68: =IFERROR(__xludf.DUMMYFUNCTION("""COMPUTED_VALUE"""),"Ягодный пунш ") -> Ягодный пунш | AR68: =IFERROR(__xludf.DUMMYFUNCTION("""COMPUTED_VALUE"""),"Виноградный холс") -> Виноградный холс | AS68: =IFERROR(__xludf.DUMMYFUNCTION("""COMPUTED_VALUE"""),"Грейпфрут смородина") -> Грейпфрут смородина | AT68: =IFERROR(__xludf.DUMMYFUNCTION("""COMPUTED_VALUE"""),"Дыня персик") -> Дыня персик | AU68: =IFERROR(__xludf.DUMMYFUNCTION("""COMPUTED_VALUE"""),"Земляника виноград") -> Земляника виноград | AV68: =IFERROR(__xludf.DUMMYFUNCTION("""COMPUTED_VALUE"""),"Киви маракуйя гуава") -> Киви маракуйя гуава | AW68: =IFERROR(__xludf.DUMMYFUNCTION("""COMPUTED_VALUE"""),"Кислые вишнёвые червячки") -> Кислые вишнёвые червячки | AX68: =IFERROR(__xludf.DUMMYFUNCTION("""COMPUTED_VALUE"""),"Кислые чернично-малиновое червячки") -> Кислые чернично-малиновое червячки
A69: =IFERROR(__xludf.DUMMYFUNCTION("""COMPUTED_VALUE"""),"Смородина холс") -> Смородина холс | B69: =IFERROR(__xludf.DUMMYFUNCTION("""COMPUTED_VALUE"""),"Тропические фрукты") -> Тропические фрукты | C69: =IFERROR(__xludf.DUMMYFUNCTION("""COMPUTED_VALUE"""),"Черничная конфета") -> Черничная конфета | D69: =IFERROR(__xludf.DUMMYFUNCTION("""COMPUTED_VALUE"""),"Яблоко вишня") -> Яблоко вишня | E69: =IFERROR(__xludf.DUMMYFUNCTION("""COMPUTED_VALUE"""),"Виноград мята") -> Виноград мята | F69: =IFERROR(__xludf.DUMMYFUNCTION("""COMPUTED_VALUE"""),"Виноград холс") -> Виноград холс | G69: =IFERROR(__xludf.DUMMYFUNCTION("""COMPUTED_VALUE"""),"Грейпфрутовый лимонад") -> Грейпфрутовый лимонад | H69: =IFERROR(__xludf.DUMMYFUNCTION("""COMPUTED_VALUE"""),"Дыня банан") -> Дыня банан | I69: =IFERROR(__xludf.DUMMYFUNCTION("""COMPUTED_VALUE"""),"Ежевичный лимонад") -> Ежевичный лимонад | J69: =IFERROR(__xludf.DUMMYFUNCTION("""COMPUTED_VALUE"""),"Земляничная конфета ") -> Земляничная конфета | K69: =IFERROR(__xludf.DUMMYFUNCTION("""COMPUTED_VALUE"""),"Ананас манго ") -> Ананас манго | L69: =IFERROR(__xludf.DUMMYFUNCTION("""COMPUTED_VALUE"""),"Жвачка черника мята ") -> Жвачка черника мята | M69: =IFERROR(__xludf.DUMMYFUNCTION("""COMPUTED_VALUE"""),"Зеленый манго") -> Зеленый манго | N69: =IFERROR(__xludf.DUMMYFUNCTION("""COMPUTED_VALUE"""),"Клюква брусника") -> Клюква брусника | O69: =IFERROR(__xludf.DUMMYFUNCTION("""COMPUTED_VALUE"""),"Апельсин ") -> Апельсин | P69: =IFERROR(__xludf.DUMMYFUNCTION("""COMPUTED_VALUE"""),"Кокос малина") -> Кокос малина | Q69: =IFERROR(__xludf.DUMMYFUNCTION("""COMPUTED_VALUE"""),"Лимонные черви") -> Лимонные черви | R69: =IFERROR(__xludf.DUMMYFUNCTION("""COMPUTED_VALUE"""),"Малиновый лимонад") -> Малиновый лимонад | S69: =IFERROR(__xludf.DUMMYFUNCTION("""COMPUTED_VALUE"""),"Смородина малина") -> Смородина малина
A70: =IFERROR(__xludf.DUMMYFUNCTION("""COMPUTED_VALUE"""),"0.4") -> 0.4 | B70: =IFERROR(__xludf.DUMMYFUNCTION("""COMPUTED_VALUE"""),"0.6") -> 0.6 | C70: =IFERROR(__xludf.DUMMYFUNCTION("""COMPUTED_VALUE"""),"0.7") -> 0.7 | D70: =IFERROR(__xludf.DUMMYFUNCTION("""COMPUTED_VALUE"""),"0.8") -> 0.8
A71: =IFERROR(__xludf.DUMMYFUNCTION("""COMPUTED_VALUE"""),"Смородина холс") -> Смородина холс | B71: =IFERROR(__xludf.DUMMYFUNCTION("""COMPUTED_VALUE"""),"Тропические фрукты") -> Тропические фрукты | C71: =IFERROR(__xludf.DUMMYFUNCTION("""COMPUTED_VALUE"""),"Черничная конфета") -> Черничная конфета | D71: =IFERROR(__xludf.DUMMYFUNCTION("""COMPUTED_VALUE"""),"Яблоко вишня") -> Яблоко вишня | E71: =IFERROR(__xludf.DUMMYFUNCTION("""COMPUTED_VALUE"""),"Виноград мята") -> Виноград мята | F71: =IFERROR(__xludf.DUMMYFUNCTION("""COMPUTED_VALUE"""),"Виноград холс") -> Виноград холс | G71: =IFERROR(__xludf.DUMMYFUNCTION("""COMPUTED_VALUE"""),"Грейпфрутовый лимонад") -> Грейпфрутовый лимонад | H71: =IFERROR(__xludf.DUMMYFUNCTION("""COMPUTED_VALUE"""),"Дыня банан") -> Дыня банан | I71: =IFERROR(__xludf.DUMMYFUNCTION("""COMPUTED_VALUE"""),"Ежевичный лимонад") -> Ежевичный лимонад | J71: =IFERROR(__xludf.DUMMYFUNCTION("""COMPUTED_VALUE"""),"Земляничная конфета ") -> Земляничная конфета | K71: =IFERROR(__xludf.DUMMYFUNCTION("""COMPUTED_VALUE"""),"Ананас манго ") -> Ананас манго | L71: =IFERROR(__xludf.DUMMYFUNCTION("""COMPUTED_VALUE"""),"Жвачка черника мята ") -> Жвачка черника мята | M71: =IFERROR(__xludf.DUMMYFUNCTION("""COMPUTED_VALUE"""),"Зеленый манго") -> Зеленый манго | N71: =IFERROR(__xludf.DUMMYFUNCTION("""COMPUTED_VALUE"""),"Клюква брусника") -> Клюква брусника | O71: =IFERROR(__xludf.DUMMYFUNCTION("""COMPUTED_VALUE"""),"Апельсин ") -> Апельсин | P71: =IFERROR(__xludf.DUMMYFUNCTION("""COMPUTED_VALUE"""),"Кокос малина") -> Кокос малина | Q71: =IFERROR(__xludf.DUMMYFUNCTION("""COMPUTED_VALUE"""),"Лимонные черви") -> Лимонные черви | R71: =IFERROR(__xludf.DUMMYFUNCTION("""COMPUTED_VALUE"""),"Малиновый лимонад") -> Малиновый лимонад | S71: =IFERROR(__xludf.DUMMYFUNCTION("""COMPUTED_VALUE"""),"Смородина малина") -> Смородина малина
A72: =IFERROR(__xludf.DUMMYFUNCTION("""COMPUTED_VALUE"""),"Ананас киви") -> Ананас киви | B72: =IFERROR(__xludf.DUMMYFUNCTION("""COMPUTED_VALUE"""),"Арбузный смузи") -> Арбузный смузи | C72: =IFERROR(__xludf.DUMMYFUNCTION("""COMPUTED_VALUE"""),"Виноградная фанта") -> Виноградная фанта | D72: =IFERROR(__xludf.DUMMYFUNCTION("""COMPUTED_VALUE"""),"Вишневый морс") -> Вишневый морс | E72: =IFERROR(__xludf.DUMMYFUNCTION("""COMPUTED_VALUE"""),"Гранатовый мармелад") -> Гранатовый мармелад | F72: =IFERROR(__xludf.DUMMYFUNCTION("""COMPUTED_VALUE"""),"Грейпфрут киви") -> Грейпфрут киви | G72: =IFERROR(__xludf.DUMMYFUNCTION("""COMPUTED_VALUE"""),"Ежевика мята") -> Ежевика мята | H72: =IFERROR(__xludf.DUMMYFUNCTION("""COMPUTED_VALUE"""),"Киви манго") -> Киви манго | I72: =IFERROR(__xludf.DUMMYFUNCTION("""COMPUTED_VALUE"""),"Клубника манго") -> Клубника манго | J72: =IFERROR(__xludf.DUMMYFUNCTION("""COMPUTED_VALUE"""),"черника грейфрут ") -> черника грейфрут | K72: =IFERROR(__xludf.DUMMYFUNCTION("""COMPUTED_VALUE"""),"Малина лайм") -> Малина лайм | L72: =IFERROR(__xludf.DUMMYFUNCTION("""COMPUTED_VALUE"""),"Манго арбуз ") -> Манго арбуз | M72: =IFERROR(__xludf.DUMMYFUNCTION("""COMPUTED_VALUE"""),"Малиновый чай с жасмином") -> Малиновый чай с жасмином | N72: =IFERROR(__xludf.DUMMYFUNCTION("""COMPUTED_VALUE"""),"малина апельсин ") -> малина апельсин | O72: =IFERROR(__xludf.DUMMYFUNCTION("""COMPUTED_VALUE"""),"Манго апельсин") -> Манго апельсин | P72: =IFERROR(__xludf.DUMMYFUNCTION("""COMPUTED_VALUE"""),"Ред булл") -> Ред булл | Q72: =IFERROR(__xludf.DUMMYFUNCTION("""COMPUTED_VALUE"""),"Спрайт") -> Спрайт | R72: =IFERROR(__xludf.DUMMYFUNCTION("""COMPUTED_VALUE"""),"ананас клюква ") -> ананас клюква | S72: =IFERROR(__xludf.DUMMYFUNCTION("""COMPUTED_VALUE"""),"Тархун") -> Тархун | T72: =IFERROR(__xludf.DUMMYFUNCTION("""COMPUTED_VALUE"""),"алоэ Виноград ") -> алоэ Виноград | U72: =IFERROR(__xludf.DUMMYFUNCTION("""COMPUTED_VALUE"""),"Фруктовая жвачка") -> Фруктовая жвачка | V72: =IFERROR(__xludf.DUMMYFUNCTION("""COMPUTED_VALUE"""),"Холодная кола") -> Холодная кола | W72: =IFERROR(__xludf.DUMMYFUNCTION("""COMPUTED_VALUE"""),"Черная смородина клюква") -> Черная смородина клюква | X72: =IFERROR(__xludf.DUMMYFUNCTION("""COMPUTED_VALUE"""),"Черника арбуз") -> Черника арбуз | Y72: =IFERROR(__xludf.DUMMYFUNCTION("""COMPUTED_VALUE"""),"Яблоко черника") -> Яблоко черника
A73: =IFERROR(__xludf.DUMMYFUNCTION("""COMPUTED_VALUE"""),"Кислый малиново-грейпфрутовый швепс") -> Кислый малиново-грейпфрутовый швепс | B73: =IFERROR(__xludf.DUMMYFUNCTION("""COMPUTED_VALUE"""),"Ананас апельсин") -> Ананас апельсин | C73: =IFERROR(__xludf.DUMMYFUNCTION("""COMPUTED_VALUE"""),"Пинаколада") -> Пинаколада | D73: =IFERROR(__xludf.DUMMYFUNCTION("""COMPUTED_VALUE"""),"Мятный бабл гам") -> Мятный бабл гам | E73: =IFERROR(__xludf.DUMMYFUNCTION("""COMPUTED_VALUE"""),"Мянго драгонфрут") -> Мянго драгонфрут | F73: =IFERROR(__xludf.DUMMYFUNCTION("""COMPUTED_VALUE"""),"Клубничная фанта") -> Клубничная фанта | G73: =IFERROR(__xludf.DUMMYFUNCTION("""COMPUTED_VALUE"""),"Клубничная арбуз") -> Клубничная арбуз | H73: =IFERROR(__xludf.DUMMYFUNCTION("""COMPUTED_VALUE"""),"Кислый скитлс") -> Кислый скитлс | I73: =IFERROR(__xludf.DUMMYFUNCTION("""COMPUTED_VALUE"""),"Кислый лайм арбуз") -> Кислый лайм арбуз | J73: =IFERROR(__xludf.DUMMYFUNCTION("""COMPUTED_VALUE"""),"Тропический банан") -> Тропический банан | K73: =IFERROR(__xludf.DUMMYFUNCTION("""COMPUTED_VALUE"""),"Яблочный энергетик") -> Яблочный энергетик | L73: =IFERROR(__xludf.DUMMYFUNCTION("""COMPUTED_VALUE"""),"Барбарисовый лимонад") -> Барбарисовый лимонад | M73: =IFERROR(__xludf.DUMMYFUNCTION("""COMPUTED_VALUE"""),"Лимонад виноград вишня") -> Лимонад виноград вишня | N73: =IFERROR(__xludf.DUMMYFUNCTION("""COMPUTED_VALUE"""),"Розовый лимонад") -> Розовый лимонад | O73: =IFERROR(__xludf.DUMMYFUNCTION("""COMPUTED_VALUE"""),"Двойной манго") -> Двойной манго | P73: =IFERROR(__xludf.DUMMYFUNCTION("""COMPUTED_VALUE"""),"Лесные ягоды ") -> Лесные ягоды | Q73: =IFERROR(__xludf.DUMMYFUNCTION("""COMPUTED_VALUE"""),"Ежевика малина ") -> Ежевика малина | R73: =IFERROR(__xludf.DUMMYFUNCTION("""COMPUTED_VALUE"""),"Смородиновый лимонад") -> Смородиновый лимонад | S73: =IFERROR(__xludf.DUMMYFUNCTION("""COMPUTED_VALUE"""),"Кола вишня") -> Кола вишня | T73: =IFERROR(__xludf.DUMMYFUNCTION("""COMPUTED_VALUE"""),"Манго арбуз") -> Манго арбуз | U73: =IFERROR(__xludf.DUMMYFUNCTION("""COMPUTED_VALUE"""),"Алоэ виноград") -> Алоэ виноград | V73: =IFERROR(__xludf.DUMMYFUNCTION("""COMPUTED_VALUE"""),"Банан клубника") -> Банан клубника | W73: =IFERROR(__xludf.DUMMYFUNCTION("""COMPUTED_VALUE"""),"Малиновый мармелад") -> Малиновый мармелад | X73: =IFERROR(__xludf.DUMMYFUNCTION("""COMPUTED_VALUE"""),"Клубника киви") -> Клубника киви | Y73: =IFERROR(__xludf.DUMMYFUNCTION("""COMPUTED_VALUE"""),"Клюква лайм") -> Клюква лайм | Z73: =IFERROR(__xludf.DUMMYFUNCTION("""COMPUTED_VALUE"""),"Гуава ананас") -> Гуава ананас | AA73: =IFERROR(__xludf.DUMMYFUNCTION("""COMPUTED_VALUE"""),"Морс") -> Морс | AB73: =IFERROR(__xludf.DUMMYFUNCTION("""COMPUTED_VALUE"""),"Красный апельсин") -> Красный апельсин | AC73: =IFERROR(__xludf.DUMMYFUNCTION("""COMPUTED_VALUE"""),"Арбузная жвачка") -> Арбузная жвачка | AD73: =IFERROR(__xludf.DUMMYFUNCTION("""COMPUTED_VALUE"""),"Смородина Виноград") -> Смородина Виноград | AE73: =IFERROR(__xludf.DUMMYFUNCTION("""COMPUTED_VALUE"""),"Гранатовая Мармелад") -> Гранатовая Мармелад | AF73: =IFERROR(__xludf.DUMMYFUNCTION("""COMPUTED_VALUE"""),"Яблоко Киви") -> Яблоко Киви | AG73: =IFERROR(__xludf.DUMMYFUNCTION("""COMPUTED_VALUE"""),"Клубника Ежевика") -> Клубника Ежевика | AH73: =IFERROR(__xludf.DUMMYFUNCTION("""COMPUTED_VALUE"""),"Клубничный Коктейль") -> Клубничный Коктейль | AI73: =IFERROR(__xludf.DUMMYFUNCTION("""COMPUTED_VALUE"""),"Клюква Земляника ") -> Клюква Земляника | AJ73: =IFERROR(__xludf.DUMMYFUNCTION("""COMPUTED_VALUE"""),"Какос Дыня") -> Какос Дыня | AK73: =IFERROR(__xludf.DUMMYFUNCTION("""COMPUTED_VALUE"""),"Маракуйя мандарин") -> Маракуйя мандарин | AL73: =IFERROR(__xludf.DUMMYFUNCTION("""COMPUTED_VALUE"""),"Персик кактус") -> Персик кактус | AM73: =IFERROR(__xludf.DUMMYFUNCTION("""COMPUTED_VALUE"""),"Спрайт") -> Спрайт | AN73: =IFERROR(__xludf.DUMMYFUNCTION("""COMPUTED_VALUE"""),"Черничная фанта") -> Черничная фанта | AO73: =IFERROR(__xludf.DUMMYFUNCTION("""COMPUTED_VALUE"""),"Ягодная жвачка") -> Ягодная жвачка | AP73: =IFERROR(__xludf.DUMMYFUNCTION("""COMPUTED_VALUE"""),"Ягодный энергетик") -> Ягодный энергетик | AQ73: =IFERROR(__xludf.DUMMYFUNCTION("""COMPUTED_VALUE"""),"Ягодный пунш ") -> Ягодный пунш | AR73: =IFERROR(__xludf.DUMMYFUNCTION("""COMPUTED_VALUE"""),"Виноградный холс") -> Виноградный холс | AS73: =IFERROR(__xludf.DUMMYFUNCTION("""COMPUTED_VALUE"""),"Грейпфрут смородина") -> Грейпфрут смородина | AT73: =IFERROR(__xludf.DUMMYFUNCTION("""COMPUTED_VALUE"""),"Дыня персик") -> Дыня персик | AU73: =IFERROR(__xludf.DUMMYFUNCTION("""COMPUTED_VALUE"""),"Земляника виноград") -> Земляника виноград | AV73: =IFERROR(__xludf.DUMMYFUNCTION("""COMPUTED_VALUE"""),"Киви маракуйя гуава") -> Киви маракуйя гуава | AW73: =IFERROR(__xludf.DUMMYFUNCTION("""COMPUTED_VALUE"""),"Кислые вишнёвые червячки") -> Кислые вишнёвые червячки | AX73: =IFERROR(__xludf.DUMMYFUNCTION("""COMPUTED_VALUE"""),"Кислые чернично-малиновое червячки") -> Кислые чернично-малиновое червячки
A74: =IFERROR(__xludf.DUMMYFUNCTION("""COMPUTED_VALUE"""),"Апельсиновое драже") -> Апельсиновое драже | B74: =IFERROR(__xludf.DUMMYFUNCTION("""COMPUTED_VALUE"""),"Бабл гам") -> Бабл гам | C74: =IFERROR(__xludf.DUMMYFUNCTION("""COMPUTED_VALUE"""),"Виноградная конфета") -> Виноградная конфета | D74: =IFERROR(__xludf.DUMMYFUNCTION("""COMPUTED_VALUE"""),"Даня кокос") -> Даня кокос | E74: =IFERROR(__xludf.DUMMYFUNCTION("""COMPUTED_VALUE"""),"Земляника груша") -> Земляника груша | F74: =IFERROR(__xludf.DUMMYFUNCTION("""COMPUTED_VALUE"""),"Кислый киви") -> Кислый киви | G74: =IFERROR(__xludf.DUMMYFUNCTION("""COMPUTED_VALUE"""),"Кислый малиновый лимонад ") -> Кислый малиновый лимонад | H74: =IFERROR(__xludf.DUMMYFUNCTION("""COMPUTED_VALUE"""),"Кола сода айс") -> Кола сода айс | I74: =IFERROR(__xludf.DUMMYFUNCTION("""COMPUTED_VALUE"""),"Ледяной ананас") -> Ледяной ананас | J74: =IFERROR(__xludf.DUMMYFUNCTION("""COMPUTED_VALUE"""),"Лимонные червячки ") -> Лимонные червячки | K74: =IFERROR(__xludf.DUMMYFUNCTION("""COMPUTED_VALUE"""),"Манго апельсин") -> Манго апельсин | L74: =IFERROR(__xludf.DUMMYFUNCTION("""COMPUTED_VALUE"""),"Смородина виноград") -> Смородина виноград | M74: =IFERROR(__xludf.DUMMYFUNCTION("""COMPUTED_VALUE"""),"Яблочный холс") -> Яблочный холс | N74: =IFERROR(__xludf.DUMMYFUNCTION("""COMPUTED_VALUE"""),"Ягодный смузи") -> Ягодный смузи | O74: =IFERROR(__xludf.DUMMYFUNCTION("""COMPUTED_VALUE"""),"Ягодный энергетик") -> Ягодный энергетик
A75: =IFERROR(__xludf.DUMMYFUNCTION("""COMPUTED_VALUE"""),"Арбуз Малина ") -> Арбуз Малина | B75: =IFERROR(__xludf.DUMMYFUNCTION("""COMPUTED_VALUE"""),"Банан Кокос ") -> Банан Кокос | C75: =IFERROR(__xludf.DUMMYFUNCTION("""COMPUTED_VALUE"""),"Барбарисовый Энергетик ") -> Барбарисовый Энергетик | D75: =IFERROR(__xludf.DUMMYFUNCTION("""COMPUTED_VALUE"""),"Виноградный Энергетик") -> Виноградный Энергетик | E75: =IFERROR(__xludf.DUMMYFUNCTION("""COMPUTED_VALUE"""),"Гранат Клубника ") -> Гранат Клубника | F75: =IFERROR(__xludf.DUMMYFUNCTION("""COMPUTED_VALUE"""),"Гранат Смородина ") -> Гранат Смородина | G75: =IFERROR(__xludf.DUMMYFUNCTION("""COMPUTED_VALUE"""),"Грейпфрутовый Швепс ") -> Грейпфрутовый Швепс | H75: =IFERROR(__xludf.DUMMYFUNCTION("""COMPUTED_VALUE"""),"Земляника Драгонфрут ") -> Земляника Драгонфрут | I75: =IFERROR(__xludf.DUMMYFUNCTION("""COMPUTED_VALUE"""),"Киви Личи ") -> Киви Личи | J75: =IFERROR(__xludf.DUMMYFUNCTION("""COMPUTED_VALUE"""),"Киви Маракуйя Гуава ") -> Киви Маракуйя Гуава | K75: =IFERROR(__xludf.DUMMYFUNCTION("""COMPUTED_VALUE"""),"Клубника Банан ") -> Клубника Банан | L75: =IFERROR(__xludf.DUMMYFUNCTION("""COMPUTED_VALUE"""),"Клубника Вишня ") -> Клубника Вишня | M75: =IFERROR(__xludf.DUMMYFUNCTION("""COMPUTED_VALUE"""),"Клубника Земляника ") -> Клубника Земляника | N75: =IFERROR(__xludf.DUMMYFUNCTION("""COMPUTED_VALUE"""),"Клубничный Мохито ") -> Клубничный Мохито | O75: =IFERROR(__xludf.DUMMYFUNCTION("""COMPUTED_VALUE"""),"Манго Грейпфрут ") -> Манго Грейпфрут | P75: =IFERROR(__xludf.DUMMYFUNCTION("""COMPUTED_VALUE"""),"Манго Персик Личи ") -> Манго Персик Личи | Q75: =IFERROR(__xludf.DUMMYFUNCTION("""COMPUTED_VALUE"""),"Персик Бабл Гам ") -> Персик Бабл Гам | R75: =IFERROR(__xludf.DUMMYFUNCTION("""COMPUTED_VALUE"""),"Садовые Ягоды ") -> Садовые Ягоды | S75: =IFERROR(__xludf.DUMMYFUNCTION("""COMPUTED_VALUE"""),"Скитлс Лимон Лайм 2") -> Скитлс Лимон Лайм 2 | T75: =IFERROR(__xludf.DUMMYFUNCTION("""COMPUTED_VALUE"""),"Смородина Мармелад 1") -> Смородина Мармелад 1 | U75: =IFERROR(__xludf.DUMMYFUNCTION("""COMPUTED_VALUE"""),"Темная Вишня 1") -> Темная Вишня 1 | V75: =IFERROR(__xludf.DUMMYFUNCTION("""COMPUTED_VALUE"""),"Фруктовые Пластинки 1") -> Фруктовые Пластинки 1 | W75: =IFERROR(__xludf.DUMMYFUNCTION("""COMPUTED_VALUE"""),"Черника Ежевика 1") -> Черника Ежевика 1 | X75: =IFERROR(__xludf.DUMMYFUNCTION("""COMPUTED_VALUE"""),"Черника Малина 1") -> Черника Малина 1 | Y75: =IFERROR(__xludf.DUMMYFUNCTION("""COMPUTED_VALUE"""),"Черника Мята 2") -> Черника Мята 2 | Z75: =IFERROR(__xludf.DUMMYFUNCTION("""COMPUTED_VALUE"""),"Яблоко Виноград 2") -> Яблоко Виноград 2 | AA75: =IFERROR(__xludf.DUMMYFUNCTION("""COMPUTED_VALUE"""),"Яблоко Малина 4") -> Яблоко Малина 4
A76: =IFERROR(__xludf.DUMMYFUNCTION("""COMPUTED_VALUE"""),"Ананас киви") -> Ананас киви | B76: =IFERROR(__xludf.DUMMYFUNCTION("""COMPUTED_VALUE"""),"Арбузный смузи") -> Арбузный смузи | C76: =IFERROR(__xludf.DUMMYFUNCTION("""COMPUTED_VALUE"""),"Виноградная фанта") -> Виноградная фанта | D76: =IFERROR(__xludf.DUMMYFUNCTION("""COMPUTED_VALUE"""),"Вишневый морс") -> Вишневый морс | E76: =IFERROR(__xludf.DUMMYFUNCTION("""COMPUTED_VALUE"""),"Гранатовый мармелад") -> Гранатовый мармелад | F76: =IFERROR(__xludf.DUMMYFUNCTION("""COMPUTED_VALUE"""),"Грейпфрут киви") -> Грейпфрут киви | G76: =IFERROR(__xludf.DUMMYFUNCTION("""COMPUTED_VALUE"""),"Ежевика мята") -> Ежевика мята | H76: =IFERROR(__xludf.DUMMYFUNCTION("""COMPUTED_VALUE"""),"Киви манго") -> Киви манго | I76: =IFERROR(__xludf.DUMMYFUNCTION("""COMPUTED_VALUE"""),"Клубника манго") -> Клубника манго | J76: =IFERROR(__xludf.DUMMYFUNCTION("""COMPUTED_VALUE"""),"черника грейфрут ") -> черника грейфрут | K76: =IFERROR(__xludf.DUMMYFUNCTION("""COMPUTED_VALUE"""),"Малина лайм") -> Малина лайм | L76: =IFERROR(__xludf.DUMMYFUNCTION("""COMPUTED_VALUE"""),"Манго арбуз ") -> Манго арбуз | M76: =IFERROR(__xludf.DUMMYFUNCTION("""COMPUTED_VALUE"""),"Малиновый чай с жасмином") -> Малиновый чай с жасмином | N76: =IFERROR(__xludf.DUMMYFUNCTION("""COMPUTED_VALUE"""),"малина апельсин ") -> малина апельсин | O76: =IFERROR(__xludf.DUMMYFUNCTION("""COMPUTED_VALUE"""),"Манго апельсин") -> Манго апельсин | P76: =IFERROR(__xludf.DUMMYFUNCTION("""COMPUTED_VALUE"""),"Ред булл") -> Ред булл | Q76: =IFERROR(__xludf.DUMMYFUNCTION("""COMPUTED_VALUE"""),"Спрайт") -> Спрайт | R76: =IFERROR(__xludf.DUMMYFUNCTION("""COMPUTED_VALUE"""),"ананас клюква ") -> ананас клюква | S76: =IFERROR(__xludf.DUMMYFUNCTION("""COMPUTED_VALUE"""),"Тархун") -> Тархун | T76: =IFERROR(__xludf.DUMMYFUNCTION("""COMPUTED_VALUE"""),"алоэ Виноград ") -> алоэ Виноград | U76: =IFERROR(__xludf.DUMMYFUNCTION("""COMPUTED_VALUE"""),"Фруктовая жвачка") -> Фруктовая жвачка | V76: =IFERROR(__xludf.DUMMYFUNCTION("""COMPUTED_VALUE"""),"Холодная кола") -> Холодная кола | W76: =IFERROR(__xludf.DUMMYFUNCTION("""COMPUTED_VALUE"""),"Черная смородина клюква") -> Черная смородина клюква | X76: =IFERROR(__xludf.DUMMYFUNCTION("""COMPUTED_VALUE"""),"Черника арбуз") -> Черника арбуз | Y76: =IFERROR(__xludf.DUMMYFUNCTION("""COMPUTED_VALUE"""),"Яблоко черника") -> Яблоко черника
A77: =IFERROR(__xludf.DUMMYFUNCTION("""COMPUTED_VALUE"""),"Смородина холс") -> Смородина холс | B77: =IFERROR(__xludf.DUMMYFUNCTION("""COMPUTED_VALUE"""),"Тропические фрукты") -> Тропические фрукты | C77: =IFERROR(__xludf.DUMMYFUNCTION("""COMPUTED_VALUE"""),"Черничная конфета") -> Черничная конфета | D77: =IFERROR(__xludf.DUMMYFUNCTION("""COMPUTED_VALUE"""),"Яблоко вишня") -> Яблоко вишня | E77: =IFERROR(__xludf.DUMMYFUNCTION("""COMPUTED_VALUE"""),"Виноград мята") -> Виноград мята | F77: =IFERROR(__xludf.DUMMYFUNCTION("""COMPUTED_VALUE"""),"Виноград холс") -> Виноград холс | G77: =IFERROR(__xludf.DUMMYFUNCTION("""COMPUTED_VALUE"""),"Грейпфрутовый лимонад") -> Грейпфрутовый лимонад | H77: =IFERROR(__xludf.DUMMYFUNCTION("""COMPUTED_VALUE"""),"Дыня банан") -> Дыня банан | I77: =IFERROR(__xludf.DUMMYFUNCTION("""COMPUTED_VALUE"""),"Ежевичный лимонад") -> Ежевичный лимонад | J77: =IFERROR(__xludf.DUMMYFUNCTION("""COMPUTED_VALUE"""),"Земляничная конфета ") -> Земляничная конфета | K77: =IFERROR(__xludf.DUMMYFUNCTION("""COMPUTED_VALUE"""),"Ананас манго ") -> Ананас манго | L77: =IFERROR(__xludf.DUMMYFUNCTION("""COMPUTED_VALUE"""),"Жвачка черника мята ") -> Жвачка черника мята | M77: =IFERROR(__xludf.DUMMYFUNCTION("""COMPUTED_VALUE"""),"Зеленый манго") -> Зеленый манго | N77: =IFERROR(__xludf.DUMMYFUNCTION("""COMPUTED_VALUE"""),"Клюква брусника") -> Клюква брусника | O77: =IFERROR(__xludf.DUMMYFUNCTION("""COMPUTED_VALUE"""),"Апельсин ") -> Апельсин | P77: =IFERROR(__xludf.DUMMYFUNCTION("""COMPUTED_VALUE"""),"Кокос малина") -> Кокос малина | Q77: =IFERROR(__xludf.DUMMYFUNCTION("""COMPUTED_VALUE"""),"Лимонные черви") -> Лимонные черви | R77: =IFERROR(__xludf.DUMMYFUNCTION("""COMPUTED_VALUE"""),"Малиновый лимонад") -> Малиновый лимонад | S77: =IFERROR(__xludf.DUMMYFUNCTION("""COMPUTED_VALUE"""),"Смородина малина") -> Смородина малина
A78: =IFERROR(__xludf.DUMMYFUNCTION("""COMPUTED_VALUE"""),"Ананас киви") -> Ананас киви | B78: =IFERROR(__xludf.DUMMYFUNCTION("""COMPUTED_VALUE"""),"Арбузный смузи") -> Арбузный смузи | C78: =IFERROR(__xludf.DUMMYFUNCTION("""COMPUTED_VALUE"""),"Виноградная фанта") -> Виноградная фанта | D78: =IFERROR(__xludf.DUMMYFUNCTION("""COMPUTED_VALUE"""),"Вишневый морс") -> Вишневый морс | E78: =IFERROR(__xludf.DUMMYFUNCTION("""COMPUTED_VALUE"""),"Гранатовый мармелад") -> Гранатовый мармелад | F78: =IFERROR(__xludf.DUMMYFUNCTION("""COMPUTED_VALUE"""),"Грейпфрут киви") -> Грейпфрут киви | G78: =IFERROR(__xludf.DUMMYFUNCTION("""COMPUTED_VALUE"""),"Ежевика мята") -> Ежевика мята | H78: =IFERROR(__xludf.DUMMYFUNCTION("""COMPUTED_VALUE"""),"Киви манго") -> Киви манго | I78: =IFERROR(__xludf.DUMMYFUNCTION("""COMPUTED_VALUE"""),"Клубника манго") -> Клубника манго | J78: =IFERROR(__xludf.DUMMYFUNCTION("""COMPUTED_VALUE"""),"черника грейфрут ") -> черника грейфрут | K78: =IFERROR(__xludf.DUMMYFUNCTION("""COMPUTED_VALUE"""),"Малина лайм") -> Малина лайм | L78: =IFERROR(__xludf.DUMMYFUNCTION("""COMPUTED_VALUE"""),"Манго арбуз ") -> Манго арбуз | M78: =IFERROR(__xludf.DUMMYFUNCTION("""COMPUTED_VALUE"""),"Малиновый чай с жасмином") -> Малиновый чай с жасмином | N78: =IFERROR(__xludf.DUMMYFUNCTION("""COMPUTED_VALUE"""),"малина апельсин ") -> малина апельсин | O78: =IFERROR(__xludf.DUMMYFUNCTION("""COMPUTED_VALUE"""),"Манго апельсин") -> Манго апельсин | P78: =IFERROR(__xludf.DUMMYFUNCTION("""COMPUTED_VALUE"""),"Ред булл") -> Ред булл | Q78: =IFERROR(__xludf.DUMMYFUNCTION("""COMPUTED_VALUE"""),"Спрайт") -> Спрайт | R78: =IFERROR(__xludf.DUMMYFUNCTION("""COMPUTED_VALUE"""),"ананас клюква ") -> ананас клюква | S78: =IFERROR(__xludf.DUMMYFUNCTION("""COMPUTED_VALUE"""),"Тархун") -> Тархун | T78: =IFERROR(__xludf.DUMMYFUNCTION("""COMPUTED_VALUE"""),"алоэ Виноград ") -> алоэ Виноград | U78: =IFERROR(__xludf.DUMMYFUNCTION("""COMPUTED_VALUE"""),"Фруктовая жвачка") -> Фруктовая жвачка | V78: =IFERROR(__xludf.DUMMYFUNCTION("""COMPUTED_VALUE"""),"Холодная кола") -> Холодная кола | W78: =IFERROR(__xludf.DUMMYFUNCTION("""COMPUTED_VALUE"""),"Черная смородина клюква") -> Черная смородина клюква | X78: =IFERROR(__xludf.DUMMYFUNCTION("""COMPUTED_VALUE"""),"Черника арбуз") -> Черника арбуз | Y78: =IFERROR(__xludf.DUMMYFUNCTION("""COMPUTED_VALUE"""),"Яблоко черника") -> Яблоко черника
A79: =IFERROR(__xludf.DUMMYFUNCTION("""COMPUTED_VALUE"""),"кислая земляника") -> кислая земляника | B79: =IFERROR(__xludf.DUMMYFUNCTION("""COMPUTED_VALUE"""),"кислая фанта с черникой") -> кислая фанта с черникой | C79: =IFERROR(__xludf.DUMMYFUNCTION("""COMPUTED_VALUE"""),"кислое харибо с колой и черешней") -> кислое харибо с колой и черешней | D79: =IFERROR(__xludf.DUMMYFUNCTION("""COMPUTED_VALUE"""),"кислое яблочно клубничная шипучка") -> кислое яблочно клубничная шипучка | E79: =IFERROR(__xludf.DUMMYFUNCTION("""COMPUTED_VALUE"""),"кислые желатинки маракуйя ананас") -> кислые желатинки маракуйя ананас | F79: =IFERROR(__xludf.DUMMYFUNCTION("""COMPUTED_VALUE"""),"кислые ленточки маракуя манго") -> кислые ленточки маракуя манго | G79: =IFERROR(__xludf.DUMMYFUNCTION("""COMPUTED_VALUE"""),"кислые мармеладные ягоды") -> кислые мармеладные ягоды | H79: =IFERROR(__xludf.DUMMYFUNCTION("""COMPUTED_VALUE"""),"кислый виноград лайм") -> кислый виноград лайм | I79: =IFERROR(__xludf.DUMMYFUNCTION("""COMPUTED_VALUE"""),"кислый грейпфрут с вишней") -> кислый грейпфрут с вишней | J79: =IFERROR(__xludf.DUMMYFUNCTION("""COMPUTED_VALUE"""),"кислый леденец виноград киви яблоко") -> кислый леденец виноград киви яблоко | K79: =IFERROR(__xludf.DUMMYFUNCTION("""COMPUTED_VALUE"""),"кислый лимонад арбуз лайм малина") -> кислый лимонад арбуз лайм малина | L79: =IFERROR(__xludf.DUMMYFUNCTION("""COMPUTED_VALUE"""),"кислый персик клубника") -> кислый персик клубника | M79: =IFERROR(__xludf.DUMMYFUNCTION("""COMPUTED_VALUE"""),"кислый яблочно лимонные колечки") -> кислый яблочно лимонные колечки | N79: =IFERROR(__xludf.DUMMYFUNCTION("""COMPUTED_VALUE"""),"фанта апельсин с кислой малиной") -> фанта апельсин с кислой малиной
A80: =IFERROR(__xludf.DUMMYFUNCTION("""COMPUTED_VALUE"""),"Смородина холс") -> Смородина холс | B80: =IFERROR(__xludf.DUMMYFUNCTION("""COMPUTED_VALUE"""),"Тропические фрукты") -> Тропические фрукты | C80: =IFERROR(__xludf.DUMMYFUNCTION("""COMPUTED_VALUE"""),"Черничная конфета") -> Черничная конфета | D80: =IFERROR(__xludf.DUMMYFUNCTION("""COMPUTED_VALUE"""),"Яблоко вишня") -> Яблоко вишня | E80: =IFERROR(__xludf.DUMMYFUNCTION("""COMPUTED_VALUE"""),"Виноград мята") -> Виноград мята | F80: =IFERROR(__xludf.DUMMYFUNCTION("""COMPUTED_VALUE"""),"Виноград холс") -> Виноград холс | G80: =IFERROR(__xludf.DUMMYFUNCTION("""COMPUTED_VALUE"""),"Грейпфрутовый лимонад") -> Грейпфрутовый лимонад | H80: =IFERROR(__xludf.DUMMYFUNCTION("""COMPUTED_VALUE"""),"Дыня банан") -> Дыня банан | I80: =IFERROR(__xludf.DUMMYFUNCTION("""COMPUTED_VALUE"""),"Ежевичный лимонад") -> Ежевичный лимонад | J80: =IFERROR(__xludf.DUMMYFUNCTION("""COMPUTED_VALUE"""),"Земляничная конфета ") -> Земляничная конфета | K80: =IFERROR(__xludf.DUMMYFUNCTION("""COMPUTED_VALUE"""),"Ананас манго ") -> Ананас манго | L80: =IFERROR(__xludf.DUMMYFUNCTION("""COMPUTED_VALUE"""),"Жвачка черника мята ") -> Жвачка черника мята | M80: =IFERROR(__xludf.DUMMYFUNCTION("""COMPUTED_VALUE"""),"Зеленый манго") -> Зеленый манго | N80: =IFERROR(__xludf.DUMMYFUNCTION("""COMPUTED_VALUE"""),"Клюква брусника") -> Клюква брусника | O80: =IFERROR(__xludf.DUMMYFUNCTION("""COMPUTED_VALUE"""),"Апельсин ") -> Апельсин | P80: =IFERROR(__xludf.DUMMYFUNCTION("""COMPUTED_VALUE"""),"Кокос малина") -> Кокос малина | Q80: =IFERROR(__xludf.DUMMYFUNCTION("""COMPUTED_VALUE"""),"Лимонные черви") -> Лимонные черви | R80: =IFERROR(__xludf.DUMMYFUNCTION("""COMPUTED_VALUE"""),"Малиновый лимонад") -> Малиновый лимонад | S80: =IFERROR(__xludf.DUMMYFUNCTION("""COMPUTED_VALUE"""),"Смородина малина") -> Смородина малина
A81: =IFERROR(__xludf.DUMMYFUNCTION("""COMPUTED_VALUE"""),"0.4") -> 0.4 | B81: =IFERROR(__xludf.DUMMYFUNCTION("""COMPUTED_VALUE"""),"0.6") -> 0.6 | C81: =IFERROR(__xludf.DUMMYFUNCTION("""COMPUTED_VALUE"""),"0.7") -> 0.7 | D81: =IFERROR(__xludf.DUMMYFUNCTION("""COMPUTED_VALUE"""),"0.8") -> 0.8
A82: =IFERROR(__xludf.DUMMYFUNCTION("""COMPUTED_VALUE"""),"0.2") -> 0.2 | B82: =IFERROR(__xludf.DUMMYFUNCTION("""COMPUTED_VALUE"""),"0.3") -> 0.3
A83: =IFERROR(__xludf.DUMMYFUNCTION("""COMPUTED_VALUE"""),"Ягодный микс") -> Ягодный микс | B83: =IFERROR(__xludf.DUMMYFUNCTION("""COMPUTED_VALUE"""),"Энергетик малина") -> Энергетик малина | C83: =IFERROR(__xludf.DUMMYFUNCTION("""COMPUTED_VALUE"""),"Клубника арбуз") -> Клубника арбуз | D83: =IFERROR(__xludf.DUMMYFUNCTION("""COMPUTED_VALUE"""),"Ежевика малина") -> Ежевика малина | E83: =IFERROR(__xludf.DUMMYFUNCTION("""COMPUTED_VALUE"""),"Голубая малина виноград") -> Голубая малина виноград | F83: =IFERROR(__xludf.DUMMYFUNCTION("""COMPUTED_VALUE"""),"Вишня яблоко") -> Вишня яблоко | G83: =IFERROR(__xludf.DUMMYFUNCTION("""COMPUTED_VALUE"""),"Виноград лёд") -> Виноград лёд | H83: =IFERROR(__xludf.DUMMYFUNCTION("""COMPUTED_VALUE"""),"Бабл гам") -> Бабл гам | I83: =IFERROR(__xludf.DUMMYFUNCTION("""COMPUTED_VALUE"""),"Энергетик лайм") -> Энергетик лайм | J83: =IFERROR(__xludf.DUMMYFUNCTION("""COMPUTED_VALUE"""),"Черника смородина айс") -> Черника смородина айс | K83: =IFERROR(__xludf.DUMMYFUNCTION("""COMPUTED_VALUE"""),"Мохито клубничный лёд") -> Мохито клубничный лёд | L83: =IFERROR(__xludf.DUMMYFUNCTION("""COMPUTED_VALUE"""),"Черная вишня лёд") -> Черная вишня лёд | M83: =IFERROR(__xludf.DUMMYFUNCTION("""COMPUTED_VALUE"""),"Ананас кокос лёд") -> Ананас кокос лёд | N83: =IFERROR(__xludf.DUMMYFUNCTION("""COMPUTED_VALUE"""),"Киви лёд") -> Киви лёд | O83: =IFERROR(__xludf.DUMMYFUNCTION("""COMPUTED_VALUE"""),"Кислая клюква лёд") -> Кислая клюква лёд | P83: =IFERROR(__xludf.DUMMYFUNCTION("""COMPUTED_VALUE"""),"Кислый скитлс лёд") -> Кислый скитлс лёд | Q83: =IFERROR(__xludf.DUMMYFUNCTION("""COMPUTED_VALUE"""),"Клубника черника лёд") -> Клубника черника лёд | R83: =IFERROR(__xludf.DUMMYFUNCTION("""COMPUTED_VALUE"""),"Малина смородина лёд") -> Малина смородина лёд | S83: =IFERROR(__xludf.DUMMYFUNCTION("""COMPUTED_VALUE"""),"Манго лёд") -> Манго лёд | T83: =IFERROR(__xludf.DUMMYFUNCTION("""COMPUTED_VALUE"""),"Малина вишня лёд") -> Малина вишня лёд
A84: =IFERROR(__xludf.DUMMYFUNCTION("""COMPUTED_VALUE"""),"Ананас киви") -> Ананас киви | B84: =IFERROR(__xludf.DUMMYFUNCTION("""COMPUTED_VALUE"""),"Арбузный смузи") -> Арбузный смузи | C84: =IFERROR(__xludf.DUMMYFUNCTION("""COMPUTED_VALUE"""),"Виноградная фанта") -> Виноградная фанта | D84: =IFERROR(__xludf.DUMMYFUNCTION("""COMPUTED_VALUE"""),"Вишневый морс") -> Вишневый морс | E84: =IFERROR(__xludf.DUMMYFUNCTION("""COMPUTED_VALUE"""),"Гранатовый мармелад") -> Гранатовый мармелад | F84: =IFERROR(__xludf.DUMMYFUNCTION("""COMPUTED_VALUE"""),"Грейпфрут киви") -> Грейпфрут киви | G84: =IFERROR(__xludf.DUMMYFUNCTION("""COMPUTED_VALUE"""),"Ежевика мята") -> Ежевика мята | H84: =IFERROR(__xludf.DUMMYFUNCTION("""COMPUTED_VALUE"""),"Киви манго") -> Киви манго | I84: =IFERROR(__xludf.DUMMYFUNCTION("""COMPUTED_VALUE"""),"Клубника манго") -> Клубника манго | J84: =IFERROR(__xludf.DUMMYFUNCTION("""COMPUTED_VALUE"""),"черника грейфрут ") -> черника грейфрут | K84: =IFERROR(__xludf.DUMMYFUNCTION("""COMPUTED_VALUE"""),"Малина лайм") -> Малина лайм | L84: =IFERROR(__xludf.DUMMYFUNCTION("""COMPUTED_VALUE"""),"Манго арбуз ") -> Манго арбуз | M84: =IFERROR(__xludf.DUMMYFUNCTION("""COMPUTED_VALUE"""),"Малиновый чай с жасмином") -> Малиновый чай с жасмином | N84: =IFERROR(__xludf.DUMMYFUNCTION("""COMPUTED_VALUE"""),"малина апельсин ") -> малина апельсин | O84: =IFERROR(__xludf.DUMMYFUNCTION("""COMPUTED_VALUE"""),"Манго апельсин") -> Манго апельсин | P84: =IFERROR(__xludf.DUMMYFUNCTION("""COMPUTED_VALUE"""),"Ред булл") -> Ред булл | Q84: =IFERROR(__xludf.DUMMYFUNCTION("""COMPUTED_VALUE"""),"Спрайт") -> Спрайт | R84: =IFERROR(__xludf.DUMMYFUNCTION("""COMPUTED_VALUE"""),"ананас клюква ") -> ананас клюква | S84: =IFERROR(__xludf.DUMMYFUNCTION("""COMPUTED_VALUE"""),"Тархун") -> Тархун | T84: =IFERROR(__xludf.DUMMYFUNCTION("""COMPUTED_VALUE"""),"алоэ Виноград ") -> алоэ Виноград | U84: =IFERROR(__xludf.DUMMYFUNCTION("""COMPUTED_VALUE"""),"Фруктовая жвачка") -> Фруктовая жвачка | V84: =IFERROR(__xludf.DUMMYFUNCTION("""COMPUTED_VALUE"""),"Холодная кола") -> Холодная кола | W84: =IFERROR(__xludf.DUMMYFUNCTION("""COMPUTED_VALUE"""),"Черная смородина клюква") -> Черная смородина клюква | X84: =IFERROR(__xludf.DUMMYFUNCTION("""COMPUTED_VALUE"""),"Черника арбуз") -> Черника арбуз | Y84: =IFERROR(__xludf.DUMMYFUNCTION("""COMPUTED_VALUE"""),"Яблоко черника") -> Яблоко черника
A85: =IFERROR(__xludf.DUMMYFUNCTION("""COMPUTED_VALUE"""),"Экзотический микс") -> Экзотический микс | B85: =IFERROR(__xludf.DUMMYFUNCTION("""COMPUTED_VALUE"""),"Энергетик") -> Энергетик | C85: =IFERROR(__xludf.DUMMYFUNCTION("""COMPUTED_VALUE"""),"Виноградный чупа-чупс") -> Виноградный чупа-чупс | D85: =IFERROR(__xludf.DUMMYFUNCTION("""COMPUTED_VALUE"""),"Кислая лесная клюква") -> Кислая лесная клюква | E85: =IFERROR(__xludf.DUMMYFUNCTION("""COMPUTED_VALUE"""),"Смородина персик") -> Смородина персик | F85: =IFERROR(__xludf.DUMMYFUNCTION("""COMPUTED_VALUE"""),"Спелый киви кисло сладкий") -> Спелый киви кисло сладкий | G85: =IFERROR(__xludf.DUMMYFUNCTION("""COMPUTED_VALUE"""),"Кислые черви в вишневом сиропе") -> Кислые черви в вишневом сиропе | H85: =IFERROR(__xludf.DUMMYFUNCTION("""COMPUTED_VALUE"""),"Грушевый лимонад") -> Грушевый лимонад | I85: =IFERROR(__xludf.DUMMYFUNCTION("""COMPUTED_VALUE"""),"Лимонад с сладкой малиной") -> Лимонад с сладкой малиной | J85: =IFERROR(__xludf.DUMMYFUNCTION("""COMPUTED_VALUE"""),"Ананасовая кислинка") -> Ананасовая кислинка | K85: =IFERROR(__xludf.DUMMYFUNCTION("""COMPUTED_VALUE"""),"Мармеладные мишки") -> Мармеладные мишки | L85: =IFERROR(__xludf.DUMMYFUNCTION("""COMPUTED_VALUE"""),"Мандариновый сок с цедрой") -> Мандариновый сок с цедрой | M85: =IFERROR(__xludf.DUMMYFUNCTION("""COMPUTED_VALUE"""),"Кисло-сладкое ягодное драже") -> Кисло-сладкое ягодное драже | N85: =IFERROR(__xludf.DUMMYFUNCTION("""COMPUTED_VALUE"""),"Классическая фанта") -> Классическая фанта | O85: =IFERROR(__xludf.DUMMYFUNCTION("""COMPUTED_VALUE"""),"Сладкие барбарисоввые конфеты") -> Сладкие барбарисоввые конфеты
A86: =IFERROR(__xludf.DUMMYFUNCTION("""COMPUTED_VALUE"""),"Арбуз Малина ") -> Арбуз Малина | B86: =IFERROR(__xludf.DUMMYFUNCTION("""COMPUTED_VALUE"""),"Банан Кокос ") -> Банан Кокос | C86: =IFERROR(__xludf.DUMMYFUNCTION("""COMPUTED_VALUE"""),"Барбарисовый Энергетик ") -> Барбарисовый Энергетик | D86: =IFERROR(__xludf.DUMMYFUNCTION("""COMPUTED_VALUE"""),"Виноградный Энергетик") -> Виноградный Энергетик | E86: =IFERROR(__xludf.DUMMYFUNCTION("""COMPUTED_VALUE"""),"Гранат Клубника ") -> Гранат Клубника | F86: =IFERROR(__xludf.DUMMYFUNCTION("""COMPUTED_VALUE"""),"Гранат Смородина ") -> Гранат Смородина | G86: =IFERROR(__xludf.DUMMYFUNCTION("""COMPUTED_VALUE"""),"Грейпфрутовый Швепс ") -> Грейпфрутовый Швепс | H86: =IFERROR(__xludf.DUMMYFUNCTION("""COMPUTED_VALUE"""),"Земляника Драгонфрут ") -> Земляника Драгонфрут | I86: =IFERROR(__xludf.DUMMYFUNCTION("""COMPUTED_VALUE"""),"Киви Личи ") -> Киви Личи | J86: =IFERROR(__xludf.DUMMYFUNCTION("""COMPUTED_VALUE"""),"Киви Маракуйя Гуава ") -> Киви Маракуйя Гуава | K86: =IFERROR(__xludf.DUMMYFUNCTION("""COMPUTED_VALUE"""),"Клубника Банан ") -> Клубника Банан | L86: =IFERROR(__xludf.DUMMYFUNCTION("""COMPUTED_VALUE"""),"Клубника Вишня ") -> Клубника Вишня | M86: =IFERROR(__xludf.DUMMYFUNCTION("""COMPUTED_VALUE"""),"Клубника Земляника ") -> Клубника Земляника | N86: =IFERROR(__xludf.DUMMYFUNCTION("""COMPUTED_VALUE"""),"Клубничный Мохито ") -> Клубничный Мохито | O86: =IFERROR(__xludf.DUMMYFUNCTION("""COMPUTED_VALUE"""),"Манго Грейпфрут ") -> Манго Грейпфрут | P86: =IFERROR(__xludf.DUMMYFUNCTION("""COMPUTED_VALUE"""),"Манго Персик Личи ") -> Манго Персик Личи | Q86: =IFERROR(__xludf.DUMMYFUNCTION("""COMPUTED_VALUE"""),"Персик Бабл Гам ") -> Персик Бабл Гам | R86: =IFERROR(__xludf.DUMMYFUNCTION("""COMPUTED_VALUE"""),"Садовые Ягоды ") -> Садовые Ягоды | S86: =IFERROR(__xludf.DUMMYFUNCTION("""COMPUTED_VALUE"""),"Скитлс Лимон Лайм 2") -> Скитлс Лимон Лайм 2 | T86: =IFERROR(__xludf.DUMMYFUNCTION("""COMPUTED_VALUE"""),"Смородина Мармелад 1") -> Смородина Мармелад 1 | U86: =IFERROR(__xludf.DUMMYFUNCTION("""COMPUTED_VALUE"""),"Темная Вишня 1") -> Темная Вишня 1 | V86: =IFERROR(__xludf.DUMMYFUNCTION("""COMPUTED_VALUE"""),"Фруктовые Пластинки 1") -> Фруктовые Пластинки 1 | W86: =IFERROR(__xludf.DUMMYFUNCTION("""COMPUTED_VALUE"""),"Черника Ежевика 1") -> Черника Ежевика 1 | X86: =IFERROR(__xludf.DUMMYFUNCTION("""COMPUTED_VALUE"""),"Черника Малина 1") -> Черника Малина 1 | Y86: =IFERROR(__xludf.DUMMYFUNCTION("""COMPUTED_VALUE"""),"Черника Мята 2") -> Черника Мята 2 | Z86: =IFERROR(__xludf.DUMMYFUNCTION("""COMPUTED_VALUE"""),"Яблоко Виноград 2") -> Яблоко Виноград 2 | AA86: =IFERROR(__xludf.DUMMYFUNCTION("""COMPUTED_VALUE"""),"Яблоко Малина 4") -> Яблоко Малина 4
A87: =IFERROR(__xludf.DUMMYFUNCTION("""COMPUTED_VALUE"""),"Арбуз Малина ") -> Арбуз Малина | B87: =IFERROR(__xludf.DUMMYFUNCTION("""COMPUTED_VALUE"""),"Банан Кокос ") -> Банан Кокос | C87: =IFERROR(__xludf.DUMMYFUNCTION("""COMPUTED_VALUE"""),"Барбарисовый Энергетик ") -> Барбарисовый Энергетик | D87: =IFERROR(__xludf.DUMMYFUNCTION("""COMPUTED_VALUE"""),"Виноградный Энергетик") -> Виноградный Энергетик | E87: =IFERROR(__xludf.DUMMYFUNCTION("""COMPUTED_VALUE"""),"Гранат Клубника ") -> Гранат Клубника | F87: =IFERROR(__xludf.DUMMYFUNCTION("""COMPUTED_VALUE"""),"Гранат Смородина ") -> Гранат Смородина | G87: =IFERROR(__xludf.DUMMYFUNCTION("""COMPUTED_VALUE"""),"Грейпфрутовый Швепс ") -> Грейпфрутовый Швепс | H87: =IFERROR(__xludf.DUMMYFUNCTION("""COMPUTED_VALUE"""),"Земляника Драгонфрут ") -> Земляника Драгонфрут | I87: =IFERROR(__xludf.DUMMYFUNCTION("""COMPUTED_VALUE"""),"Киви Личи ") -> Киви Личи | J87: =IFERROR(__xludf.DUMMYFUNCTION("""COMPUTED_VALUE"""),"Киви Маракуйя Гуава ") -> Киви Маракуйя Гуава | K87: =IFERROR(__xludf.DUMMYFUNCTION("""COMPUTED_VALUE"""),"Клубника Банан ") -> Клубника Банан | L87: =IFERROR(__xludf.DUMMYFUNCTION("""COMPUTED_VALUE"""),"Клубника Вишня ") -> Клубника Вишня | M87: =IFERROR(__xludf.DUMMYFUNCTION("""COMPUTED_VALUE"""),"Клубника Земляника ") -> Клубника Земляника | N87: =IFERROR(__xludf.DUMMYFUNCTION("""COMPUTED_VALUE"""),"Клубничный Мохито ") -> Клубничный Мохито | O87: =IFERROR(__xludf.DUMMYFUNCTION("""COMPUTED_VALUE"""),"Манго Грейпфрут ") -> Манго Грейпфрут | P87: =IFERROR(__xludf.DUMMYFUNCTION("""COMPUTED_VALUE"""),"Манго Персик Личи ") -> Манго Персик Личи | Q87: =IFERROR(__xludf.DUMMYFUNCTION("""COMPUTED_VALUE"""),"Персик Бабл Гам ") -> Персик Бабл Гам | R87: =IFERROR(__xludf.DUMMYFUNCTION("""COMPUTED_VALUE"""),"Садовые Ягоды ") -> Садовые Ягоды | S87: =IFERROR(__xludf.DUMMYFUNCTION("""COMPUTED_VALUE"""),"Скитлс Лимон Лайм 2") -> Скитлс Лимон Лайм 2 | T87: =IFERROR(__xludf.DUMMYFUNCTION("""COMPUTED_VALUE"""),"Смородина Мармелад 1") -> Смородина Мармелад 1 | U87: =IFERROR(__xludf.DUMMYFUNCTION("""COMPUTED_VALUE"""),"Темная Вишня 1") -> Темная Вишня 1 | V87: =IFERROR(__xludf.DUMMYFUNCTION("""COMPUTED_VALUE"""),"Фруктовые Пластинки 1") -> Фруктовые Пластинки 1 | W87: =IFERROR(__xludf.DUMMYFUNCTION("""COMPUTED_VALUE"""),"Черника Ежевика 1") -> Черника Ежевика 1 | X87: =IFERROR(__xludf.DUMMYFUNCTION("""COMPUTED_VALUE"""),"Черника Малина 1") -> Черника Малина 1 | Y87: =IFERROR(__xludf.DUMMYFUNCTION("""COMPUTED_VALUE"""),"Черника Мята 2") -> Черника Мята 2 | Z87: =IFERROR(__xludf.DUMMYFUNCTION("""COMPUTED_VALUE"""),"Яблоко Виноград 2") -> Яблоко Виноград 2 | AA87: =IFERROR(__xludf.DUMMYFUNCTION("""COMPUTED_VALUE"""),"Яблоко Малина 4") -> Яблоко Малина 4
A88: =IFERROR(__xludf.DUMMYFUNCTION("""COMPUTED_VALUE"""),"Маракуйя с тропическими нотками") -> Маракуйя с тропическими нотками | B88: =IFERROR(__xludf.DUMMYFUNCTION("""COMPUTED_VALUE"""),"Арбузный милкшейк") -> Арбузный милкшейк | C88: =IFERROR(__xludf.DUMMYFUNCTION("""COMPUTED_VALUE"""),"Конфеты со вкусом винограда") -> Конфеты со вкусом винограда | D88: =IFERROR(__xludf.DUMMYFUNCTION("""COMPUTED_VALUE"""),"Манго с апельсином и послевкусием гуавы") -> Манго с апельсином и послевкусием гуавы | E88: =IFERROR(__xludf.DUMMYFUNCTION("""COMPUTED_VALUE"""),"Холодное сочетание мяты и конфет холс") -> Холодное сочетание мяты и конфет холс | F88: =IFERROR(__xludf.DUMMYFUNCTION("""COMPUTED_VALUE"""),"Яблочные мармеладные червячки") -> Яблочные мармеладные червячки | G88: =IFERROR(__xludf.DUMMYFUNCTION("""COMPUTED_VALUE"""),"Микс сладкогоперсика и вишни с кислинкой") -> Микс сладкогоперсика и вишни с кислинкой | H88: =IFERROR(__xludf.DUMMYFUNCTION("""COMPUTED_VALUE"""),"Лимон лайм") -> Лимон лайм | I88: =IFERROR(__xludf.DUMMYFUNCTION("""COMPUTED_VALUE"""),"Классика энергетика с кислой малиной") -> Классика энергетика с кислой малиной | J88: =IFERROR(__xludf.DUMMYFUNCTION("""COMPUTED_VALUE"""),"Зеленое манго и смородина") -> Зеленое манго и смородина | K88: =IFERROR(__xludf.DUMMYFUNCTION("""COMPUTED_VALUE"""),"Дуэт лемонграсса и сладкой малины") -> Дуэт лемонграсса и сладкой малины | L88: =IFERROR(__xludf.DUMMYFUNCTION("""COMPUTED_VALUE"""),"Сладкий мармелад из черной смородины") -> Сладкий мармелад из черной смородины | M88: =IFERROR(__xludf.DUMMYFUNCTION("""COMPUTED_VALUE"""),"Вишня кола") -> Вишня кола | N88: =IFERROR(__xludf.DUMMYFUNCTION("""COMPUTED_VALUE"""),"Малина с кокосом") -> Малина с кокосом | O88: =IFERROR(__xludf.DUMMYFUNCTION("""COMPUTED_VALUE"""),"Сладкие конфеты СКИТЛЗ и смородина") -> Сладкие конфеты СКИТЛЗ и смородина | P88: =IFERROR(__xludf.DUMMYFUNCTION("""COMPUTED_VALUE"""),"Ежевичный лимонад") -> Ежевичный лимонад | Q88: =IFERROR(__xludf.DUMMYFUNCTION("""COMPUTED_VALUE"""),"Дыня кокос") -> Дыня кокос | R88: =IFERROR(__xludf.DUMMYFUNCTION("""COMPUTED_VALUE"""),"Земляничный бабл гам") -> Земляничный бабл гам | S88: =IFERROR(__xludf.DUMMYFUNCTION("""COMPUTED_VALUE"""),"Лимонные леденцы") -> Лимонные леденцы | T88: =IFERROR(__xludf.DUMMYFUNCTION("""COMPUTED_VALUE"""),"Экзотический фрукты") -> Экзотический фрукты | U88: =IFERROR(__xludf.DUMMYFUNCTION("""COMPUTED_VALUE"""),"Личи виноград мята") -> Личи виноград мята | V88: =IFERROR(__xludf.DUMMYFUNCTION("""COMPUTED_VALUE"""),"Черника малина мята") -> Черника малина мята | W88: =IFERROR(__xludf.DUMMYFUNCTION("""COMPUTED_VALUE"""),"Абрикосовый йогурт") -> Абрикосовый йогурт | X88: =IFERROR(__xludf.DUMMYFUNCTION("""COMPUTED_VALUE"""),"Арбуз лед") -> Арбуз лед | Y88: =IFERROR(__xludf.DUMMYFUNCTION("""COMPUTED_VALUE"""),"Банан клубника лед") -> Банан клубника лед | Z88: =IFERROR(__xludf.DUMMYFUNCTION("""COMPUTED_VALUE"""),"Арбузное мороженное") -> Арбузное мороженное | AA88: =IFERROR(__xludf.DUMMYFUNCTION("""COMPUTED_VALUE"""),"Клубника малина жвачка") -> Клубника малина жвачка | AB88: =IFERROR(__xludf.DUMMYFUNCTION("""COMPUTED_VALUE"""),"Клубничное мороженное") -> Клубничное мороженное | AC88: =IFERROR(__xludf.DUMMYFUNCTION("""COMPUTED_VALUE"""),"Кола сода лед") -> Кола сода лед | AD88: =IFERROR(__xludf.DUMMYFUNCTION("""COMPUTED_VALUE"""),"Банановый милкшейк") -> Банановый милкшейк | AE88: =IFERROR(__xludf.DUMMYFUNCTION("""COMPUTED_VALUE"""),"Микс ягод лед") -> Микс ягод лед | AF88: =IFERROR(__xludf.DUMMYFUNCTION("""COMPUTED_VALUE"""),"Брусничный морс") -> Брусничный морс | AG88: =IFERROR(__xludf.DUMMYFUNCTION("""COMPUTED_VALUE"""),"Яблочный лимонад") -> Яблочный лимонад | AH88: =IFERROR(__xludf.DUMMYFUNCTION("""COMPUTED_VALUE"""),"Лесные ягоды") -> Лесные ягоды | AI88: =IFERROR(__xludf.DUMMYFUNCTION("""COMPUTED_VALUE"""),"Смородиновый лимонад") -> Смородиновый лимонад | AJ88: =IFERROR(__xludf.DUMMYFUNCTION("""COMPUTED_VALUE"""),"Вишня лайм лед") -> Вишня лайм лед | AK88: =IFERROR(__xludf.DUMMYFUNCTION("""COMPUTED_VALUE"""),"Лист виноград мята энергетик") -> Лист виноград мята энергетик | AL88: =IFERROR(__xludf.DUMMYFUNCTION("""COMPUTED_VALUE"""),"Двойное яблоко лед") -> Двойное яблоко лед | AM88: =IFERROR(__xludf.DUMMYFUNCTION("""COMPUTED_VALUE"""),"Смородиновый холс") -> Смородиновый холс | AN88: =IFERROR(__xludf.DUMMYFUNCTION("""COMPUTED_VALUE"""),"Клубничное шампанское") -> Клубничное шампанское
A89: =IFERROR(__xludf.DUMMYFUNCTION("""COMPUTED_VALUE"""),"кислая земляника") -> кислая земляника | B89: =IFERROR(__xludf.DUMMYFUNCTION("""COMPUTED_VALUE"""),"кислая фанта с черникой") -> кислая фанта с черникой | C89: =IFERROR(__xludf.DUMMYFUNCTION("""COMPUTED_VALUE"""),"кислое харибо с колой и черешней") -> кислое харибо с колой и черешней | D89: =IFERROR(__xludf.DUMMYFUNCTION("""COMPUTED_VALUE"""),"кислое яблочно клубничная шипучка") -> кислое яблочно клубничная шипучка | E89: =IFERROR(__xludf.DUMMYFUNCTION("""COMPUTED_VALUE"""),"кислые желатинки маракуйя ананас") -> кислые желатинки маракуйя ананас | F89: =IFERROR(__xludf.DUMMYFUNCTION("""COMPUTED_VALUE"""),"кислые ленточки маракуя манго") -> кислые ленточки маракуя манго | G89: =IFERROR(__xludf.DUMMYFUNCTION("""COMPUTED_VALUE"""),"кислые мармеладные ягоды") -> кислые мармеладные ягоды | H89: =IFERROR(__xludf.DUMMYFUNCTION("""COMPUTED_VALUE"""),"кислый виноград лайм") -> кислый виноград лайм | I89: =IFERROR(__xludf.DUMMYFUNCTION("""COMPUTED_VALUE"""),"кислый грейпфрут с вишней") -> кислый грейпфрут с вишней | J89: =IFERROR(__xludf.DUMMYFUNCTION("""COMPUTED_VALUE"""),"кислый леденец виноград киви яблоко") -> кислый леденец виноград киви яблоко | K89: =IFERROR(__xludf.DUMMYFUNCTION("""COMPUTED_VALUE"""),"кислый лимонад арбуз лайм малина") -> кислый лимонад арбуз лайм малина | L89: =IFERROR(__xludf.DUMMYFUNCTION("""COMPUTED_VALUE"""),"кислый персик клубника") -> кислый персик клубника | M89: =IFERROR(__xludf.DUMMYFUNCTION("""COMPUTED_VALUE"""),"кислый яблочно лимонные колечки") -> кислый яблочно лимонные колечки | N89: =IFERROR(__xludf.DUMMYFUNCTION("""COMPUTED_VALUE"""),"фанта апельсин с кислой малиной") -> фанта апельсин с кислой малиной
A90: =IFERROR(__xludf.DUMMYFUNCTION("""COMPUTED_VALUE"""),"Арбуз Малина ") -> Арбуз Малина | B90: =IFERROR(__xludf.DUMMYFUNCTION("""COMPUTED_VALUE"""),"Банан Кокос ") -> Банан Кокос | C90: =IFERROR(__xludf.DUMMYFUNCTION("""COMPUTED_VALUE"""),"Барбарисовый Энергетик ") -> Барбарисовый Энергетик | D90: =IFERROR(__xludf.DUMMYFUNCTION("""COMPUTED_VALUE"""),"Виноградный Энергетик") -> Виноградный Энергетик | E90: =IFERROR(__xludf.DUMMYFUNCTION("""COMPUTED_VALUE"""),"Гранат Клубника ") -> Гранат Клубника | F90: =IFERROR(__xludf.DUMMYFUNCTION("""COMPUTED_VALUE"""),"Гранат Смородина ") -> Гранат Смородина | G90: =IFERROR(__xludf.DUMMYFUNCTION("""COMPUTED_VALUE"""),"Грейпфрутовый Швепс ") -> Грейпфрутовый Швепс | H90: =IFERROR(__xludf.DUMMYFUNCTION("""COMPUTED_VALUE"""),"Земляника Драгонфрут ") -> Земляника Драгонфрут | I90: =IFERROR(__xludf.DUMMYFUNCTION("""COMPUTED_VALUE"""),"Киви Личи ") -> Киви Личи | J90: =IFERROR(__xludf.DUMMYFUNCTION("""COMPUTED_VALUE"""),"Киви Маракуйя Гуава ") -> Киви Маракуйя Гуава | K90: =IFERROR(__xludf.DUMMYFUNCTION("""COMPUTED_VALUE"""),"Клубника Банан ") -> Клубника Банан | L90: =IFERROR(__xludf.DUMMYFUNCTION("""COMPUTED_VALUE"""),"Клубника Вишня ") -> Клубника Вишня | M90: =IFERROR(__xludf.DUMMYFUNCTION("""COMPUTED_VALUE"""),"Клубника Земляника ") -> Клубника Земляника | N90: =IFERROR(__xludf.DUMMYFUNCTION("""COMPUTED_VALUE"""),"Клубничный Мохито ") -> Клубничный Мохито | O90: =IFERROR(__xludf.DUMMYFUNCTION("""COMPUTED_VALUE"""),"Манго Грейпфрут ") -> Манго Грейпфрут | P90: =IFERROR(__xludf.DUMMYFUNCTION("""COMPUTED_VALUE"""),"Манго Персик Личи ") -> Манго Персик Личи | Q90: =IFERROR(__xludf.DUMMYFUNCTION("""COMPUTED_VALUE"""),"Персик Бабл Гам ") -> Персик Бабл Гам | R90: =IFERROR(__xludf.DUMMYFUNCTION("""COMPUTED_VALUE"""),"Садовые Ягоды ") -> Садовые Ягоды | S90: =IFERROR(__xludf.DUMMYFUNCTION("""COMPUTED_VALUE"""),"Скитлс Лимон Лайм 2") -> Скитлс Лимон Лайм 2 | T90: =IFERROR(__xludf.DUMMYFUNCTION("""COMPUTED_VALUE"""),"Смородина Мармелад 1") -> Смородина Мармелад 1 | U90: =IFERROR(__xludf.DUMMYFUNCTION("""COMPUTED_VALUE"""),"Темная Вишня 1") -> Темная Вишня 1 | V90: =IFERROR(__xludf.DUMMYFUNCTION("""COMPUTED_VALUE"""),"Фруктовые Пластинки 1") -> Фруктовые Пластинки 1 | W90: =IFERROR(__xludf.DUMMYFUNCTION("""COMPUTED_VALUE"""),"Черника Ежевика 1") -> Черника Ежевика 1 | X90: =IFERROR(__xludf.DUMMYFUNCTION("""COMPUTED_VALUE"""),"Черника Малина 1") -> Черника Малина 1 | Y90: =IFERROR(__xludf.DUMMYFUNCTION("""COMPUTED_VALUE"""),"Черника Мята 2") -> Черника Мята 2 | Z90: =IFERROR(__xludf.DUMMYFUNCTION("""COMPUTED_VALUE"""),"Яблоко Виноград 2") -> Яблоко Виноград 2 | AA90: =IFERROR(__xludf.DUMMYFUNCTION("""COMPUTED_VALUE"""),"Яблоко Малина 4") -> Яблоко Малина 4
A91: =IFERROR(__xludf.DUMMYFUNCTION("""COMPUTED_VALUE"""),"Кислый малиново-грейпфрутовый швепс") -> Кислый малиново-грейпфрутовый швепс | B91: =IFERROR(__xludf.DUMMYFUNCTION("""COMPUTED_VALUE"""),"Ананас апельсин") -> Ананас апельсин | C91: =IFERROR(__xludf.DUMMYFUNCTION("""COMPUTED_VALUE"""),"Пинаколада") -> Пинаколада | D91: =IFERROR(__xludf.DUMMYFUNCTION("""COMPUTED_VALUE"""),"Мятный бабл гам") -> Мятный бабл гам | E91: =IFERROR(__xludf.DUMMYFUNCTION("""COMPUTED_VALUE"""),"Мянго драгонфрут") -> Мянго драгонфрут | F91: =IFERROR(__xludf.DUMMYFUNCTION("""COMPUTED_VALUE"""),"Клубничная фанта") -> Клубничная фанта | G91: =IFERROR(__xludf.DUMMYFUNCTION("""COMPUTED_VALUE"""),"Клубничная арбуз") -> Клубничная арбуз | H91: =IFERROR(__xludf.DUMMYFUNCTION("""COMPUTED_VALUE"""),"Кислый скитлс") -> Кислый скитлс | I91: =IFERROR(__xludf.DUMMYFUNCTION("""COMPUTED_VALUE"""),"Кислый лайм арбуз") -> Кислый лайм арбуз | J91: =IFERROR(__xludf.DUMMYFUNCTION("""COMPUTED_VALUE"""),"Тропический банан") -> Тропический банан | K91: =IFERROR(__xludf.DUMMYFUNCTION("""COMPUTED_VALUE"""),"Яблочный энергетик") -> Яблочный энергетик | L91: =IFERROR(__xludf.DUMMYFUNCTION("""COMPUTED_VALUE"""),"Барбарисовый лимонад") -> Барбарисовый лимонад | M91: =IFERROR(__xludf.DUMMYFUNCTION("""COMPUTED_VALUE"""),"Лимонад виноград вишня") -> Лимонад виноград вишня | N91: =IFERROR(__xludf.DUMMYFUNCTION("""COMPUTED_VALUE"""),"Розовый лимонад") -> Розовый лимонад | O91: =IFERROR(__xludf.DUMMYFUNCTION("""COMPUTED_VALUE"""),"Двойной манго") -> Двойной манго | P91: =IFERROR(__xludf.DUMMYFUNCTION("""COMPUTED_VALUE"""),"Лесные ягоды ") -> Лесные ягоды | Q91: =IFERROR(__xludf.DUMMYFUNCTION("""COMPUTED_VALUE"""),"Ежевика малина ") -> Ежевика малина | R91: =IFERROR(__xludf.DUMMYFUNCTION("""COMPUTED_VALUE"""),"Смородиновый лимонад") -> Смородиновый лимонад | S91: =IFERROR(__xludf.DUMMYFUNCTION("""COMPUTED_VALUE"""),"Кола вишня") -> Кола вишня | T91: =IFERROR(__xludf.DUMMYFUNCTION("""COMPUTED_VALUE"""),"Манго арбуз") -> Манго арбуз | U91: =IFERROR(__xludf.DUMMYFUNCTION("""COMPUTED_VALUE"""),"Алоэ виноград") -> Алоэ виноград | V91: =IFERROR(__xludf.DUMMYFUNCTION("""COMPUTED_VALUE"""),"Банан клубника") -> Банан клубника | W91: =IFERROR(__xludf.DUMMYFUNCTION("""COMPUTED_VALUE"""),"Малиновый мармелад") -> Малиновый мармелад | X91: =IFERROR(__xludf.DUMMYFUNCTION("""COMPUTED_VALUE"""),"Клубника киви") -> Клубника киви | Y91: =IFERROR(__xludf.DUMMYFUNCTION("""COMPUTED_VALUE"""),"Клюква лайм") -> Клюква лайм | Z91: =IFERROR(__xludf.DUMMYFUNCTION("""COMPUTED_VALUE"""),"Гуава ананас") -> Гуава ананас | AA91: =IFERROR(__xludf.DUMMYFUNCTION("""COMPUTED_VALUE"""),"Морс") -> Морс | AB91: =IFERROR(__xludf.DUMMYFUNCTION("""COMPUTED_VALUE"""),"Красный апельсин") -> Красный апельсин | AC91: =IFERROR(__xludf.DUMMYFUNCTION("""COMPUTED_VALUE"""),"Арбузная жвачка") -> Арбузная жвачка | AD91: =IFERROR(__xludf.DUMMYFUNCTION("""COMPUTED_VALUE"""),"Смородина Виноград") -> Смородина Виноград | AE91: =IFERROR(__xludf.DUMMYFUNCTION("""COMPUTED_VALUE"""),"Гранатовая Мармелад") -> Гранатовая Мармелад | AF91: =IFERROR(__xludf.DUMMYFUNCTION("""COMPUTED_VALUE"""),"Яблоко Киви") -> Яблоко Киви | AG91: =IFERROR(__xludf.DUMMYFUNCTION("""COMPUTED_VALUE"""),"Клубника Ежевика") -> Клубника Ежевика | AH91: =IFERROR(__xludf.DUMMYFUNCTION("""COMPUTED_VALUE"""),"Клубничный Коктейль") -> Клубничный Коктейль | AI91: =IFERROR(__xludf.DUMMYFUNCTION("""COMPUTED_VALUE"""),"Клюква Земляника ") -> Клюква Земляника | AJ91: =IFERROR(__xludf.DUMMYFUNCTION("""COMPUTED_VALUE"""),"Какос Дыня") -> Какос Дыня | AK91: =IFERROR(__xludf.DUMMYFUNCTION("""COMPUTED_VALUE"""),"Маракуйя мандарин") -> Маракуйя мандарин | AL91: =IFERROR(__xludf.DUMMYFUNCTION("""COMPUTED_VALUE"""),"Персик кактус") -> Персик кактус | AM91: =IFERROR(__xludf.DUMMYFUNCTION("""COMPUTED_VALUE"""),"Спрайт") -> Спрайт | AN91: =IFERROR(__xludf.DUMMYFUNCTION("""COMPUTED_VALUE"""),"Черничная фанта") -> Черничная фанта | AO91: =IFERROR(__xludf.DUMMYFUNCTION("""COMPUTED_VALUE"""),"Ягодная жвачка") -> Ягодная жвачка | AP91: =IFERROR(__xludf.DUMMYFUNCTION("""COMPUTED_VALUE"""),"Ягодный энергетик") -> Ягодный энергетик | AQ91: =IFERROR(__xludf.DUMMYFUNCTION("""COMPUTED_VALUE"""),"Ягодный пунш ") -> Ягодный пунш | AR91: =IFERROR(__xludf.DUMMYFUNCTION("""COMPUTED_VALUE"""),"Виноградный холс") -> Виноградный холс | AS91: =IFERROR(__xludf.DUMMYFUNCTION("""COMPUTED_VALUE"""),"Грейпфрут смородина") -> Грейпфрут смородина | AT91: =IFERROR(__xludf.DUMMYFUNCTION("""COMPUTED_VALUE"""),"Дыня персик") -> Дыня персик | AU91: =IFERROR(__xludf.DUMMYFUNCTION("""COMPUTED_VALUE"""),"Земляника виноград") -> Земляника виноград | AV91: =IFERROR(__xludf.DUMMYFUNCTION("""COMPUTED_VALUE"""),"Киви маракуйя гуава") -> Киви маракуйя гуава | AW91: =IFERROR(__xludf.DUMMYFUNCTION("""COMPUTED_VALUE"""),"Кислые вишнёвые червячки") -> Кислые вишнёвые червячки | AX91: =IFERROR(__xludf.DUMMYFUNCTION("""COMPUTED_VALUE"""),"Кислые чернично-малиновое червячки") -> Кислые чернично-малиновое червячки
A130: =IFERROR(__xludf.DUMMYFUNCTION("""COMPUTED_VALUE"""),"Ананас киви") -> Ананас киви | B130: =IFERROR(__xludf.DUMMYFUNCTION("""COMPUTED_VALUE"""),"Арбузный смузи") -> Арбузный смузи | C130: =IFERROR(__xludf.DUMMYFUNCTION("""COMPUTED_VALUE"""),"Виноградная фанта") -> Виноградная фанта | D130: =IFERROR(__xludf.DUMMYFUNCTION("""COMPUTED_VALUE"""),"Вишневый морс") -> Вишневый морс | E130: =IFERROR(__xludf.DUMMYFUNCTION("""COMPUTED_VALUE"""),"Гранатовый мармелад") -> Гранатовый мармелад | F130: =IFERROR(__xludf.DUMMYFUNCTION("""COMPUTED_VALUE"""),"Грейпфрут киви") -> Грейпфрут киви | G130: =IFERROR(__xludf.DUMMYFUNCTION("""COMPUTED_VALUE"""),"Ежевика мята") -> Ежевика мята | H130: =IFERROR(__xludf.DUMMYFUNCTION("""COMPUTED_VALUE"""),"Киви манго") -> Киви манго | I130: =IFERROR(__xludf.DUMMYFUNCTION("""COMPUTED_VALUE"""),"Клубника манго") -> Клубника манго | J130: =IFERROR(__xludf.DUMMYFUNCTION("""COMPUTED_VALUE"""),"черника грейфрут ") -> черника грейфрут | K130: =IFERROR(__xludf.DUMMYFUNCTION("""COMPUTED_VALUE"""),"Малина лайм") -> Малина лайм | L130: =IFERROR(__xludf.DUMMYFUNCTION("""COMPUTED_VALUE"""),"Манго арбуз ") -> Манго арбуз | M130: =IFERROR(__xludf.DUMMYFUNCTION("""COMPUTED_VALUE"""),"Малиновый чай с жасмином") -> Малиновый чай с жасмином | N130: =IFERROR(__xludf.DUMMYFUNCTION("""COMPUTED_VALUE"""),"малина апельсин ") -> малина апельсин | O130: =IFERROR(__xludf.DUMMYFUNCTION("""COMPUTED_VALUE"""),"Манго апельсин") -> Манго апельсин | P130: =IFERROR(__xludf.DUMMYFUNCTION("""COMPUTED_VALUE"""),"Ред булл") -> Ред булл | Q130: =IFERROR(__xludf.DUMMYFUNCTION("""COMPUTED_VALUE"""),"Спрайт") -> Спрайт | R130: =IFERROR(__xludf.DUMMYFUNCTION("""COMPUTED_VALUE"""),"ананас клюква ") -> ананас клюква | S130: =IFERROR(__xludf.DUMMYFUNCTION("""COMPUTED_VALUE"""),"Тархун") -> Тархун | T130: =IFERROR(__xludf.DUMMYFUNCTION("""COMPUTED_VALUE"""),"алоэ Виноград ") -> алоэ Виноград | U130: =IFERROR(__xludf.DUMMYFUNCTION("""COMPUTED_VALUE"""),"Фруктовая жвачка") -> Фруктовая жвачка | V130: =IFERROR(__xludf.DUMMYFUNCTION("""COMPUTED_VALUE"""),"Холодная кола") -> Холодная кола | W130: =IFERROR(__xludf.DUMMYFUNCTION("""COMPUTED_VALUE"""),"Черная смородина клюква") -> Черная смородина клюква | X130: =IFERROR(__xludf.DUMMYFUNCTION("""COMPUTED_VALUE"""),"Черника арбуз") -> Черника арбуз | Y130: =IFERROR(__xludf.DUMMYFUNCTION("""COMPUTED_VALUE"""),"Яблоко черника") -> Яблоко черника
A131: =IFERROR(__xludf.DUMMYFUNCTION("""COMPUTED_VALUE"""),"Ананас киви") -> Ананас киви | B131: =IFERROR(__xludf.DUMMYFUNCTION("""COMPUTED_VALUE"""),"Арбузный смузи") -> Арбузный смузи | C131: =IFERROR(__xludf.DUMMYFUNCTION("""COMPUTED_VALUE"""),"Виноградная фанта") -> Виноградная фанта | D131: =IFERROR(__xludf.DUMMYFUNCTION("""COMPUTED_VALUE"""),"Вишневый морс") -> Вишневый морс | E131: =IFERROR(__xludf.DUMMYFUNCTION("""COMPUTED_VALUE"""),"Гранатовый мармелад") -> Гранатовый мармелад | F131: =IFERROR(__xludf.DUMMYFUNCTION("""COMPUTED_VALUE"""),"Грейпфрут киви") -> Грейпфрут киви | G131: =IFERROR(__xludf.DUMMYFUNCTION("""COMPUTED_VALUE"""),"Ежевика мята") -> Ежевика мята | H131: =IFERROR(__xludf.DUMMYFUNCTION("""COMPUTED_VALUE"""),"Киви манго") -> Киви манго | I131: =IFERROR(__xludf.DUMMYFUNCTION("""COMPUTED_VALUE"""),"Клубника манго") -> Клубника манго | J131: =IFERROR(__xludf.DUMMYFUNCTION("""COMPUTED_VALUE"""),"черника грейфрут ") -> черника грейфрут | K131: =IFERROR(__xludf.DUMMYFUNCTION("""COMPUTED_VALUE"""),"Малина лайм") -> Малина лайм | L131: =IFERROR(__xludf.DUMMYFUNCTION("""COMPUTED_VALUE"""),"Манго арбуз ") -> Манго арбуз | M131: =IFERROR(__xludf.DUMMYFUNCTION("""COMPUTED_VALUE"""),"Малиновый чай с жасмином") -> Малиновый чай с жасмином | N131: =IFERROR(__xludf.DUMMYFUNCTION("""COMPUTED_VALUE"""),"малина апельсин ") -> малина апельсин | O131: =IFERROR(__xludf.DUMMYFUNCTION("""COMPUTED_VALUE"""),"Манго апельсин") -> Манго апельсин | P131: =IFERROR(__xludf.DUMMYFUNCTION("""COMPUTED_VALUE"""),"Ред булл") -> Ред булл | Q131: =IFERROR(__xludf.DUMMYFUNCTION("""COMPUTED_VALUE"""),"Спрайт") -> Спрайт | R131: =IFERROR(__xludf.DUMMYFUNCTION("""COMPUTED_VALUE"""),"ананас клюква ") -> ананас клюква | S131: =IFERROR(__xludf.DUMMYFUNCTION("""COMPUTED_VALUE"""),"Тархун") -> Тархун | T131: =IFERROR(__xludf.DUMMYFUNCTION("""COMPUTED_VALUE"""),"алоэ Виноград ") -> алоэ Виноград | U131: =IFERROR(__xludf.DUMMYFUNCTION("""COMPUTED_VALUE"""),"Фруктовая жвачка") -> Фруктовая жвачка | V131: =IFERROR(__xludf.DUMMYFUNCTION("""COMPUTED_VALUE"""),"Холодная кола") -> Холодная кола | W131: =IFERROR(__xludf.DUMMYFUNCTION("""COMPUTED_VALUE"""),"Черная смородина клюква") -> Черная смородина клюква | X131: =IFERROR(__xludf.DUMMYFUNCTION("""COMPUTED_VALUE"""),"Черника арбуз") -> Черника арбуз | Y131: =IFERROR(__xludf.DUMMYFUNCTION("""COMPUTED_VALUE"""),"Яблоко черника") -> Яблоко черника
A132: =IFERROR(__xludf.DUMMYFUNCTION("""COMPUTED_VALUE"""),"0.4") -> 0.4 | B132: =IFERROR(__xludf.DUMMYFUNCTION("""COMPUTED_VALUE"""),"0.6") -> 0.6 | C132: =IFERROR(__xludf.DUMMYFUNCTION("""COMPUTED_VALUE"""),"0.7") -> 0.7 | D132: =IFERROR(__xludf.DUMMYFUNCTION("""COMPUTED_VALUE"""),"0.8") -> 0.8
A133: =IFERROR(__xludf.DUMMYFUNCTION("""COMPUTED_VALUE"""),"Арбуз Малина ") -> Арбуз Малина | B133: =IFERROR(__xludf.DUMMYFUNCTION("""COMPUTED_VALUE"""),"Банан Кокос ") -> Банан Кокос | C133: =IFERROR(__xludf.DUMMYFUNCTION("""COMPUTED_VALUE"""),"Барбарисовый Энергетик ") -> Барбарисовый Энергетик | D133: =IFERROR(__xludf.DUMMYFUNCTION("""COMPUTED_VALUE"""),"Виноградный Энергетик") -> Виноградный Энергетик | E133: =IFERROR(__xludf.DUMMYFUNCTION("""COMPUTED_VALUE"""),"Гранат Клубника ") -> Гранат Клубника | F133: =IFERROR(__xludf.DUMMYFUNCTION("""COMPUTED_VALUE"""),"Гранат Смородина ") -> Гранат Смородина | G133: =IFERROR(__xludf.DUMMYFUNCTION("""COMPUTED_VALUE"""),"Грейпфрутовый Швепс ") -> Грейпфрутовый Швепс | H133: =IFERROR(__xludf.DUMMYFUNCTION("""COMPUTED_VALUE"""),"Земляника Драгонфрут ") -> Земляника Драгонфрут | I133: =IFERROR(__xludf.DUMMYFUNCTION("""COMPUTED_VALUE"""),"Киви Личи ") -> Киви Личи | J133: =IFERROR(__xludf.DUMMYFUNCTION("""COMPUTED_VALUE"""),"Киви Маракуйя Гуава ") -> Киви Маракуйя Гуава | K133: =IFERROR(__xludf.DUMMYFUNCTION("""COMPUTED_VALUE"""),"Клубника Банан ") -> Клубника Банан | L133: =IFERROR(__xludf.DUMMYFUNCTION("""COMPUTED_VALUE"""),"Клубника Вишня ") -> Клубника Вишня | M133: =IFERROR(__xludf.DUMMYFUNCTION("""COMPUTED_VALUE"""),"Клубника Земляника ") -> Клубника Земляника | N133: =IFERROR(__xludf.DUMMYFUNCTION("""COMPUTED_VALUE"""),"Клубничный Мохито ") -> Клубничный Мохито | O133: =IFERROR(__xludf.DUMMYFUNCTION("""COMPUTED_VALUE"""),"Манго Грейпфрут ") -> Манго Грейпфрут | P133: =IFERROR(__xludf.DUMMYFUNCTION("""COMPUTED_VALUE"""),"Манго Персик Личи ") -> Манго Персик Личи | Q133: =IFERROR(__xludf.DUMMYFUNCTION("""COMPUTED_VALUE"""),"Персик Бабл Гам ") -> Персик Бабл Гам | R133: =IFERROR(__xludf.DUMMYFUNCTION("""COMPUTED_VALUE"""),"Садовые Ягоды ") -> Садовые Ягоды | S133: =IFERROR(__xludf.DUMMYFUNCTION("""COMPUTED_VALUE"""),"Скитлс Лимон Лайм 2") -> Скитлс Лимон Лайм 2 | T133: =IFERROR(__xludf.DUMMYFUNCTION("""COMPUTED_VALUE"""),"Смородина Мармелад 1") -> Смородина Мармелад 1 | U133: =IFERROR(__xludf.DUMMYFUNCTION("""COMPUTED_VALUE"""),"Темная Вишня 1") -> Темная Вишня 1 | V133: =IFERROR(__xludf.DUMMYFUNCTION("""COMPUTED_VALUE"""),"Фруктовые Пластинки 1") -> Фруктовые Пластинки 1 | W133: =IFERROR(__xludf.DUMMYFUNCTION("""COMPUTED_VALUE"""),"Черника Ежевика 1") -> Черника Ежевика 1 | X133: =IFERROR(__xludf.DUMMYFUNCTION("""COMPUTED_VALUE"""),"Черника Малина 1") -> Черника Малина 1 | Y133: =IFERROR(__xludf.DUMMYFUNCTION("""COMPUTED_VALUE"""),"Черника Мята 2") -> Черника Мята 2 | Z133: =IFERROR(__xludf.DUMMYFUNCTION("""COMPUTED_VALUE"""),"Яблоко Виноград 2") -> Яблоко Виноград 2 | AA133: =IFERROR(__xludf.DUMMYFUNCTION("""COMPUTED_VALUE"""),"Яблоко Малина 4") -> Яблоко Малина 4
A134: =IFERROR(__xludf.DUMMYFUNCTION("""COMPUTED_VALUE"""),"Кислый малиново-грейпфрутовый швепс") -> Кислый малиново-грейпфрутовый швепс | B134: =IFERROR(__xludf.DUMMYFUNCTION("""COMPUTED_VALUE"""),"Ананас апельсин") -> Ананас апельсин | C134: =IFERROR(__xludf.DUMMYFUNCTION("""COMPUTED_VALUE"""),"Пинаколада") -> Пинаколада | D134: =IFERROR(__xludf.DUMMYFUNCTION("""COMPUTED_VALUE"""),"Мятный бабл гам") -> Мятный бабл гам | E134: =IFERROR(__xludf.DUMMYFUNCTION("""COMPUTED_VALUE"""),"Мянго драгонфрут") -> Мянго драгонфрут | F134: =IFERROR(__xludf.DUMMYFUNCTION("""COMPUTED_VALUE"""),"Клубничная фанта") -> Клубничная фанта | G134: =IFERROR(__xludf.DUMMYFUNCTION("""COMPUTED_VALUE"""),"Клубничная арбуз") -> Клубничная арбуз | H134: =IFERROR(__xludf.DUMMYFUNCTION("""COMPUTED_VALUE"""),"Кислый скитлс") -> Кислый скитлс | I134: =IFERROR(__xludf.DUMMYFUNCTION("""COMPUTED_VALUE"""),"Кислый лайм арбуз") -> Кислый лайм арбуз | J134: =IFERROR(__xludf.DUMMYFUNCTION("""COMPUTED_VALUE"""),"Тропический банан") -> Тропический банан | K134: =IFERROR(__xludf.DUMMYFUNCTION("""COMPUTED_VALUE"""),"Яблочный энергетик") -> Яблочный энергетик | L134: =IFERROR(__xludf.DUMMYFUNCTION("""COMPUTED_VALUE"""),"Барбарисовый лимонад") -> Барбарисовый лимонад | M134: =IFERROR(__xludf.DUMMYFUNCTION("""COMPUTED_VALUE"""),"Лимонад виноград вишня") -> Лимонад виноград вишня | N134: =IFERROR(__xludf.DUMMYFUNCTION("""COMPUTED_VALUE"""),"Розовый лимонад") -> Розовый лимонад | O134: =IFERROR(__xludf.DUMMYFUNCTION("""COMPUTED_VALUE"""),"Двойной манго") -> Двойной манго | P134: =IFERROR(__xludf.DUMMYFUNCTION("""COMPUTED_VALUE"""),"Лесные ягоды ") -> Лесные ягоды | Q134: =IFERROR(__xludf.DUMMYFUNCTION("""COMPUTED_VALUE"""),"Ежевика малина ") -> Ежевика малина | R134: =IFERROR(__xludf.DUMMYFUNCTION("""COMPUTED_VALUE"""),"Смородиновый лимонад") -> Смородиновый лимонад | S134: =IFERROR(__xludf.DUMMYFUNCTION("""COMPUTED_VALUE"""),"Кола вишня") -> Кола вишня | T134: =IFERROR(__xludf.DUMMYFUNCTION("""COMPUTED_VALUE"""),"Манго арбуз") -> Манго арбуз | U134: =IFERROR(__xludf.DUMMYFUNCTION("""COMPUTED_VALUE"""),"Алоэ виноград") -> Алоэ виноград | V134: =IFERROR(__xludf.DUMMYFUNCTION("""COMPUTED_VALUE"""),"Банан клубника") -> Банан клубника | W134: =IFERROR(__xludf.DUMMYFUNCTION("""COMPUTED_VALUE"""),"Малиновый мармелад") -> Малиновый мармелад | X134: =IFERROR(__xludf.DUMMYFUNCTION("""COMPUTED_VALUE"""),"Клубника киви") -> Клубника киви | Y134: =IFERROR(__xludf.DUMMYFUNCTION("""COMPUTED_VALUE"""),"Клюква лайм") -> Клюква лайм | Z134: =IFERROR(__xludf.DUMMYFUNCTION("""COMPUTED_VALUE"""),"Гуава ананас") -> Гуава ананас | AA134: =IFERROR(__xludf.DUMMYFUNCTION("""COMPUTED_VALUE"""),"Морс") -> Морс | AB134: =IFERROR(__xludf.DUMMYFUNCTION("""COMPUTED_VALUE"""),"Красный апельсин") -> Красный апельсин | AC134: =IFERROR(__xludf.DUMMYFUNCTION("""COMPUTED_VALUE"""),"Арбузная жвачка") -> Арбузная жвачка | AD134: =IFERROR(__xludf.DUMMYFUNCTION("""COMPUTED_VALUE"""),"Смородина Виноград") -> Смородина Виноград | AE134: =IFERROR(__xludf.DUMMYFUNCTION("""COMPUTED_VALUE"""),"Гранатовая Мармелад") -> Гранатовая Мармелад | AF134: =IFERROR(__xludf.DUMMYFUNCTION("""COMPUTED_VALUE"""),"Яблоко Киви") -> Яблоко Киви | AG134: =IFERROR(__xludf.DUMMYFUNCTION("""COMPUTED_VALUE"""),"Клубника Ежевика") -> Клубника Ежевика | AH134: =IFERROR(__xludf.DUMMYFUNCTION("""COMPUTED_VALUE"""),"Клубничный Коктейль") -> Клубничный Коктейль | AI134: =IFERROR(__xludf.DUMMYFUNCTION("""COMPUTED_VALUE"""),"Клюква Земляника ") -> Клюква Земляника | AJ134: =IFERROR(__xludf.DUMMYFUNCTION("""COMPUTED_VALUE"""),"Какос Дыня") -> Какос Дыня | AK134: =IFERROR(__xludf.DUMMYFUNCTION("""COMPUTED_VALUE"""),"Маракуйя мандарин") -> Маракуйя мандарин | AL134: =IFERROR(__xludf.DUMMYFUNCTION("""COMPUTED_VALUE"""),"Персик кактус") -> Персик кактус | AM134: =IFERROR(__xludf.DUMMYFUNCTION("""COMPUTED_VALUE"""),"Спрайт") -> Спрайт | AN134: =IFERROR(__xludf.DUMMYFUNCTION("""COMPUTED_VALUE"""),"Черничная фанта") -> Черничная фанта | AO134: =IFERROR(__xludf.DUMMYFUNCTION("""COMPUTED_VALUE"""),"Ягодная жвачка") -> Ягодная жвачка | AP134: =IFERROR(__xludf.DUMMYFUNCTION("""COMPUTED_VALUE"""),"Ягодный энергетик") -> Ягодный энергетик | AQ134: =IFERROR(__xludf.DUMMYFUNCTION("""COMPUTED_VALUE"""),"Ягодный пунш ") -> Ягодный пунш | AR134: =IFERROR(__xludf.DUMMYFUNCTION("""COMPUTED_VALUE"""),"Виноградный холс") -> Виноградный холс | AS134: =IFERROR(__xludf.DUMMYFUNCTION("""COMPUTED_VALUE"""),"Грейпфрут смородина") -> Грейпфрут смородина | AT134: =IFERROR(__xludf.DUMMYFUNCTION("""COMPUTED_VALUE"""),"Дыня персик") -> Дыня персик | AU134: =IFERROR(__xludf.DUMMYFUNCTION("""COMPUTED_VALUE"""),"Земляника виноград") -> Земляника виноград | AV134: =IFERROR(__xludf.DUMMYFUNCTION("""COMPUTED_VALUE"""),"Киви маракуйя гуава") -> Киви маракуйя гуава | AW134: =IFERROR(__xludf.DUMMYFUNCTION("""COMPUTED_VALUE"""),"Кислые вишнёвые червячки") -> Кислые вишнёвые червячки | AX134: =IFERROR(__xludf.DUMMYFUNCTION("""COMPUTED_VALUE"""),"Кислые чернично-малиновое червячки") -> Кислые чернично-малиновое червячки
A135: =IFERROR(__xludf.DUMMYFUNCTION("""COMPUTED_VALUE"""),"0.4") -> 0.4 | B135: =IFERROR(__xludf.DUMMYFUNCTION("""COMPUTED_VALUE"""),"0.6") -> 0.6 | C135: =IFERROR(__xludf.DUMMYFUNCTION("""COMPUTED_VALUE"""),"0.7") -> 0.7 | D135: =IFERROR(__xludf.DUMMYFUNCTION("""COMPUTED_VALUE"""),"0.8") -> 0.8
A136: =IFERROR(__xludf.DUMMYFUNCTION("""COMPUTED_VALUE"""),"Арбуз Малина ") -> Арбуз Малина | B136: =IFERROR(__xludf.DUMMYFUNCTION("""COMPUTED_VALUE"""),"Банан Кокос ") -> Банан Кокос | C136: =IFERROR(__xludf.DUMMYFUNCTION("""COMPUTED_VALUE"""),"Барбарисовый Энергетик ") -> Барбарисовый Энергетик | D136: =IFERROR(__xludf.DUMMYFUNCTION("""COMPUTED_VALUE"""),"Виноградный Энергетик") -> Виноградный Энергетик | E136: =IFERROR(__xludf.DUMMYFUNCTION("""COMPUTED_VALUE"""),"Гранат Клубника ") -> Гранат Клубника | F136: =IFERROR(__xludf.DUMMYFUNCTION("""COMPUTED_VALUE"""),"Гранат Смородина ") -> Гранат Смородина | G136: =IFERROR(__xludf.DUMMYFUNCTION("""COMPUTED_VALUE"""),"Грейпфрутовый Швепс ") -> Грейпфрутовый Швепс | H136: =IFERROR(__xludf.DUMMYFUNCTION("""COMPUTED_VALUE"""),"Земляника Драгонфрут ") -> Земляника Драгонфрут | I136: =IFERROR(__xludf.DUMMYFUNCTION("""COMPUTED_VALUE"""),"Киви Личи ") -> Киви Личи | J136: =IFERROR(__xludf.DUMMYFUNCTION("""COMPUTED_VALUE"""),"Киви Маракуйя Гуава ") -> Киви Маракуйя Гуава | K136: =IFERROR(__xludf.DUMMYFUNCTION("""COMPUTED_VALUE"""),"Клубника Банан ") -> Клубника Банан | L136: =IFERROR(__xludf.DUMMYFUNCTION("""COMPUTED_VALUE"""),"Клубника Вишня ") -> Клубника Вишня | M136: =IFERROR(__xludf.DUMMYFUNCTION("""COMPUTED_VALUE"""),"Клубника Земляника ") -> Клубника Земляника | N136: =IFERROR(__xludf.DUMMYFUNCTION("""COMPUTED_VALUE"""),"Клубничный Мохито ") -> Клубничный Мохито | O136: =IFERROR(__xludf.DUMMYFUNCTION("""COMPUTED_VALUE"""),"Манго Грейпфрут ") -> Манго Грейпфрут | P136: =IFERROR(__xludf.DUMMYFUNCTION("""COMPUTED_VALUE"""),"Манго Персик Личи ") -> Манго Персик Личи | Q136: =IFERROR(__xludf.DUMMYFUNCTION("""COMPUTED_VALUE"""),"Персик Бабл Гам ") -> Персик Бабл Гам | R136: =IFERROR(__xludf.DUMMYFUNCTION("""COMPUTED_VALUE"""),"Садовые Ягоды ") -> Садовые Ягоды | S136: =IFERROR(__xludf.DUMMYFUNCTION("""COMPUTED_VALUE"""),"Скитлс Лимон Лайм 2") -> Скитлс Лимон Лайм 2 | T136: =IFERROR(__xludf.DUMMYFUNCTION("""COMPUTED_VALUE"""),"Смородина Мармелад 1") -> Смородина Мармелад 1 | U136: =IFERROR(__xludf.DUMMYFUNCTION("""COMPUTED_VALUE"""),"Темная Вишня 1") -> Темная Вишня 1 | V136: =IFERROR(__xludf.DUMMYFUNCTION("""COMPUTED_VALUE"""),"Фруктовые Пластинки 1") -> Фруктовые Пластинки 1 | W136: =IFERROR(__xludf.DUMMYFUNCTION("""COMPUTED_VALUE"""),"Черника Ежевика 1") -> Черника Ежевика 1 | X136: =IFERROR(__xludf.DUMMYFUNCTION("""COMPUTED_VALUE"""),"Черника Малина 1") -> Черника Малина 1 | Y136: =IFERROR(__xludf.DUMMYFUNCTION("""COMPUTED_VALUE"""),"Черника Мята 2") -> Черника Мята 2 | Z136: =IFERROR(__xludf.DUMMYFUNCTION("""COMPUTED_VALUE"""),"Яблоко Виноград 2") -> Яблоко Виноград 2 | AA136: =IFERROR(__xludf.DUMMYFUNCTION("""COMPUTED_VALUE"""),"Яблоко Малина 4") -> Яблоко Малина 4
A137: =IFERROR(__xludf.DUMMYFUNCTION("""COMPUTED_VALUE"""),"0.4") -> 0.4 | B137: =IFERROR(__xludf.DUMMYFUNCTION("""COMPUTED_VALUE"""),"0.6") -> 0.6 | C137: =IFERROR(__xludf.DUMMYFUNCTION("""COMPUTED_VALUE"""),"0.7") -> 0.7 | D137: =IFERROR(__xludf.DUMMYFUNCTION("""COMPUTED_VALUE"""),"0.8") -> 0.8
A138: =IFERROR(__xludf.DUMMYFUNCTION("""COMPUTED_VALUE"""),"0.4") -> 0.4 | B138: =IFERROR(__xludf.DUMMYFUNCTION("""COMPUTED_VALUE"""),"0.6") -> 0.6 | C138: =IFERROR(__xludf.DUMMYFUNCTION("""COMPUTED_VALUE"""),"0.7") -> 0.7 | D138: =IFERROR(__xludf.DUMMYFUNCTION("""COMPUTED_VALUE"""),"0.8") -> 0.8
A139: =IFERROR(__xludf.DUMMYFUNCTION("""COMPUTED_VALUE"""),"Арбуз Малина ") -> Арбуз Малина | B139: =IFERROR(__xludf.DUMMYFUNCTION("""COMPUTED_VALUE"""),"Банан Кокос ") -> Банан Кокос | C139: =IFERROR(__xludf.DUMMYFUNCTION("""COMPUTED_VALUE"""),"Барбарисовый Энергетик ") -> Барбарисовый Энергетик | D139: =IFERROR(__xludf.DUMMYFUNCTION("""COMPUTED_VALUE"""),"Виноградный Энергетик") -> Виноградный Энергетик | E139: =IFERROR(__xludf.DUMMYFUNCTION("""COMPUTED_VALUE"""),"Гранат Клубника ") -> Гранат Клубника | F139: =IFERROR(__xludf.DUMMYFUNCTION("""COMPUTED_VALUE"""),"Гранат Смородина ") -> Гранат Смородина | G139: =IFERROR(__xludf.DUMMYFUNCTION("""COMPUTED_VALUE"""),"Грейпфрутовый Швепс ") -> Грейпфрутовый Швепс | H139: =IFERROR(__xludf.DUMMYFUNCTION("""COMPUTED_VALUE"""),"Земляника Драгонфрут ") -> Земляника Драгонфрут | I139: =IFERROR(__xludf.DUMMYFUNCTION("""COMPUTED_VALUE"""),"Киви Личи ") -> Киви Личи | J139: =IFERROR(__xludf.DUMMYFUNCTION("""COMPUTED_VALUE"""),"Киви Маракуйя Гуава ") -> Киви Маракуйя Гуава | K139: =IFERROR(__xludf.DUMMYFUNCTION("""COMPUTED_VALUE"""),"Клубника Банан ") -> Клубника Банан | L139: =IFERROR(__xludf.DUMMYFUNCTION("""COMPUTED_VALUE"""),"Клубника Вишня ") -> Клубника Вишня | M139: =IFERROR(__xludf.DUMMYFUNCTION("""COMPUTED_VALUE"""),"Клубника Земляника ") -> Клубника Земляника | N139: =IFERROR(__xludf.DUMMYFUNCTION("""COMPUTED_VALUE"""),"Клубничный Мохито ") -> Клубничный Мохито | O139: =IFERROR(__xludf.DUMMYFUNCTION("""COMPUTED_VALUE"""),"Манго Грейпфрут ") -> Манго Грейпфрут | P139: =IFERROR(__xludf.DUMMYFUNCTION("""COMPUTED_VALUE"""),"Манго Персик Личи ") -> Манго Персик Личи | Q139: =IFERROR(__xludf.DUMMYFUNCTION("""COMPUTED_VALUE"""),"Персик Бабл Гам ") -> Персик Бабл Гам | R139: =IFERROR(__xludf.DUMMYFUNCTION("""COMPUTED_VALUE"""),"Садовые Ягоды ") -> Садовые Ягоды | S139: =IFERROR(__xludf.DUMMYFUNCTION("""COMPUTED_VALUE"""),"Скитлс Лимон Лайм 2") -> Скитлс Лимон Лайм 2 | T139: =IFERROR(__xludf.DUMMYFUNCTION("""COMPUTED_VALUE"""),"Смородина Мармелад 1") -> Смородина Мармелад 1 | U139: =IFERROR(__xludf.DUMMYFUNCTION("""COMPUTED_VALUE"""),"Темная Вишня 1") -> Темная Вишня 1 | V139: =IFERROR(__xludf.DUMMYFUNCTION("""COMPUTED_VALUE"""),"Фруктовые Пластинки 1") -> Фруктовые Пластинки 1 | W139: =IFERROR(__xludf.DUMMYFUNCTION("""COMPUTED_VALUE"""),"Черника Ежевика 1") -> Черника Ежевика 1 | X139: =IFERROR(__xludf.DUMMYFUNCTION("""COMPUTED_VALUE"""),"Черника Малина 1") -> Черника Малина 1 | Y139: =IFERROR(__xludf.DUMMYFUNCTION("""COMPUTED_VALUE"""),"Черника Мята 2") -> Черника Мята 2 | Z139: =IFERROR(__xludf.DUMMYFUNCTION("""COMPUTED_VALUE"""),"Яблоко Виноград 2") -> Яблоко Виноград 2 | AA139: =IFERROR(__xludf.DUMMYFUNCTION("""COMPUTED_VALUE"""),"Яблоко Малина 4") -> Яблоко Малина 4
A140: =IFERROR(__xludf.DUMMYFUNCTION("""COMPUTED_VALUE"""),"Лесные ягоды") -> Лесные ягоды | B140: =IFERROR(__xludf.DUMMYFUNCTION("""COMPUTED_VALUE"""),"Алоэ виноград ") -> Алоэ виноград | C140: =IFERROR(__xludf.DUMMYFUNCTION("""COMPUTED_VALUE"""),"Апельсиновый адреналин") -> Апельсиновый адреналин | D140: =IFERROR(__xludf.DUMMYFUNCTION("""COMPUTED_VALUE"""),"Клюква лайм") -> Клюква лайм | E140: =IFERROR(__xludf.DUMMYFUNCTION("""COMPUTED_VALUE"""),"Виноградная фанта ") -> Виноградная фанта | F140: =IFERROR(__xludf.DUMMYFUNCTION("""COMPUTED_VALUE"""),"Зеленый чай лемонграсс") -> Зеленый чай лемонграсс | G140: =IFERROR(__xludf.DUMMYFUNCTION("""COMPUTED_VALUE"""),"Малина арбуз") -> Малина арбуз | H140: =IFERROR(__xludf.DUMMYFUNCTION("""COMPUTED_VALUE"""),"Ананас персик") -> Ананас персик | I140: =IFERROR(__xludf.DUMMYFUNCTION("""COMPUTED_VALUE"""),"Клубничный мохито ") -> Клубничный мохито | J140: =IFERROR(__xludf.DUMMYFUNCTION("""COMPUTED_VALUE"""),"Яблоко лайм") -> Яблоко лайм | K140: =IFERROR(__xludf.DUMMYFUNCTION("""COMPUTED_VALUE"""),"Спрайт арбуз лайм ") -> Спрайт арбуз лайм | L140: =IFERROR(__xludf.DUMMYFUNCTION("""COMPUTED_VALUE"""),"Черничная фанта") -> Черничная фанта | M140: =IFERROR(__xludf.DUMMYFUNCTION("""COMPUTED_VALUE"""),"Чёрная смородина") -> Чёрная смородина | N140: =IFERROR(__xludf.DUMMYFUNCTION("""COMPUTED_VALUE"""),"Червячки голубика малина") -> Червячки голубика малина | O140: =IFERROR(__xludf.DUMMYFUNCTION("""COMPUTED_VALUE"""),"Малина смородина ") -> Малина смородина | P140: =IFERROR(__xludf.DUMMYFUNCTION("""COMPUTED_VALUE"""),"Черника лайм ") -> Черника лайм | Q140: =IFERROR(__xludf.DUMMYFUNCTION("""COMPUTED_VALUE"""),"Виноградный чупа чупс") -> Виноградный чупа чупс | R140: =IFERROR(__xludf.DUMMYFUNCTION("""COMPUTED_VALUE"""),"Киви лайм") -> Киви лайм | S140: =IFERROR(__xludf.DUMMYFUNCTION("""COMPUTED_VALUE"""),"Ягодный морс") -> Ягодный морс | T140: =IFERROR(__xludf.DUMMYFUNCTION("""COMPUTED_VALUE"""),"Фруктовый скитлс") -> Фруктовый скитлс | U140: =IFERROR(__xludf.DUMMYFUNCTION("""COMPUTED_VALUE"""),"черника лимон ") -> черника лимон | V140: =IFERROR(__xludf.DUMMYFUNCTION("""COMPUTED_VALUE"""),"Вишнёвая бомба") -> Вишнёвая бомба | W140: =IFERROR(__xludf.DUMMYFUNCTION("""COMPUTED_VALUE"""),"Тропический манго") -> Тропический манго
A141: =IFERROR(__xludf.DUMMYFUNCTION("""COMPUTED_VALUE"""),"Смородина холс") -> Смородина холс | B141: =IFERROR(__xludf.DUMMYFUNCTION("""COMPUTED_VALUE"""),"Тропические фрукты") -> Тропические фрукты | C141: =IFERROR(__xludf.DUMMYFUNCTION("""COMPUTED_VALUE"""),"Черничная конфета") -> Черничная конфета | D141: =IFERROR(__xludf.DUMMYFUNCTION("""COMPUTED_VALUE"""),"Яблоко вишня") -> Яблоко вишня | E141: =IFERROR(__xludf.DUMMYFUNCTION("""COMPUTED_VALUE"""),"Виноград мята") -> Виноград мята | F141: =IFERROR(__xludf.DUMMYFUNCTION("""COMPUTED_VALUE"""),"Виноград холс") -> Виноград холс | G141: =IFERROR(__xludf.DUMMYFUNCTION("""COMPUTED_VALUE"""),"Грейпфрутовый лимонад") -> Грейпфрутовый лимонад | H141: =IFERROR(__xludf.DUMMYFUNCTION("""COMPUTED_VALUE"""),"Дыня банан") -> Дыня банан | I141: =IFERROR(__xludf.DUMMYFUNCTION("""COMPUTED_VALUE"""),"Ежевичный лимонад") -> Ежевичный лимонад | J141: =IFERROR(__xludf.DUMMYFUNCTION("""COMPUTED_VALUE"""),"Земляничная конфета ") -> Земляничная конфета | K141: =IFERROR(__xludf.DUMMYFUNCTION("""COMPUTED_VALUE"""),"Ананас манго ") -> Ананас манго | L141: =IFERROR(__xludf.DUMMYFUNCTION("""COMPUTED_VALUE"""),"Жвачка черника мята ") -> Жвачка черника мята | M141: =IFERROR(__xludf.DUMMYFUNCTION("""COMPUTED_VALUE"""),"Зеленый манго") -> Зеленый манго | N141: =IFERROR(__xludf.DUMMYFUNCTION("""COMPUTED_VALUE"""),"Клюква брусника") -> Клюква брусника | O141: =IFERROR(__xludf.DUMMYFUNCTION("""COMPUTED_VALUE"""),"Апельсин ") -> Апельсин | P141: =IFERROR(__xludf.DUMMYFUNCTION("""COMPUTED_VALUE"""),"Кокос малина") -> Кокос малина | Q141: =IFERROR(__xludf.DUMMYFUNCTION("""COMPUTED_VALUE"""),"Лимонные черви") -> Лимонные черви | R141: =IFERROR(__xludf.DUMMYFUNCTION("""COMPUTED_VALUE"""),"Малиновый лимонад") -> Малиновый лимонад | S141: =IFERROR(__xludf.DUMMYFUNCTION("""COMPUTED_VALUE"""),"Смородина малина") -> Смородина малина
A142: =IFERROR(__xludf.DUMMYFUNCTION("""COMPUTED_VALUE"""),"0.3") -> 0.3
A143: =IFERROR(__xludf.DUMMYFUNCTION("""COMPUTED_VALUE"""),"кислая земляника") -> кислая земляника | B143: =IFERROR(__xludf.DUMMYFUNCTION("""COMPUTED_VALUE"""),"кислая фанта с черникой") -> кислая фанта с черникой | C143: =IFERROR(__xludf.DUMMYFUNCTION("""COMPUTED_VALUE"""),"кислое харибо с колой и черешней") -> кислое харибо с колой и черешней | D143: =IFERROR(__xludf.DUMMYFUNCTION("""COMPUTED_VALUE"""),"кислое яблочно клубничная шипучка") -> кислое яблочно клубничная шипучка | E143: =IFERROR(__xludf.DUMMYFUNCTION("""COMPUTED_VALUE"""),"кислые желатинки маракуйя ананас") -> кислые желатинки маракуйя ананас | F143: =IFERROR(__xludf.DUMMYFUNCTION("""COMPUTED_VALUE"""),"кислые ленточки маракуя манго") -> кислые ленточки маракуя манго | G143: =IFERROR(__xludf.DUMMYFUNCTION("""COMPUTED_VALUE"""),"кислые мармеладные ягоды") -> кислые мармеладные ягоды | H143: =IFERROR(__xludf.DUMMYFUNCTION("""COMPUTED_VALUE"""),"кислый виноград лайм") -> кислый виноград лайм | I143: =IFERROR(__xludf.DUMMYFUNCTION("""COMPUTED_VALUE"""),"кислый грейпфрут с вишней") -> кислый грейпфрут с вишней | J143: =IFERROR(__xludf.DUMMYFUNCTION("""COMPUTED_VALUE"""),"кислый леденец виноград киви яблоко") -> кислый леденец виноград киви яблоко | K143: =IFERROR(__xludf.DUMMYFUNCTION("""COMPUTED_VALUE"""),"кислый лимонад арбуз лайм малина") -> кислый лимонад арбуз лайм малина | L143: =IFERROR(__xludf.DUMMYFUNCTION("""COMPUTED_VALUE"""),"кислый персик клубника") -> кислый персик клубника | M143: =IFERROR(__xludf.DUMMYFUNCTION("""COMPUTED_VALUE"""),"кислый яблочно лимонные колечки") -> кислый яблочно лимонные колечки | N143: =IFERROR(__xludf.DUMMYFUNCTION("""COMPUTED_VALUE"""),"фанта апельсин с кислой малиной") -> фанта апельсин с кислой малиной
A144: =IFERROR(__xludf.DUMMYFUNCTION("""COMPUTED_VALUE"""),"0.4") -> 0.4 | B144: =IFERROR(__xludf.DUMMYFUNCTION("""COMPUTED_VALUE"""),"0.6") -> 0.6 | C144: =IFERROR(__xludf.DUMMYFUNCTION("""COMPUTED_VALUE"""),"0.7") -> 0.7 | D144: =IFERROR(__xludf.DUMMYFUNCTION("""COMPUTED_VALUE"""),"0.8") -> 0.8
A145: =IFERROR(__xludf.DUMMYFUNCTION("""COMPUTED_VALUE"""),"Кислый малиново-грейпфрутовый швепс") -> Кислый малиново-грейпфрутовый швепс | B145: =IFERROR(__xludf.DUMMYFUNCTION("""COMPUTED_VALUE"""),"Ананас апельсин") -> Ананас апельсин | C145: =IFERROR(__xludf.DUMMYFUNCTION("""COMPUTED_VALUE"""),"Пинаколада") -> Пинаколада | D145: =IFERROR(__xludf.DUMMYFUNCTION("""COMPUTED_VALUE"""),"Мятный бабл гам") -> Мятный бабл гам | E145: =IFERROR(__xludf.DUMMYFUNCTION("""COMPUTED_VALUE"""),"Мянго драгонфрут") -> Мянго драгонфрут | F145: =IFERROR(__xludf.DUMMYFUNCTION("""COMPUTED_VALUE"""),"Клубничная фанта") -> Клубничная фанта | G145: =IFERROR(__xludf.DUMMYFUNCTION("""COMPUTED_VALUE"""),"Клубничная арбуз") -> Клубничная арбуз | H145: =IFERROR(__xludf.DUMMYFUNCTION("""COMPUTED_VALUE"""),"Кислый скитлс") -> Кислый скитлс | I145: =IFERROR(__xludf.DUMMYFUNCTION("""COMPUTED_VALUE"""),"Кислый лайм арбуз") -> Кислый лайм арбуз | J145: =IFERROR(__xludf.DUMMYFUNCTION("""COMPUTED_VALUE"""),"Тропический банан") -> Тропический банан | K145: =IFERROR(__xludf.DUMMYFUNCTION("""COMPUTED_VALUE"""),"Яблочный энергетик") -> Яблочный энергетик | L145: =IFERROR(__xludf.DUMMYFUNCTION("""COMPUTED_VALUE"""),"Барбарисовый лимонад") -> Барбарисовый лимонад | M145: =IFERROR(__xludf.DUMMYFUNCTION("""COMPUTED_VALUE"""),"Лимонад виноград вишня") -> Лимонад виноград вишня | N145: =IFERROR(__xludf.DUMMYFUNCTION("""COMPUTED_VALUE"""),"Розовый лимонад") -> Розовый лимонад | O145: =IFERROR(__xludf.DUMMYFUNCTION("""COMPUTED_VALUE"""),"Двойной манго") -> Двойной манго | P145: =IFERROR(__xludf.DUMMYFUNCTION("""COMPUTED_VALUE"""),"Лесные ягоды ") -> Лесные ягоды | Q145: =IFERROR(__xludf.DUMMYFUNCTION("""COMPUTED_VALUE"""),"Ежевика малина ") -> Ежевика малина | R145: =IFERROR(__xludf.DUMMYFUNCTION("""COMPUTED_VALUE"""),"Смородиновый лимонад") -> Смородиновый лимонад | S145: =IFERROR(__xludf.DUMMYFUNCTION("""COMPUTED_VALUE"""),"Кола вишня") -> Кола вишня | T145: =IFERROR(__xludf.DUMMYFUNCTION("""COMPUTED_VALUE"""),"Манго арбуз") -> Манго арбуз | U145: =IFERROR(__xludf.DUMMYFUNCTION("""COMPUTED_VALUE"""),"Алоэ виноград") -> Алоэ виноград | V145: =IFERROR(__xludf.DUMMYFUNCTION("""COMPUTED_VALUE"""),"Банан клубника") -> Банан клубника | W145: =IFERROR(__xludf.DUMMYFUNCTION("""COMPUTED_VALUE"""),"Малиновый мармелад") -> Малиновый мармелад | X145: =IFERROR(__xludf.DUMMYFUNCTION("""COMPUTED_VALUE"""),"Клубника киви") -> Клубника киви | Y145: =IFERROR(__xludf.DUMMYFUNCTION("""COMPUTED_VALUE"""),"Клюква лайм") -> Клюква лайм | Z145: =IFERROR(__xludf.DUMMYFUNCTION("""COMPUTED_VALUE"""),"Гуава ананас") -> Гуава ананас | AA145: =IFERROR(__xludf.DUMMYFUNCTION("""COMPUTED_VALUE"""),"Морс") -> Морс | AB145: =IFERROR(__xludf.DUMMYFUNCTION("""COMPUTED_VALUE"""),"Красный апельсин") -> Красный апельсин | AC145: =IFERROR(__xludf.DUMMYFUNCTION("""COMPUTED_VALUE"""),"Арбузная жвачка") -> Арбузная жвачка | AD145: =IFERROR(__xludf.DUMMYFUNCTION("""COMPUTED_VALUE"""),"Смородина Виноград") -> Смородина Виноград | AE145: =IFERROR(__xludf.DUMMYFUNCTION("""COMPUTED_VALUE"""),"Гранатовая Мармелад") -> Гранатовая Мармелад | AF145: =IFERROR(__xludf.DUMMYFUNCTION("""COMPUTED_VALUE"""),"Яблоко Киви") -> Яблоко Киви | AG145: =IFERROR(__xludf.DUMMYFUNCTION("""COMPUTED_VALUE"""),"Клубника Ежевика") -> Клубника Ежевика | AH145: =IFERROR(__xludf.DUMMYFUNCTION("""COMPUTED_VALUE"""),"Клубничный Коктейль") -> Клубничный Коктейль | AI145: =IFERROR(__xludf.DUMMYFUNCTION("""COMPUTED_VALUE"""),"Клюква Земляника ") -> Клюква Земляника | AJ145: =IFERROR(__xludf.DUMMYFUNCTION("""COMPUTED_VALUE"""),"Какос Дыня") -> Какос Дыня | AK145: =IFERROR(__xludf.DUMMYFUNCTION("""COMPUTED_VALUE"""),"Маракуйя мандарин") -> Маракуйя мандарин | AL145: =IFERROR(__xludf.DUMMYFUNCTION("""COMPUTED_VALUE"""),"Персик кактус") -> Персик кактус | AM145: =IFERROR(__xludf.DUMMYFUNCTION("""COMPUTED_VALUE"""),"Спрайт") -> Спрайт | AN145: =IFERROR(__xludf.DUMMYFUNCTION("""COMPUTED_VALUE"""),"Черничная фанта") -> Черничная фанта | AO145: =IFERROR(__xludf.DUMMYFUNCTION("""COMPUTED_VALUE"""),"Ягодная жвачка") -> Ягодная жвачка | AP145: =IFERROR(__xludf.DUMMYFUNCTION("""COMPUTED_VALUE"""),"Ягодный энергетик") -> Ягодный энергетик | AQ145: =IFERROR(__xludf.DUMMYFUNCTION("""COMPUTED_VALUE"""),"Ягодный пунш ") -> Ягодный пунш | AR145: =IFERROR(__xludf.DUMMYFUNCTION("""COMPUTED_VALUE"""),"Виноградный холс") -> Виноградный холс | AS145: =IFERROR(__xludf.DUMMYFUNCTION("""COMPUTED_VALUE"""),"Грейпфрут смородина") -> Грейпфрут смородина | AT145: =IFERROR(__xludf.DUMMYFUNCTION("""COMPUTED_VALUE"""),"Дыня персик") -> Дыня персик | AU145: =IFERROR(__xludf.DUMMYFUNCTION("""COMPUTED_VALUE"""),"Земляника виноград") -> Земляника виноград | AV145: =IFERROR(__xludf.DUMMYFUNCTION("""COMPUTED_VALUE"""),"Киви маракуйя гуава") -> Киви маракуйя гуава | AW145: =IFERROR(__xludf.DUMMYFUNCTION("""COMPUTED_VALUE"""),"Кислые вишнёвые червячки") -> Кислые вишнёвые червячки | AX145: =IFERROR(__xludf.DUMMYFUNCTION("""COMPUTED_VALUE"""),"Кислые чернично-малиновое червячки") -> Кислые чернично-малиновое червячки
A146: =IFERROR(__xludf.DUMMYFUNCTION("""COMPUTED_VALUE"""),"Арбуз Малина ") -> Арбуз Малина | B146: =IFERROR(__xludf.DUMMYFUNCTION("""COMPUTED_VALUE"""),"Банан Кокос ") -> Банан Кокос | C146: =IFERROR(__xludf.DUMMYFUNCTION("""COMPUTED_VALUE"""),"Барбарисовый Энергетик ") -> Барбарисовый Энергетик | D146: =IFERROR(__xludf.DUMMYFUNCTION("""COMPUTED_VALUE"""),"Виноградный Энергетик") -> Виноградный Энергетик | E146: =IFERROR(__xludf.DUMMYFUNCTION("""COMPUTED_VALUE"""),"Гранат Клубника ") -> Гранат Клубника | F146: =IFERROR(__xludf.DUMMYFUNCTION("""COMPUTED_VALUE"""),"Гранат Смородина ") -> Гранат Смородина | G146: =IFERROR(__xludf.DUMMYFUNCTION("""COMPUTED_VALUE"""),"Грейпфрутовый Швепс ") -> Грейпфрутовый Швепс | H146: =IFERROR(__xludf.DUMMYFUNCTION("""COMPUTED_VALUE"""),"Земляника Драгонфрут ") -> Земляника Драгонфрут | I146: =IFERROR(__xludf.DUMMYFUNCTION("""COMPUTED_VALUE"""),"Киви Личи ") -> Киви Личи | J146: =IFERROR(__xludf.DUMMYFUNCTION("""COMPUTED_VALUE"""),"Киви Маракуйя Гуава ") -> Киви Маракуйя Гуава | K146: =IFERROR(__xludf.DUMMYFUNCTION("""COMPUTED_VALUE"""),"Клубника Банан ") -> Клубника Банан | L146: =IFERROR(__xludf.DUMMYFUNCTION("""COMPUTED_VALUE"""),"Клубника Вишня ") -> Клубника Вишня | M146: =IFERROR(__xludf.DUMMYFUNCTION("""COMPUTED_VALUE"""),"Клубника Земляника ") -> Клубника Земляника | N146: =IFERROR(__xludf.DUMMYFUNCTION("""COMPUTED_VALUE"""),"Клубничный Мохито ") -> Клубничный Мохито | O146: =IFERROR(__xludf.DUMMYFUNCTION("""COMPUTED_VALUE"""),"Манго Грейпфрут ") -> Манго Грейпфрут | P146: =IFERROR(__xludf.DUMMYFUNCTION("""COMPUTED_VALUE"""),"Манго Персик Личи ") -> Манго Персик Личи | Q146: =IFERROR(__xludf.DUMMYFUNCTION("""COMPUTED_VALUE"""),"Персик Бабл Гам ") -> Персик Бабл Гам | R146: =IFERROR(__xludf.DUMMYFUNCTION("""COMPUTED_VALUE"""),"Садовые Ягоды ") -> Садовые Ягоды | S146: =IFERROR(__xludf.DUMMYFUNCTION("""COMPUTED_VALUE"""),"Скитлс Лимон Лайм 2") -> Скитлс Лимон Лайм 2 | T146: =IFERROR(__xludf.DUMMYFUNCTION("""COMPUTED_VALUE"""),"Смородина Мармелад 1") -> Смородина Мармелад 1 | U146: =IFERROR(__xludf.DUMMYFUNCTION("""COMPUTED_VALUE"""),"Темная Вишня 1") -> Темная Вишня 1 | V146: =IFERROR(__xludf.DUMMYFUNCTION("""COMPUTED_VALUE"""),"Фруктовые Пластинки 1") -> Фруктовые Пластинки 1 | W146: =IFERROR(__xludf.DUMMYFUNCTION("""COMPUTED_VALUE"""),"Черника Ежевика 1") -> Черника Ежевика 1 | X146: =IFERROR(__xludf.DUMMYFUNCTION("""COMPUTED_VALUE"""),"Черника Малина 1") -> Черника Малина 1 | Y146: =IFERROR(__xludf.DUMMYFUNCTION("""COMPUTED_VALUE"""),"Черника Мята 2") -> Черника Мята 2 | Z146: =IFERROR(__xludf.DUMMYFUNCTION("""COMPUTED_VALUE"""),"Яблоко Виноград 2") -> Яблоко Виноград 2 | AA146: =IFERROR(__xludf.DUMMYFUNCTION("""COMPUTED_VALUE"""),"Яблоко Малина 4") -> Яблоко Малина 4
A147: =IFERROR(__xludf.DUMMYFUNCTION("""COMPUTED_VALUE"""),"0.4") -> 0.4 | B147: =IFERROR(__xludf.DUMMYFUNCTION("""COMPUTED_VALUE"""),"0.6") -> 0.6 | C147: =IFERROR(__xludf.DUMMYFUNCTION("""COMPUTED_VALUE"""),"0.7") -> 0.7 | D147: =IFERROR(__xludf.DUMMYFUNCTION("""COMPUTED_VALUE"""),"0.8") -> 0.8
A148: =IFERROR(__xludf.DUMMYFUNCTION("""COMPUTED_VALUE"""),"0.4") -> 0.4 | B148: =IFERROR(__xludf.DUMMYFUNCTION("""COMPUTED_VALUE"""),"0.6") -> 0.6 | C148: =IFERROR(__xludf.DUMMYFUNCTION("""COMPUTED_VALUE"""),"0.7") -> 0.7 | D148: =IFERROR(__xludf.DUMMYFUNCTION("""COMPUTED_VALUE"""),"0.8") -> 0.8
A149: =IFERROR(__xludf.DUMMYFUNCTION("""COMPUTED_VALUE"""),"Ананас киви") -> Ананас киви | B149: =IFERROR(__xludf.DUMMYFUNCTION("""COMPUTED_VALUE"""),"Арбузный смузи") -> Арбузный смузи | C149: =IFERROR(__xludf.DUMMYFUNCTION("""COMPUTED_VALUE"""),"Виноградная фанта") -> Виноградная фанта | D149: =IFERROR(__xludf.DUMMYFUNCTION("""COMPUTED_VALUE"""),"Вишневый морс") -> Вишневый морс | E149: =IFERROR(__xludf.DUMMYFUNCTION("""COMPUTED_VALUE"""),"Гранатовый мармелад") -> Гранатовый мармелад | F149: =IFERROR(__xludf.DUMMYFUNCTION("""COMPUTED_VALUE"""),"Грейпфрут киви") -> Грейпфрут киви | G149: =IFERROR(__xludf.DUMMYFUNCTION("""COMPUTED_VALUE"""),"Ежевика мята") -> Ежевика мята | H149: =IFERROR(__xludf.DUMMYFUNCTION("""COMPUTED_VALUE"""),"Киви манго") -> Киви манго | I149: =IFERROR(__xludf.DUMMYFUNCTION("""COMPUTED_VALUE"""),"Клубника манго") -> Клубника манго | J149: =IFERROR(__xludf.DUMMYFUNCTION("""COMPUTED_VALUE"""),"черника грейфрут ") -> черника грейфрут | K149: =IFERROR(__xludf.DUMMYFUNCTION("""COMPUTED_VALUE"""),"Малина лайм") -> Малина лайм | L149: =IFERROR(__xludf.DUMMYFUNCTION("""COMPUTED_VALUE"""),"Манго арбуз ") -> Манго арбуз | M149: =IFERROR(__xludf.DUMMYFUNCTION("""COMPUTED_VALUE"""),"Малиновый чай с жасмином") -> Малиновый чай с жасмином | N149: =IFERROR(__xludf.DUMMYFUNCTION("""COMPUTED_VALUE"""),"малина апельсин ") -> малина апельсин | O149: =IFERROR(__xludf.DUMMYFUNCTION("""COMPUTED_VALUE"""),"Манго апельсин") -> Манго апельсин | P149: =IFERROR(__xludf.DUMMYFUNCTION("""COMPUTED_VALUE"""),"Ред булл") -> Ред булл | Q149: =IFERROR(__xludf.DUMMYFUNCTION("""COMPUTED_VALUE"""),"Спрайт") -> Спрайт | R149: =IFERROR(__xludf.DUMMYFUNCTION("""COMPUTED_VALUE"""),"ананас клюква ") -> ананас клюква | S149: =IFERROR(__xludf.DUMMYFUNCTION("""COMPUTED_VALUE"""),"Тархун") -> Тархун | T149: =IFERROR(__xludf.DUMMYFUNCTION("""COMPUTED_VALUE"""),"алоэ Виноград ") -> алоэ Виноград | U149: =IFERROR(__xludf.DUMMYFUNCTION("""COMPUTED_VALUE"""),"Фруктовая жвачка") -> Фруктовая жвачка | V149: =IFERROR(__xludf.DUMMYFUNCTION("""COMPUTED_VALUE"""),"Холодная кола") -> Холодная кола | W149: =IFERROR(__xludf.DUMMYFUNCTION("""COMPUTED_VALUE"""),"Черная смородина клюква") -> Черная смородина клюква | X149: =IFERROR(__xludf.DUMMYFUNCTION("""COMPUTED_VALUE"""),"Черника арбуз") -> Черника арбуз | Y149: =IFERROR(__xludf.DUMMYFUNCTION("""COMPUTED_VALUE"""),"Яблоко черника") -> Яблоко черника
A193: =IFERROR(__xludf.DUMMYFUNCTION("""COMPUTED_VALUE"""),"Арбуз Малина ") -> Арбуз Малина | B193: =IFERROR(__xludf.DUMMYFUNCTION("""COMPUTED_VALUE"""),"Банан Кокос ") -> Банан Кокос | C193: =IFERROR(__xludf.DUMMYFUNCTION("""COMPUTED_VALUE"""),"Барбарисовый Энергетик ") -> Барбарисовый Энергетик | D193: =IFERROR(__xludf.DUMMYFUNCTION("""COMPUTED_VALUE"""),"Виноградный Энергетик") -> Виноградный Энергетик | E193: =IFERROR(__xludf.DUMMYFUNCTION("""COMPUTED_VALUE"""),"Гранат Клубника ") -> Гранат Клубника | F193: =IFERROR(__xludf.DUMMYFUNCTION("""COMPUTED_VALUE"""),"Гранат Смородина ") -> Гранат Смородина | G193: =IFERROR(__xludf.DUMMYFUNCTION("""COMPUTED_VALUE"""),"Грейпфрутовый Швепс ") -> Грейпфрутовый Швепс | H193: =IFERROR(__xludf.DUMMYFUNCTION("""COMPUTED_VALUE"""),"Земляника Драгонфрут ") -> Земляника Драгонфрут | I193: =IFERROR(__xludf.DUMMYFUNCTION("""COMPUTED_VALUE"""),"Киви Личи ") -> Киви Личи | J193: =IFERROR(__xludf.DUMMYFUNCTION("""COMPUTED_VALUE"""),"Киви Маракуйя Гуава ") -> Киви Маракуйя Гуава | K193: =IFERROR(__xludf.DUMMYFUNCTION("""COMPUTED_VALUE"""),"Клубника Банан ") -> Клубника Банан | L193: =IFERROR(__xludf.DUMMYFUNCTION("""COMPUTED_VALUE"""),"Клубника Вишня ") -> Клубника Вишня | M193: =IFERROR(__xludf.DUMMYFUNCTION("""COMPUTED_VALUE"""),"Клубника Земляника ") -> Клубника Земляника | N193: =IFERROR(__xludf.DUMMYFUNCTION("""COMPUTED_VALUE"""),"Клубничный Мохито ") -> Клубничный Мохито | O193: =IFERROR(__xludf.DUMMYFUNCTION("""COMPUTED_VALUE"""),"Манго Грейпфрут ") -> Манго Грейпфрут | P193: =IFERROR(__xludf.DUMMYFUNCTION("""COMPUTED_VALUE"""),"Манго Персик Личи ") -> Манго Персик Личи | Q193: =IFERROR(__xludf.DUMMYFUNCTION("""COMPUTED_VALUE"""),"Персик Бабл Гам ") -> Персик Бабл Гам | R193: =IFERROR(__xludf.DUMMYFUNCTION("""COMPUTED_VALUE"""),"Садовые Ягоды ") -> Садовые Ягоды | S193: =IFERROR(__xludf.DUMMYFUNCTION("""COMPUTED_VALUE"""),"Скитлс Лимон Лайм 2") -> Скитлс Лимон Лайм 2 | T193: =IFERROR(__xludf.DUMMYFUNCTION("""COMPUTED_VALUE"""),"Смородина Мармелад 1") -> Смородина Мармелад 1 | U193: =IFERROR(__xludf.DUMMYFUNCTION("""COMPUTED_VALUE"""),"Темная Вишня 1") -> Темная Вишня 1 | V193: =IFERROR(__xludf.DUMMYFUNCTION("""COMPUTED_VALUE"""),"Фруктовые Пластинки 1") -> Фруктовые Пластинки 1 | W193: =IFERROR(__xludf.DUMMYFUNCTION("""COMPUTED_VALUE"""),"Черника Ежевика 1") -> Черника Ежевика 1 | X193: =IFERROR(__xludf.DUMMYFUNCTION("""COMPUTED_VALUE"""),"Черника Малина 1") -> Черника Малина 1 | Y193: =IFERROR(__xludf.DUMMYFUNCTION("""COMPUTED_VALUE"""),"Черника Мята 2") -> Черника Мята 2 | Z193: =IFERROR(__xludf.DUMMYFUNCTION("""COMPUTED_VALUE"""),"Яблоко Виноград 2") -> Яблоко Виноград 2 | AA193: =IFERROR(__xludf.DUMMYFUNCTION("""COMPUTED_VALUE"""),"Яблоко Малина 4") -> Яблоко Малина 4
A194: =IFERROR(__xludf.DUMMYFUNCTION("""COMPUTED_VALUE"""),"Лесные ягоды") -> Лесные ягоды | B194: =IFERROR(__xludf.DUMMYFUNCTION("""COMPUTED_VALUE"""),"Алоэ виноград ") -> Алоэ виноград | C194: =IFERROR(__xludf.DUMMYFUNCTION("""COMPUTED_VALUE"""),"Апельсиновый адреналин") -> Апельсиновый адреналин | D194: =IFERROR(__xludf.DUMMYFUNCTION("""COMPUTED_VALUE"""),"Клюква лайм") -> Клюква лайм | E194: =IFERROR(__xludf.DUMMYFUNCTION("""COMPUTED_VALUE"""),"Виноградная фанта ") -> Виноградная фанта | F194: =IFERROR(__xludf.DUMMYFUNCTION("""COMPUTED_VALUE"""),"Зеленый чай лемонграсс") -> Зеленый чай лемонграсс | G194: =IFERROR(__xludf.DUMMYFUNCTION("""COMPUTED_VALUE"""),"Малина арбуз") -> Малина арбуз | H194: =IFERROR(__xludf.DUMMYFUNCTION("""COMPUTED_VALUE"""),"Ананас персик") -> Ананас персик | I194: =IFERROR(__xludf.DUMMYFUNCTION("""COMPUTED_VALUE"""),"Клубничный мохито ") -> Клубничный мохито | J194: =IFERROR(__xludf.DUMMYFUNCTION("""COMPUTED_VALUE"""),"Яблоко лайм") -> Яблоко лайм | K194: =IFERROR(__xludf.DUMMYFUNCTION("""COMPUTED_VALUE"""),"Спрайт арбуз лайм ") -> Спрайт арбуз лайм | L194: =IFERROR(__xludf.DUMMYFUNCTION("""COMPUTED_VALUE"""),"Черничная фанта") -> Черничная фанта | M194: =IFERROR(__xludf.DUMMYFUNCTION("""COMPUTED_VALUE"""),"Чёрная смородина") -> Чёрная смородина | N194: =IFERROR(__xludf.DUMMYFUNCTION("""COMPUTED_VALUE"""),"Червячки голубика малина") -> Червячки голубика малина | O194: =IFERROR(__xludf.DUMMYFUNCTION("""COMPUTED_VALUE"""),"Малина смородина ") -> Малина смородина | P194: =IFERROR(__xludf.DUMMYFUNCTION("""COMPUTED_VALUE"""),"Черника лайм ") -> Черника лайм | Q194: =IFERROR(__xludf.DUMMYFUNCTION("""COMPUTED_VALUE"""),"Виноградный чупа чупс") -> Виноградный чупа чупс | R194: =IFERROR(__xludf.DUMMYFUNCTION("""COMPUTED_VALUE"""),"Киви лайм") -> Киви лайм | S194: =IFERROR(__xludf.DUMMYFUNCTION("""COMPUTED_VALUE"""),"Ягодный морс") -> Ягодный морс | T194: =IFERROR(__xludf.DUMMYFUNCTION("""COMPUTED_VALUE"""),"Фруктовый скитлс") -> Фруктовый скитлс | U194: =IFERROR(__xludf.DUMMYFUNCTION("""COMPUTED_VALUE"""),"черника лимон ") -> черника лимон | V194: =IFERROR(__xludf.DUMMYFUNCTION("""COMPUTED_VALUE"""),"Вишнёвая бомба") -> Вишнёвая бомба | W194: =IFERROR(__xludf.DUMMYFUNCTION("""COMPUTED_VALUE"""),"Тропический манго") -> Тропический манго
A195: =IFERROR(__xludf.DUMMYFUNCTION("""COMPUTED_VALUE"""),"Арбуз Малина ") -> Арбуз Малина | B195: =IFERROR(__xludf.DUMMYFUNCTION("""COMPUTED_VALUE"""),"Банан Кокос ") -> Банан Кокос | C195: =IFERROR(__xludf.DUMMYFUNCTION("""COMPUTED_VALUE"""),"Барбарисовый Энергетик ") -> Барбарисовый Энергетик | D195: =IFERROR(__xludf.DUMMYFUNCTION("""COMPUTED_VALUE"""),"Виноградный Энергетик") -> Виноградный Энергетик | E195: =IFERROR(__xludf.DUMMYFUNCTION("""COMPUTED_VALUE"""),"Гранат Клубника ") -> Гранат Клубника | F195: =IFERROR(__xludf.DUMMYFUNCTION("""COMPUTED_VALUE"""),"Гранат Смородина ") -> Гранат Смородина | G195: =IFERROR(__xludf.DUMMYFUNCTION("""COMPUTED_VALUE"""),"Грейпфрутовый Швепс ") -> Грейпфрутовый Швепс | H195: =IFERROR(__xludf.DUMMYFUNCTION("""COMPUTED_VALUE"""),"Земляника Драгонфрут ") -> Земляника Драгонфрут | I195: =IFERROR(__xludf.DUMMYFUNCTION("""COMPUTED_VALUE"""),"Киви Личи ") -> Киви Личи | J195: =IFERROR(__xludf.DUMMYFUNCTION("""COMPUTED_VALUE"""),"Киви Маракуйя Гуава ") -> Киви Маракуйя Гуава | K195: =IFERROR(__xludf.DUMMYFUNCTION("""COMPUTED_VALUE"""),"Клубника Банан ") -> Клубника Банан | L195: =IFERROR(__xludf.DUMMYFUNCTION("""COMPUTED_VALUE"""),"Клубника Вишня ") -> Клубника Вишня | M195: =IFERROR(__xludf.DUMMYFUNCTION("""COMPUTED_VALUE"""),"Клубника Земляника ") -> Клубника Земляника | N195: =IFERROR(__xludf.DUMMYFUNCTION("""COMPUTED_VALUE"""),"Клубничный Мохито ") -> Клубничный Мохито | O195: =IFERROR(__xludf.DUMMYFUNCTION("""COMPUTED_VALUE"""),"Манго Грейпфрут ") -> Манго Грейпфрут | P195: =IFERROR(__xludf.DUMMYFUNCTION("""COMPUTED_VALUE"""),"Манго Персик Личи ") -> Манго Персик Личи | Q195: =IFERROR(__xludf.DUMMYFUNCTION("""COMPUTED_VALUE"""),"Персик Бабл Гам ") -> Персик Бабл Гам | R195: =IFERROR(__xludf.DUMMYFUNCTION("""COMPUTED_VALUE"""),"Садовые Ягоды ") -> Садовые Ягоды | S195: =IFERROR(__xludf.DUMMYFUNCTION("""COMPUTED_VALUE"""),"Скитлс Лимон Лайм 2") -> Скитлс Лимон Лайм 2 | T195: =IFERROR(__xludf.DUMMYFUNCTION("""COMPUTED_VALUE"""),"Смородина Мармелад 1") -> Смородина Мармелад 1 | U195: =IFERROR(__xludf.DUMMYFUNCTION("""COMPUTED_VALUE"""),"Темная Вишня 1") -> Темная Вишня 1 | V195: =IFERROR(__xludf.DUMMYFUNCTION("""COMPUTED_VALUE"""),"Фруктовые Пластинки 1") -> Фруктовые Пластинки 1 | W195: =IFERROR(__xludf.DUMMYFUNCTION("""COMPUTED_VALUE"""),"Черника Ежевика 1") -> Черника Ежевика 1 | X195: =IFERROR(__xludf.DUMMYFUNCTION("""COMPUTED_VALUE"""),"Черника Малина 1") -> Черника Малина 1 | Y195: =IFERROR(__xludf.DUMMYFUNCTION("""COMPUTED_VALUE"""),"Черника Мята 2") -> Черника Мята 2 | Z195: =IFERROR(__xludf.DUMMYFUNCTION("""COMPUTED_VALUE"""),"Яблоко Виноград 2") -> Яблоко Виноград 2 | AA195: =IFERROR(__xludf.DUMMYFUNCTION("""COMPUTED_VALUE"""),"Яблоко Малина 4") -> Яблоко Малина 4
A196: =IFERROR(__xludf.DUMMYFUNCTION("""COMPUTED_VALUE"""),"Смородина холс") -> Смородина холс | B196: =IFERROR(__xludf.DUMMYFUNCTION("""COMPUTED_VALUE"""),"Тропические фрукты") -> Тропические фрукты | C196: =IFERROR(__xludf.DUMMYFUNCTION("""COMPUTED_VALUE"""),"Черничная конфета") -> Черничная конфета | D196: =IFERROR(__xludf.DUMMYFUNCTION("""COMPUTED_VALUE"""),"Яблоко вишня") -> Яблоко вишня | E196: =IFERROR(__xludf.DUMMYFUNCTION("""COMPUTED_VALUE"""),"Виноград мята") -> Виноград мята | F196: =IFERROR(__xludf.DUMMYFUNCTION("""COMPUTED_VALUE"""),"Виноград холс") -> Виноград холс | G196: =IFERROR(__xludf.DUMMYFUNCTION("""COMPUTED_VALUE"""),"Грейпфрутовый лимонад") -> Грейпфрутовый лимонад | H196: =IFERROR(__xludf.DUMMYFUNCTION("""COMPUTED_VALUE"""),"Дыня банан") -> Дыня банан | I196: =IFERROR(__xludf.DUMMYFUNCTION("""COMPUTED_VALUE"""),"Ежевичный лимонад") -> Ежевичный лимонад | J196: =IFERROR(__xludf.DUMMYFUNCTION("""COMPUTED_VALUE"""),"Земляничная конфета ") -> Земляничная конфета | K196: =IFERROR(__xludf.DUMMYFUNCTION("""COMPUTED_VALUE"""),"Ананас манго ") -> Ананас манго | L196: =IFERROR(__xludf.DUMMYFUNCTION("""COMPUTED_VALUE"""),"Жвачка черника мята ") -> Жвачка черника мята | M196: =IFERROR(__xludf.DUMMYFUNCTION("""COMPUTED_VALUE"""),"Зеленый манго") -> Зеленый манго | N196: =IFERROR(__xludf.DUMMYFUNCTION("""COMPUTED_VALUE"""),"Клюква брусника") -> Клюква брусника | O196: =IFERROR(__xludf.DUMMYFUNCTION("""COMPUTED_VALUE"""),"Апельсин ") -> Апельсин | P196: =IFERROR(__xludf.DUMMYFUNCTION("""COMPUTED_VALUE"""),"Кокос малина") -> Кокос малина | Q196: =IFERROR(__xludf.DUMMYFUNCTION("""COMPUTED_VALUE"""),"Лимонные черви") -> Лимонные черви | R196: =IFERROR(__xludf.DUMMYFUNCTION("""COMPUTED_VALUE"""),"Малиновый лимонад") -> Малиновый лимонад | S196: =IFERROR(__xludf.DUMMYFUNCTION("""COMPUTED_VALUE"""),"Смородина малина") -> Смородина малина
A197: =IFERROR(__xludf.DUMMYFUNCTION("""COMPUTED_VALUE"""),"Кислый малиново-грейпфрутовый швепс") -> Кислый малиново-грейпфрутовый швепс | B197: =IFERROR(__xludf.DUMMYFUNCTION("""COMPUTED_VALUE"""),"Ананас апельсин") -> Ананас апельсин | C197: =IFERROR(__xludf.DUMMYFUNCTION("""COMPUTED_VALUE"""),"Пинаколада") -> Пинаколада | D197: =IFERROR(__xludf.DUMMYFUNCTION("""COMPUTED_VALUE"""),"Мятный бабл гам") -> Мятный бабл гам | E197: =IFERROR(__xludf.DUMMYFUNCTION("""COMPUTED_VALUE"""),"Мянго драгонфрут") -> Мянго драгонфрут | F197: =IFERROR(__xludf.DUMMYFUNCTION("""COMPUTED_VALUE"""),"Клубничная фанта") -> Клубничная фанта | G197: =IFERROR(__xludf.DUMMYFUNCTION("""COMPUTED_VALUE"""),"Клубничная арбуз") -> Клубничная арбуз | H197: =IFERROR(__xludf.DUMMYFUNCTION("""COMPUTED_VALUE"""),"Кислый скитлс") -> Кислый скитлс | I197: =IFERROR(__xludf.DUMMYFUNCTION("""COMPUTED_VALUE"""),"Кислый лайм арбуз") -> Кислый лайм арбуз | J197: =IFERROR(__xludf.DUMMYFUNCTION("""COMPUTED_VALUE"""),"Тропический банан") -> Тропический банан | K197: =IFERROR(__xludf.DUMMYFUNCTION("""COMPUTED_VALUE"""),"Яблочный энергетик") -> Яблочный энергетик | L197: =IFERROR(__xludf.DUMMYFUNCTION("""COMPUTED_VALUE"""),"Барбарисовый лимонад") -> Барбарисовый лимонад | M197: =IFERROR(__xludf.DUMMYFUNCTION("""COMPUTED_VALUE"""),"Лимонад виноград вишня") -> Лимонад виноград вишня | N197: =IFERROR(__xludf.DUMMYFUNCTION("""COMPUTED_VALUE"""),"Розовый лимонад") -> Розовый лимонад | O197: =IFERROR(__xludf.DUMMYFUNCTION("""COMPUTED_VALUE"""),"Двойной манго") -> Двойной манго | P197: =IFERROR(__xludf.DUMMYFUNCTION("""COMPUTED_VALUE"""),"Лесные ягоды ") -> Лесные ягоды | Q197: =IFERROR(__xludf.DUMMYFUNCTION("""COMPUTED_VALUE"""),"Ежевика малина ") -> Ежевика малина | R197: =IFERROR(__xludf.DUMMYFUNCTION("""COMPUTED_VALUE"""),"Смородиновый лимонад") -> Смородиновый лимонад | S197: =IFERROR(__xludf.DUMMYFUNCTION("""COMPUTED_VALUE"""),"Кола вишня") -> Кола вишня | T197: =IFERROR(__xludf.DUMMYFUNCTION("""COMPUTED_VALUE"""),"Манго арбуз") -> Манго арбуз | U197: =IFERROR(__xludf.DUMMYFUNCTION("""COMPUTED_VALUE"""),"Алоэ виноград") -> Алоэ виноград | V197: =IFERROR(__xludf.DUMMYFUNCTION("""COMPUTED_VALUE"""),"Банан клубника") -> Банан клубника | W197: =IFERROR(__xludf.DUMMYFUNCTION("""COMPUTED_VALUE"""),"Малиновый мармелад") -> Малиновый мармелад | X197: =IFERROR(__xludf.DUMMYFUNCTION("""COMPUTED_VALUE"""),"Клубника киви") -> Клубника киви | Y197: =IFERROR(__xludf.DUMMYFUNCTION("""COMPUTED_VALUE"""),"Клюква лайм") -> Клюква лайм | Z197: =IFERROR(__xludf.DUMMYFUNCTION("""COMPUTED_VALUE"""),"Гуава ананас") -> Гуава ананас | AA197: =IFERROR(__xludf.DUMMYFUNCTION("""COMPUTED_VALUE"""),"Морс") -> Морс | AB197: =IFERROR(__xludf.DUMMYFUNCTION("""COMPUTED_VALUE"""),"Красный апельсин") -> Красный апельсин | AC197: =IFERROR(__xludf.DUMMYFUNCTION("""COMPUTED_VALUE"""),"Арбузная жвачка") -> Арбузная жвачка | AD197: =IFERROR(__xludf.DUMMYFUNCTION("""COMPUTED_VALUE"""),"Смородина Виноград") -> Смородина Виноград | AE197: =IFERROR(__xludf.DUMMYFUNCTION("""COMPUTED_VALUE"""),"Гранатовая Мармелад") -> Гранатовая Мармелад | AF197: =IFERROR(__xludf.DUMMYFUNCTION("""COMPUTED_VALUE"""),"Яблоко Киви") -> Яблоко Киви | AG197: =IFERROR(__xludf.DUMMYFUNCTION("""COMPUTED_VALUE"""),"Клубника Ежевика") -> Клубника Ежевика | AH197: =IFERROR(__xludf.DUMMYFUNCTION("""COMPUTED_VALUE"""),"Клубничный Коктейль") -> Клубничный Коктейль | AI197: =IFERROR(__xludf.DUMMYFUNCTION("""COMPUTED_VALUE"""),"Клюква Земляника ") -> Клюква Земляника | AJ197: =IFERROR(__xludf.DUMMYFUNCTION("""COMPUTED_VALUE"""),"Какос Дыня") -> Какос Дыня | AK197: =IFERROR(__xludf.DUMMYFUNCTION("""COMPUTED_VALUE"""),"Маракуйя мандарин") -> Маракуйя мандарин | AL197: =IFERROR(__xludf.DUMMYFUNCTION("""COMPUTED_VALUE"""),"Персик кактус") -> Персик кактус | AM197: =IFERROR(__xludf.DUMMYFUNCTION("""COMPUTED_VALUE"""),"Спрайт") -> Спрайт | AN197: =IFERROR(__xludf.DUMMYFUNCTION("""COMPUTED_VALUE"""),"Черничная фанта") -> Черничная фанта | AO197: =IFERROR(__xludf.DUMMYFUNCTION("""COMPUTED_VALUE"""),"Ягодная жвачка") -> Ягодная жвачка | AP197: =IFERROR(__xludf.DUMMYFUNCTION("""COMPUTED_VALUE"""),"Ягодный энергетик") -> Ягодный энергетик | AQ197: =IFERROR(__xludf.DUMMYFUNCTION("""COMPUTED_VALUE"""),"Ягодный пунш ") -> Ягодный пунш | AR197: =IFERROR(__xludf.DUMMYFUNCTION("""COMPUTED_VALUE"""),"Виноградный холс") -> Виноградный холс | AS197: =IFERROR(__xludf.DUMMYFUNCTION("""COMPUTED_VALUE"""),"Грейпфрут смородина") -> Грейпфрут смородина | AT197: =IFERROR(__xludf.DUMMYFUNCTION("""COMPUTED_VALUE"""),"Дыня персик") -> Дыня персик | AU197: =IFERROR(__xludf.DUMMYFUNCTION("""COMPUTED_VALUE"""),"Земляника виноград") -> Земляника виноград | AV197: =IFERROR(__xludf.DUMMYFUNCTION("""COMPUTED_VALUE"""),"Киви маракуйя гуава") -> Киви маракуйя гуава | AW197: =IFERROR(__xludf.DUMMYFUNCTION("""COMPUTED_VALUE"""),"Кислые вишнёвые червячки") -> Кислые вишнёвые червячки | AX197: =IFERROR(__xludf.DUMMYFUNCTION("""COMPUTED_VALUE"""),"Кислые чернично-малиновое червячки") -> Кислые чернично-малиновое червячки
A198: =IFERROR(__xludf.DUMMYFUNCTION("""COMPUTED_VALUE"""),"Ананас киви") -> Ананас киви | B198: =IFERROR(__xludf.DUMMYFUNCTION("""COMPUTED_VALUE"""),"Арбузный смузи") -> Арбузный смузи | C198: =IFERROR(__xludf.DUMMYFUNCTION("""COMPUTED_VALUE"""),"Виноградная фанта") -> Виноградная фанта | D198: =IFERROR(__xludf.DUMMYFUNCTION("""COMPUTED_VALUE"""),"Вишневый морс") -> Вишневый морс | E198: =IFERROR(__xludf.DUMMYFUNCTION("""COMPUTED_VALUE"""),"Гранатовый мармелад") -> Гранатовый мармелад | F198: =IFERROR(__xludf.DUMMYFUNCTION("""COMPUTED_VALUE"""),"Грейпфрут киви") -> Грейпфрут киви | G198: =IFERROR(__xludf.DUMMYFUNCTION("""COMPUTED_VALUE"""),"Ежевика мята") -> Ежевика мята | H198: =IFERROR(__xludf.DUMMYFUNCTION("""COMPUTED_VALUE"""),"Киви манго") -> Киви манго | I198: =IFERROR(__xludf.DUMMYFUNCTION("""COMPUTED_VALUE"""),"Клубника манго") -> Клубника манго | J198: =IFERROR(__xludf.DUMMYFUNCTION("""COMPUTED_VALUE"""),"черника грейфрут ") -> черника грейфрут | K198: =IFERROR(__xludf.DUMMYFUNCTION("""COMPUTED_VALUE"""),"Малина лайм") -> Малина лайм | L198: =IFERROR(__xludf.DUMMYFUNCTION("""COMPUTED_VALUE"""),"Манго арбуз ") -> Манго арбуз | M198: =IFERROR(__xludf.DUMMYFUNCTION("""COMPUTED_VALUE"""),"Малиновый чай с жасмином") -> Малиновый чай с жасмином | N198: =IFERROR(__xludf.DUMMYFUNCTION("""COMPUTED_VALUE"""),"малина апельсин ") -> малина апельсин | O198: =IFERROR(__xludf.DUMMYFUNCTION("""COMPUTED_VALUE"""),"Манго апельсин") -> Манго апельсин | P198: =IFERROR(__xludf.DUMMYFUNCTION("""COMPUTED_VALUE"""),"Ред булл") -> Ред булл | Q198: =IFERROR(__xludf.DUMMYFUNCTION("""COMPUTED_VALUE"""),"Спрайт") -> Спрайт | R198: =IFERROR(__xludf.DUMMYFUNCTION("""COMPUTED_VALUE"""),"ананас клюква ") -> ананас клюква | S198: =IFERROR(__xludf.DUMMYFUNCTION("""COMPUTED_VALUE"""),"Тархун") -> Тархун | T198: =IFERROR(__xludf.DUMMYFUNCTION("""COMPUTED_VALUE"""),"алоэ Виноград ") -> алоэ Виноград | U198: =IFERROR(__xludf.DUMMYFUNCTION("""COMPUTED_VALUE"""),"Фруктовая жвачка") -> Фруктовая жвачка | V198: =IFERROR(__xludf.DUMMYFUNCTION("""COMPUTED_VALUE"""),"Холодная кола") -> Холодная кола | W198: =IFERROR(__xludf.DUMMYFUNCTION("""COMPUTED_VALUE"""),"Черная смородина клюква") -> Черная смородина клюква | X198: =IFERROR(__xludf.DUMMYFUNCTION("""COMPUTED_VALUE"""),"Черника арбуз") -> Черника арбуз | Y198: =IFERROR(__xludf.DUMMYFUNCTION("""COMPUTED_VALUE"""),"Яблоко черника") -> Яблоко черника
